Workbook

Sheet Dashboard
A1: 📊 DASHBOARD KẾT QUẢ KINH DOANH Q2/2026
A2: Dữ liệu cập nhật tự động từ Sheet1 - Table1
A4: 📈 TỔNG SỐ DN | C4: 📊 ĐÃ CÔNG BỐ | F4: ✅ DN CÓ LÃI | H4: ❌ DN BỊ LỖ | J4: 📊 TỶ LỆ CÓ LÃI
A5: =COUNTA(INDEX(Sheet4!$A:$AG,0,_xlfn.XMATCH("Mã",Sheet4!$1:$1)))-1 -> 1593 | C5: {=_xlfn.LET( _xlpm.colDTT,_xlfn.XMATCH("*Doanh thu thuần*Q2*2026*",Sheet4!$1:$1,2), _xlpm.colTNL,_xlfn.XMATCH("*Thu nhập lãi thuần*Quý: 2*2026*",Sheet4!$1:$1,2), _xlpm.dttData,INDEX(Sheet4!$A:$AG,0,_xlpm.colDTT), _xlpm.tnlData,INDEX(Sheet4!$A:$AG,0,_xlpm.colTNL), SUMPRODUCT((_xlpm.dttData<>"")*(_xlpm.dttData<>0)*(ROW(_xlpm.dttData)>1)*1)+SUMPRODUCT((OR(_xlpm.dttData="",_xlpm.dttData=0))*(_xlpm.tnlData<>"")*(_xlpm.tnlData<>0)*(ROW(_xlpm.tnlData)>1)*1) )} -> 405 | F5: {=_xlfn.LET( _xlpm.colLNST,_xlfn.XMATCH("*Lợi nhuận sau thuế*Q2*2026*",Sheet4!$1:$1,2), _xlpm.lnstData,INDEX(Sheet4!$A:$AG,0,_xlpm.colLNST), SUMPRODUCT((_xlpm.lnstData>0)*(ROW(_xlpm.lnstData)>1)*1) )} -> 362 | H5: {=_xlfn.LET( _xlpm.colLNST,_xlfn.XMATCH("*Lợi nhuận sau thuế*Q2*2026*",Sheet4!$1:$1,2), _xlpm.lnstData,INDEX(Sheet4!$A:$AG,0,_xlpm.colLNST), SUMPRODUCT((_xlpm.lnstData<0)*(ROW(_xlpm.lnstData)>1)*1) )} -> 47 | J5: {=_xlfn.LET( _xlpm.colLNST,_xlfn.XMATCH("*Lợi nhuận sau thuế*Q2*2026*",Sheet4!$1:$1,2), _xlpm.lnstData,INDEX(Sheet4!$A:$AG,0,_xlpm.colLNST), _xlpm.coLai,SUMPRODUCT((_xlpm.lnstData>0)*(ROW(_xlpm.lnstData)>1)*1), _xlpm.biLo,SUMPRODUCT((_xlpm.lnstData<0)*(ROW(_xlpm.lnstData)>1)*1), _xlpm.coLai/(_xlpm.coLai+_xlpm.biLo) )} -> 0.88508557
A7: 📊 THỐNG KÊ THEO PHÂN NGÀNH (ICB L1)
A8: Phân ngành | B8: Số DN | C8: Đã công bố | D8: Tổng DT Q2 (tỷ) | E8: Tổng LNST Q2 (tỷ) | F8: DT (YoY %) | G8: LNST (YoY %)
A9: Công nghiệp | B9: =_xlfn.LET( _xlpm.colNganh,_xlfn.XMATCH("*ICB L1*",Sheet4!$1:$1,2), _xlpm.nganhData,INDEX(Sheet4!$2:$1605,0,_xlpm.colNganh), COUNTIF(_xlpm.nganhData,$A9) ) -> 572 | C9: {=_xlfn.LET( _xlpm.colNganh,_xlfn.XMATCH("*ICB L1*",Sheet4!$1:$1,2), _xlpm.colDTT,_xlfn.XMATCH("*Doanh thu thuần*Q2*2026*",Sheet4!$1:$1,2), _xlpm.colTNL,_xlfn.XMATCH("*Thu nhập lãi thuần*Quý: 2*2026*",Sheet4!$1:$1,2), _xlpm.nganhData,INDEX(Sheet4!$2:$1605,0,_xlpm.colNganh), _xlpm.dttData,INDEX(Sheet4!$2:$1605,0,_xlpm.colDTT), _xlpm.tnlData,INDEX(Sheet4!$2:$1605,0,_xlpm.colTNL), IF($A9="Ngân hàng", SUMPRODUCT((_xlpm.nganhData=$A9)*(_xlpm.tnlData<>"")*(_xlpm.tnlData<>0)*1), SUMPRODUCT((_xlpm.nganhData=$A9)*(_xlpm.dttData<>"")*(_xlpm.dttData<>0)*1) ) )} -> 114 | D9: {=_xlfn.LET( _xlpm.colNganh,_xlfn.XMATCH("*ICB L1*",Sheet4!$1:$1,2), _xlpm.colDTT,_xlfn.XMATCH("*Doanh thu thuần*Q2*2026*",Sheet4!$1:$1,2), _xlpm.colTNL,_xlfn.XMATCH("*Thu nhập lãi thuần*Quý: 2*2026*",Sheet4!$1:$1,2), _xlpm.nganhData,INDEX(Sheet4!$2:$1605,0,_xlpm.colNganh), _xlpm.dttData,INDEX(Sheet4!$2:$1605,0,_xlpm.colDTT), _xlpm.tnlData,INDEX(Sheet4!$2:$1605,0,_xlpm.colTNL), IF($A9="Ngân hàng", SUMPRODUCT((_xlpm.nganhData=$A9)*(_xlpm.tnlData))/1000000000, SUMPRODUCT((_xlpm.nganhData=$A9)*(_xlpm.dttData))/1000000000 ) )} -> 33929.182 | E9: {=_xlfn.LET( _xlpm.colNganh,_xlfn.XMATCH("*ICB L1*",Sheet4!$1:$1,2), _xlpm.colLNST,_xlfn.XMATCH("*Lợi nhuận sau thuế*Q2*2026*",Sheet4!$1:$1,2), _xlpm.nganhData,INDEX(Sheet4!$2:$1605,0,_xlpm.colNganh), _xlpm.lnstData,INDEX(Sheet4!$2:$1605,0,_xlpm.colLNST), SUMPRODUCT((_xlpm.nganhData=$A9)*(_xlpm.lnstData))/1000000000 )} -> 3439.4574 | F9: {=_xlfn.LET( _xlpm.colNganh,_xlfn.XMATCH("*ICB L1*",Sheet4!$1:$1,2), _xlpm.colDTT,_xlfn.XMATCH("*Doanh thu thuần*Q2*2026*",Sheet4!$1:$1,2), _xlpm.colTNL26,_xlfn.XMATCH("*Thu nhập lãi thuần*Quý: 2*2026*",Sheet4!$1:$1,2), _xlpm.colTNL25,_xlfn.XMATCH("*Thu nhập lãi thuần*Q2*2025*",Sheet4!$1:$1,2), _xlpm.colTTDTT,_xlfn.XMATCH("*Tăng trưởng doanh thu thuần (YoY) (Quý*",Sheet4!$1:$1,2), _xlpm.nganhData,INDEX(Sheet4!$2:$1605,0,_xlpm.colNganh), _xlpm.dttData,INDEX(Sheet4!$2:$1605,0,_xlpm.colDTT), _xlpm.tnl26Data,INDEX(Sheet4!$2:$1605,0,_xlpm.colTNL26), _xlpm.tnl25Data,INDEX(Sheet4!$2:$1605,0,_xlpm.colTNL25), _xlpm.ttdttData,INDEX(Sheet4!$2:$1605,0,_xlpm.colTTDTT), IF($A9="Ngân hàng", _xlfn.LET( _xlpm.sumTNL26,SUMPRODUCT((_xlpm.nganhData=$A9)*(_xlpm.tnl26Data<>0)*(_xlpm.tnl26Data)), _xlpm.sumTNL25Match,SUMPRODUCT((_xlpm.nganhData=$A9)*(_xlpm.tnl26Data<>0)*(_xlpm.tnl25Data)), IF(OR(_xlpm.sumTNL26=0,_xlpm.sumTNL25Match=0),"-",_xlpm.sumTNL26/_xlpm.sumTNL25Match-1) ), _xlfn.LET( _xlpm.tongDT,SUMPRODUCT((_xlpm.nganhData=$A9)*(_xlpm.dttData)), _xlpm.tongTT,SUMPRODUCT((_xlpm.nganhData=$A9)*(_xlpm.dttData)*(_xlpm.ttdttData)), IF(_xlpm.tongDT=0,"-",_xlpm.tongTT/_xlpm.tongDT) ) ) )} -> 0.33255605 | G9: {=_xlfn.LET( _xlpm.colNganh,_xlfn.XMATCH("*ICB L1*",Sheet4!$1:$1,2), _xlpm.colLNST,_xlfn.XMATCH("*Lợi nhuận sau thuế*Q2*2026*",Sheet4!$1:$1,2), _xlpm.colTTLNST,_xlfn.XMATCH("*Tăng trưởng lợi nhuận sau thuế (YoY) (Quý*",Sheet4!$1:$1,2), _xlpm.nganhData,INDEX(Sheet4!$2:$1605,0,_xlpm.colNganh), _xlpm.lnstData,INDEX(Sheet4!$2:$1605,0,_xlpm.colLNST), _xlpm.ttlnstData,INDEX(Sheet4!$2:$1605,0,_xlpm.colTTLNST), _xlfn.LET( _xlpm.tongLNST,SUMPRODUCT((_xlpm.nganhData=$A9)*(_xlpm.lnstData)), _xlpm.tongTT,SUMPRODUCT((_xlpm.nganhData=$A9)*(_xlpm.lnstData)*(_xlpm.ttlnstData)), IF(_xlpm.tongLNST=0,"-",_xlpm.tongTT/_xlpm.tongLNST) ) )} -> 3.9424359
A10: Công nghệ Thông tin | B10: =_xlfn.LET( _xlpm.colNganh,_xlfn.XMATCH("*ICB L1*",Sheet4!$1:$1,2), _xlpm.nganhData,INDEX(Sheet4!$2:$1605,0,_xlpm.colNganh), COUNTIF(_xlpm.nganhData,$A10) ) -> 27 | C10: {=_xlfn.LET( _xlpm.colNganh,_xlfn.XMATCH("*ICB L1*",Sheet4!$1:$1,2), _xlpm.colDTT,_xlfn.XMATCH("*Doanh thu thuần*Q2*2026*",Sheet4!$1:$1,2), _xlpm.colTNL,_xlfn.XMATCH("*Thu nhập lãi thuần*Quý: 2*2026*",Sheet4!$1:$1,2), _xlpm.nganhData,INDEX(Sheet4!$2:$1605,0,_xlpm.colNganh), _xlpm.dttData,INDEX(Sheet4!$2:$1605,0,_xlpm.colDTT), _xlpm.tnlData,INDEX(Sheet4!$2:$1605,0,_xlpm.colTNL), IF($A10="Ngân hàng", SUMPRODUCT((_xlpm.nganhData=$A10)*(_xlpm.tnlData<>"")*(_xlpm.tnlData<>0)*1), SUMPRODUCT((_xlpm.nganhData=$A10)*(_xlpm.dttData<>"")*(_xlpm.dttData<>0)*1) ) )} -> 4 | D10: {=_xlfn.LET( _xlpm.colNganh,_xlfn.XMATCH("*ICB L1*",Sheet4!$1:$1,2), _xlpm.colDTT,_xlfn.XMATCH("*Doanh thu thuần*Q2*2026*",Sheet4!$1:$1,2), _xlpm.colTNL,_xlfn.XMATCH("*Thu nhập lãi thuần*Quý: 2*2026*",Sheet4!$1:$1,2), _xlpm.nganhData,INDEX(Sheet4!$2:$1605,0,_xlpm.colNganh), _xlpm.dttData,INDEX(Sheet4!$2:$1605,0,_xlpm.colDTT), _xlpm.tnlData,INDEX(Sheet4!$2:$1605,0,_xlpm.colTNL), IF($A10="Ngân hàng", SUMPRODUCT((_xlpm.nganhData=$A10)*(_xlpm.tnlData))/1000000000, SUMPRODUCT((_xlpm.nganhData=$A10)*(_xlpm.dttData))/1000000000 ) )} -> 230.21316 | E10: {=_xlfn.LET( _xlpm.colNganh,_xlfn.XMATCH("*ICB L1*",Sheet4!$1:$1,2), _xlpm.colLNST,_xlfn.XMATCH("*Lợi nhuận sau thuế*Q2*2026*",Sheet4!$1:$1,2), _xlpm.nganhData,INDEX(Sheet4!$2:$1605,0,_xlpm.colNganh), _xlpm.lnstData,INDEX(Sheet4!$2:$1605,0,_xlpm.colLNST), SUMPRODUCT((_xlpm.nganhData=$A10)*(_xlpm.lnstData))/1000000000 )} -> 15.117617 | F10: {=_xlfn.LET( _xlpm.colNganh,_xlfn.XMATCH("*ICB L1*",Sheet4!$1:$1,2), _xlpm.colDTT,_xlfn.XMATCH("*Doanh thu thuần*Q2*2026*",Sheet4!$1:$1,2), _xlpm.colTNL26,_xlfn.XMATCH("*Thu nhập lãi thuần*Quý: 2*2026*",Sheet4!$1:$1,2), _xlpm.colTNL25,_xlfn.XMATCH("*Thu nhập lãi thuần*Q2*2025*",Sheet4!$1:$1,2), _xlpm.colTTDTT,_xlfn.XMATCH("*Tăng trưởng doanh thu thuần (YoY) (Quý*",Sheet4!$1:$1,2), _xlpm.nganhData,INDEX(Sheet4!$2:$1605,0,_xlpm.colNganh), _xlpm.dttData,INDEX(Sheet4!$2:$1605,0,_xlpm.colDTT), _xlpm.tnl26Data,INDEX(Sheet4!$2:$1605,0,_xlpm.colTNL26), _xlpm.tnl25Data,INDEX(Sheet4!$2:$1605,0,_xlpm.colTNL25), _xlpm.ttdttData,INDEX(Sheet4!$2:$1605,0,_xlpm.colTTDTT), IF($A10="Ngân hàng", _xlfn.LET( _xlpm.sumTNL26,SUMPRODUCT((_xlpm.nganhData=$A10)*(_xlpm.tnl26Data<>0)*(_xlpm.tnl26Data)), _xlpm.sumTNL25Match,SUMPRODUCT((_xlpm.nganhData=$A10)*(_xlpm.tnl26Data<>0)*(_xlpm.tnl25Data)), IF(OR(_xlpm.sumTNL26=0,_xlpm.sumTNL25Match=0),"-",_xlpm.sumTNL26/_xlpm.sumTNL25Match-1) ), _xlfn.LET( _xlpm.tongDT,SUMPRODUCT((_xlpm.nganhData=$A10)*(_xlpm.dttData)), _xlpm.tongTT,SUMPRODUCT((_xlpm.nganhData=$A10)*(_xlpm.dttData)*(_xlpm.ttdttData)), IF(_xlpm.tongDT=0,"-",_xlpm.tongTT/_xlpm.tongDT) ) ) )} -> 1.0373207 | G10: {=_xlfn.LET( _xlpm.colNganh,_xlfn.XMATCH("*ICB L1*",Sheet4!$1:$1,2), _xlpm.colLNST,_xlfn.XMATCH("*Lợi nhuận sau thuế*Q2*2026*",Sheet4!$1:$1,2), _xlpm.colTTLNST,_xlfn.XMATCH("*Tăng trưởng lợi nhuận sau thuế (YoY) (Quý*",Sheet4!$1:$1,2), _xlpm.nganhData,INDEX(Sheet4!$2:$1605,0,_xlpm.colNganh), _xlpm.lnstData,INDEX(Sheet4!$2:$1605,0,_xlpm.colLNST), _xlpm.ttlnstData,INDEX(Sheet4!$2:$1605,0,_xlpm.colTTLNST), _xlfn.LET( _xlpm.tongLNST,SUMPRODUCT((_xlpm.nganhData=$A10)*(_xlpm.lnstData)), _xlpm.tongTT,SUMPRODUCT((_xlpm.nganhData=$A10)*(_xlpm.lnstData)*(_xlpm.ttlnstData)), IF(_xlpm.tongLNST=0,"-",_xlpm.tongTT/_xlpm.tongLNST) ) )} -> 13.232936
A11: Dược phẩm và Y tế | B11: =_xlfn.LET( _xlpm.colNganh,_xlfn.XMATCH("*ICB L1*",Sheet4!$1:$1,2), _xlpm.nganhData,INDEX(Sheet4!$2:$1605,0,_xlpm.colNganh), COUNTIF(_xlpm.nganhData,$A11) ) -> 65 | C11: {=_xlfn.LET( _xlpm.colNganh,_xlfn.XMATCH("*ICB L1*",Sheet4!$1:$1,2), _xlpm.colDTT,_xlfn.XMATCH("*Doanh thu thuần*Q2*2026*",Sheet4!$1:$1,2), _xlpm.colTNL,_xlfn.XMATCH("*Thu nhập lãi thuần*Quý: 2*2026*",Sheet4!$1:$1,2), _xlpm.nganhData,INDEX(Sheet4!$2:$1605,0,_xlpm.colNganh), _xlpm.dttData,INDEX(Sheet4!$2:$1605,0,_xlpm.colDTT), _xlpm.tnlData,INDEX(Sheet4!$2:$1605,0,_xlpm.colTNL), IF($A11="Ngân hàng", SUMPRODUCT((_xlpm.nganhData=$A11)*(_xlpm.tnlData<>"")*(_xlpm.tnlData<>0)*1), SUMPRODUCT((_xlpm.nganhData=$A11)*(_xlpm.dttData<>"")*(_xlpm.dttData<>0)*1) ) )} -> 15 | D11: {=_xlfn.LET( _xlpm.colNganh,_xlfn.XMATCH("*ICB L1*",Sheet4!$1:$1,2), _xlpm.colDTT,_xlfn.XMATCH("*Doanh thu thuần*Q2*2026*",Sheet4!$1:$1,2), _xlpm.colTNL,_xlfn.XMATCH("*Thu nhập lãi thuần*Quý: 2*2026*",Sheet4!$1:$1,2), _xlpm.nganhData,INDEX(Sheet4!$2:$1605,0,_xlpm.colNganh), _xlpm.dttData,INDEX(Sheet4!$2:$1605,0,_xlpm.colDTT), _xlpm.tnlData,INDEX(Sheet4!$2:$1605,0,_xlpm.colTNL), IF($A11="Ngân hàng", SUMPRODUCT((_xlpm.nganhData=$A11)*(_xlpm.tnlData))/1000000000, SUMPRODUCT((_xlpm.nganhData=$A11)*(_xlpm.dttData))/1000000000 ) )} -> 4197.1007 | E11: {=_xlfn.LET( _xlpm.colNganh,_xlfn.XMATCH("*ICB L1*",Sheet4!$1:$1,2), _xlpm.colLNST,_xlfn.XMATCH("*Lợi nhuận sau thuế*Q2*2026*",Sheet4!$1:$1,2), _xlpm.nganhData,INDEX(Sheet4!$2:$1605,0,_xlpm.colNganh), _xlpm.lnstData,INDEX(Sheet4!$2:$1605,0,_xlpm.colLNST), SUMPRODUCT((_xlpm.nganhData=$A11)*(_xlpm.lnstData))/1000000000 )} -> 546.57342 | F11: {=_xlfn.LET( _xlpm.colNganh,_xlfn.XMATCH("*ICB L1*",Sheet4!$1:$1,2), _xlpm.colDTT,_xlfn.XMATCH("*Doanh thu thuần*Q2*2026*",Sheet4!$1:$1,2), _xlpm.colTNL26,_xlfn.XMATCH("*Thu nhập lãi thuần*Quý: 2*2026*",Sheet4!$1:$1,2), _xlpm.colTNL25,_xlfn.XMATCH("*Thu nhập lãi thuần*Q2*2025*",Sheet4!$1:$1,2), _xlpm.colTTDTT,_xlfn.XMATCH("*Tăng trưởng doanh thu thuần (YoY) (Quý*",Sheet4!$1:$1,2), _xlpm.nganhData,INDEX(Sheet4!$2:$1605,0,_xlpm.colNganh), _xlpm.dttData,INDEX(Sheet4!$2:$1605,0,_xlpm.colDTT), _xlpm.tnl26Data,INDEX(Sheet4!$2:$1605,0,_xlpm.colTNL26), _xlpm.tnl25Data,INDEX(Sheet4!$2:$1605,0,_xlpm.colTNL25), _xlpm.ttdttData,INDEX(Sheet4!$2:$1605,0,_xlpm.colTTDTT), IF($A11="Ngân hàng", _xlfn.LET( _xlpm.sumTNL26,SUMPRODUCT((_xlpm.nganhData=$A11)*(_xlpm.tnl26Data<>0)*(_xlpm.tnl26Data)), _xlpm.sumTNL25Match,SUMPRODUCT((_xlpm.nganhData=$A11)*(_xlpm.tnl26Data<>0)*(_xlpm.tnl25Data)), IF(OR(_xlpm.sumTNL26=0,_xlpm.sumTNL25Match=0),"-",_xlpm.sumTNL26/_xlpm.sumTNL25Match-1) ), _xlfn.LET( _xlpm.tongDT,SUMPRODUCT((_xlpm.nganhData=$A11)*(_xlpm.dttData)), _xlpm.tongTT,SUMPRODUCT((_xlpm.nganhData=$A11)*(_xlpm.dttData)*(_xlpm.ttdttData)), IF(_xlpm.tongDT=0,"-",_xlpm.tongTT/_xlpm.tongDT) ) ) )} -> 0.081299108 | G11: {=_xlfn.LET( _xlpm.colNganh,_xlfn.XMATCH("*ICB L1*",Sheet4!$1:$1,2), _xlpm.colLNST,_xlfn.XMATCH("*Lợi nhuận sau thuế*Q2*2026*",Sheet4!$1:$1,2), _xlpm.colTTLNST,_xlfn.XMATCH("*Tăng trưởng lợi nhuận sau thuế (YoY) (Quý*",Sheet4!$1:$1,2), _xlpm.nganhData,INDEX(Sheet4!$2:$1605,0,_xlpm.colNganh), _xlpm.lnstData,INDEX(Sheet4!$2:$1605,0,_xlpm.colLNST), _xlpm.ttlnstData,INDEX(Sheet4!$2:$1605,0,_xlpm.colTTLNST), _xlfn.LET( _xlpm.tongLNST,SUMPRODUCT((_xlpm.nganhData=$A11)*(_xlpm.lnstData)), _xlpm.tongTT,SUMPRODUCT((_xlpm.nganhData=$A11)*(_xlpm.lnstData)*(_xlpm.ttlnstData)), IF(_xlpm.tongLNST=0,"-",_xlpm.tongTT/_xlpm.tongLNST) ) )} -> 2.895358
A12: Dầu khí | B12: =_xlfn.LET( _xlpm.colNganh,_xlfn.XMATCH("*ICB L1*",Sheet4!$1:$1,2), _xlpm.nganhData,INDEX(Sheet4!$2:$1605,0,_xlpm.colNganh), COUNTIF(_xlpm.nganhData,$A12) ) -> 12 | C12: {=_xlfn.LET( _xlpm.colNganh,_xlfn.XMATCH("*ICB L1*",Sheet4!$1:$1,2), _xlpm.colDTT,_xlfn.XMATCH("*Doanh thu thuần*Q2*2026*",Sheet4!$1:$1,2), _xlpm.colTNL,_xlfn.XMATCH("*Thu nhập lãi thuần*Quý: 2*2026*",Sheet4!$1:$1,2), _xlpm.nganhData,INDEX(Sheet4!$2:$1605,0,_xlpm.colNganh), _xlpm.dttData,INDEX(Sheet4!$2:$1605,0,_xlpm.colDTT), _xlpm.tnlData,INDEX(Sheet4!$2:$1605,0,_xlpm.colTNL), IF($A12="Ngân hàng", SUMPRODUCT((_xlpm.nganhData=$A12)*(_xlpm.tnlData<>"")*(_xlpm.tnlData<>0)*1), SUMPRODUCT((_xlpm.nganhData=$A12)*(_xlpm.dttData<>"")*(_xlpm.dttData<>0)*1) ) )} -> 1 | D12: {=_xlfn.LET( _xlpm.colNganh,_xlfn.XMATCH("*ICB L1*",Sheet4!$1:$1,2), _xlpm.colDTT,_xlfn.XMATCH("*Doanh thu thuần*Q2*2026*",Sheet4!$1:$1,2), _xlpm.colTNL,_xlfn.XMATCH("*Thu nhập lãi thuần*Quý: 2*2026*",Sheet4!$1:$1,2), _xlpm.nganhData,INDEX(Sheet4!$2:$1605,0,_xlpm.colNganh), _xlpm.dttData,INDEX(Sheet4!$2:$1605,0,_xlpm.colDTT), _xlpm.tnlData,INDEX(Sheet4!$2:$1605,0,_xlpm.colTNL), IF($A12="Ngân hàng", SUMPRODUCT((_xlpm.nganhData=$A12)*(_xlpm.tnlData))/1000000000, SUMPRODUCT((_xlpm.nganhData=$A12)*(_xlpm.dttData))/1000000000 ) )} -> 1643.9066 | E12: {=_xlfn.LET( _xlpm.colNganh,_xlfn.XMATCH("*ICB L1*",Sheet4!$1:$1,2), _xlpm.colLNST,_xlfn.XMATCH("*Lợi nhuận sau thuế*Q2*2026*",Sheet4!$1:$1,2), _xlpm.nganhData,INDEX(Sheet4!$2:$1605,0,_xlpm.colNganh), _xlpm.lnstData,INDEX(Sheet4!$2:$1605,0,_xlpm.colLNST), SUMPRODUCT((_xlpm.nganhData=$A12)*(_xlpm.lnstData))/1000000000 )} -> 43.95777 | F12: {=_xlfn.LET( _xlpm.colNganh,_xlfn.XMATCH("*ICB L1*",Sheet4!$1:$1,2), _xlpm.colDTT,_xlfn.XMATCH("*Doanh thu thuần*Q2*2026*",Sheet4!$1:$1,2), _xlpm.colTNL26,_xlfn.XMATCH("*Thu nhập lãi thuần*Quý: 2*2026*",Sheet4!$1:$1,2), _xlpm.colTNL25,_xlfn.XMATCH("*Thu nhập lãi thuần*Q2*2025*",Sheet4!$1:$1,2), _xlpm.colTTDTT,_xlfn.XMATCH("*Tăng trưởng doanh thu thuần (YoY) (Quý*",Sheet4!$1:$1,2), _xlpm.nganhData,INDEX(Sheet4!$2:$1605,0,_xlpm.colNganh), _xlpm.dttData,INDEX(Sheet4!$2:$1605,0,_xlpm.colDTT), _xlpm.tnl26Data,INDEX(Sheet4!$2:$1605,0,_xlpm.colTNL26), _xlpm.tnl25Data,INDEX(Sheet4!$2:$1605,0,_xlpm.colTNL25), _xlpm.ttdttData,INDEX(Sheet4!$2:$1605,0,_xlpm.colTTDTT), IF($A12="Ngân hàng", _xlfn.LET( _xlpm.sumTNL26,SUMPRODUCT((_xlpm.nganhData=$A12)*(_xlpm.tnl26Data<>0)*(_xlpm.tnl26Data)), _xlpm.sumTNL25Match,SUMPRODUCT((_xlpm.nganhData=$A12)*(_xlpm.tnl26Data<>0)*(_xlpm.tnl25Data)), IF(OR(_xlpm.sumTNL26=0,_xlpm.sumTNL25Match=0),"-",_xlpm.sumTNL26/_xlpm.sumTNL25Match-1) ), _xlfn.LET( _xlpm.tongDT,SUMPRODUCT((_xlpm.nganhData=$A12)*(_xlpm.dttData)), _xlpm.tongTT,SUMPRODUCT((_xlpm.nganhData=$A12)*(_xlpm.dttData)*(_xlpm.ttdttData)), IF(_xlpm.tongDT=0,"-",_xlpm.tongTT/_xlpm.tongDT) ) ) )} -> 2.2415 | G12: {=_xlfn.LET( _xlpm.colNganh,_xlfn.XMATCH("*ICB L1*",Sheet4!$1:$1,2), _xlpm.colLNST,_xlfn.XMATCH("*Lợi nhuận sau thuế*Q2*2026*",Sheet4!$1:$1,2), _xlpm.colTTLNST,_xlfn.XMATCH("*Tăng trưởng lợi nhuận sau thuế (YoY) (Quý*",Sheet4!$1:$1,2), _xlpm.nganhData,INDEX(Sheet4!$2:$1605,0,_xlpm.colNganh), _xlpm.lnstData,INDEX(Sheet4!$2:$1605,0,_xlpm.colLNST), _xlpm.ttlnstData,INDEX(Sheet4!$2:$1605,0,_xlpm.colTTLNST), _xlfn.LET( _xlpm.tongLNST,SUMPRODUCT((_xlpm.nganhData=$A12)*(_xlpm.lnstData)), _xlpm.tongTT,SUMPRODUCT((_xlpm.nganhData=$A12)*(_xlpm.lnstData)*(_xlpm.ttlnstData)), IF(_xlpm.tongLNST=0,"-",_xlpm.tongTT/_xlpm.tongLNST) ) )} -> 1.3018
A13: Dịch vụ Tiêu dùng | B13: =_xlfn.LET( _xlpm.colNganh,_xlfn.XMATCH("*ICB L1*",Sheet4!$1:$1,2), _xlpm.nganhData,INDEX(Sheet4!$2:$1605,0,_xlpm.colNganh), COUNTIF(_xlpm.nganhData,$A13) ) -> 109 | C13: {=_xlfn.LET( _xlpm.colNganh,_xlfn.XMATCH("*ICB L1*",Sheet4!$1:$1,2), _xlpm.colDTT,_xlfn.XMATCH("*Doanh thu thuần*Q2*2026*",Sheet4!$1:$1,2), _xlpm.colTNL,_xlfn.XMATCH("*Thu nhập lãi thuần*Quý: 2*2026*",Sheet4!$1:$1,2), _xlpm.nganhData,INDEX(Sheet4!$2:$1605,0,_xlpm.colNganh), _xlpm.dttData,INDEX(Sheet4!$2:$1605,0,_xlpm.colDTT), _xlpm.tnlData,INDEX(Sheet4!$2:$1605,0,_xlpm.colTNL), IF($A13="Ngân hàng", SUMPRODUCT((_xlpm.nganhData=$A13)*(_xlpm.tnlData<>"")*(_xlpm.tnlData<>0)*1), SUMPRODUCT((_xlpm.nganhData=$A13)*(_xlpm.dttData<>"")*(_xlpm.dttData<>0)*1) ) )} -> 28 | D13: {=_xlfn.LET( _xlpm.colNganh,_xlfn.XMATCH("*ICB L1*",Sheet4!$1:$1,2), _xlpm.colDTT,_xlfn.XMATCH("*Doanh thu thuần*Q2*2026*",Sheet4!$1:$1,2), _xlpm.colTNL,_xlfn.XMATCH("*Thu nhập lãi thuần*Quý: 2*2026*",Sheet4!$1:$1,2), _xlpm.nganhData,INDEX(Sheet4!$2:$1605,0,_xlpm.colNganh), _xlpm.dttData,INDEX(Sheet4!$2:$1605,0,_xlpm.colDTT), _xlpm.tnlData,INDEX(Sheet4!$2:$1605,0,_xlpm.colTNL), IF($A13="Ngân hàng", SUMPRODUCT((_xlpm.nganhData=$A13)*(_xlpm.tnlData))/1000000000, SUMPRODUCT((_xlpm.nganhData=$A13)*(_xlpm.dttData))/1000000000 ) )} -> 10082.863 | E13: {=_xlfn.LET( _xlpm.colNganh,_xlfn.XMATCH("*ICB L1*",Sheet4!$1:$1,2), _xlpm.colLNST,_xlfn.XMATCH("*Lợi nhuận sau thuế*Q2*2026*",Sheet4!$1:$1,2), _xlpm.nganhData,INDEX(Sheet4!$2:$1605,0,_xlpm.colNganh), _xlpm.lnstData,INDEX(Sheet4!$2:$1605,0,_xlpm.colLNST), SUMPRODUCT((_xlpm.nganhData=$A13)*(_xlpm.lnstData))/1000000000 )} -> 809.50332 | F13: {=_xlfn.LET( _xlpm.colNganh,_xlfn.XMATCH("*ICB L1*",Sheet4!$1:$1,2), _xlpm.colDTT,_xlfn.XMATCH("*Doanh thu thuần*Q2*2026*",Sheet4!$1:$1,2), _xlpm.colTNL26,_xlfn.XMATCH("*Thu nhập lãi thuần*Quý: 2*2026*",Sheet4!$1:$1,2), _xlpm.colTNL25,_xlfn.XMATCH("*Thu nhập lãi thuần*Q2*2025*",Sheet4!$1:$1,2), _xlpm.colTTDTT,_xlfn.XMATCH("*Tăng trưởng doanh thu thuần (YoY) (Quý*",Sheet4!$1:$1,2), _xlpm.nganhData,INDEX(Sheet4!$2:$1605,0,_xlpm.colNganh), _xlpm.dttData,INDEX(Sheet4!$2:$1605,0,_xlpm.colDTT), _xlpm.tnl26Data,INDEX(Sheet4!$2:$1605,0,_xlpm.colTNL26), _xlpm.tnl25Data,INDEX(Sheet4!$2:$1605,0,_xlpm.colTNL25), _xlpm.ttdttData,INDEX(Sheet4!$2:$1605,0,_xlpm.colTTDTT), IF($A13="Ngân hàng", _xlfn.LET( _xlpm.sumTNL26,SUMPRODUCT((_xlpm.nganhData=$A13)*(_xlpm.tnl26Data<>0)*(_xlpm.tnl26Data)), _xlpm.sumTNL25Match,SUMPRODUCT((_xlpm.nganhData=$A13)*(_xlpm.tnl26Data<>0)*(_xlpm.tnl25Data)), IF(OR(_xlpm.sumTNL26=0,_xlpm.sumTNL25Match=0),"-",_xlpm.sumTNL26/_xlpm.sumTNL25Match-1) ), _xlfn.LET( _xlpm.tongDT,SUMPRODUCT((_xlpm.nganhData=$A13)*(_xlpm.dttData)), _xlpm.tongTT,SUMPRODUCT((_xlpm.nganhData=$A13)*(_xlpm.dttData)*(_xlpm.ttdttData)), IF(_xlpm.tongDT=0,"-",_xlpm.tongTT/_xlpm.tongDT) ) ) )} -> 0.21850025 | G13: {=_xlfn.LET( _xlpm.colNganh,_xlfn.XMATCH("*ICB L1*",Sheet4!$1:$1,2), _xlpm.colLNST,_xlfn.XMATCH("*Lợi nhuận sau thuế*Q2*2026*",Sheet4!$1:$1,2), _xlpm.colTTLNST,_xlfn.XMATCH("*Tăng trưởng lợi nhuận sau thuế (YoY) (Quý*",Sheet4!$1:$1,2), _xlpm.nganhData,INDEX(Sheet4!$2:$1605,0,_xlpm.colNganh), _xlpm.lnstData,INDEX(Sheet4!$2:$1605,0,_xlpm.colLNST), _xlpm.ttlnstData,INDEX(Sheet4!$2:$1605,0,_xlpm.colTTLNST), _xlfn.LET( _xlpm.tongLNST,SUMPRODUCT((_xlpm.nganhData=$A13)*(_xlpm.lnstData)), _xlpm.tongTT,SUMPRODUCT((_xlpm.nganhData=$A13)*(_xlpm.lnstData)*(_xlpm.ttlnstData)), IF(_xlpm.tongLNST=0,"-",_xlpm.tongTT/_xlpm.tongLNST) ) )} -> 1.6463304
A14: Hàng Tiêu dùng | B14: =_xlfn.LET( _xlpm.colNganh,_xlfn.XMATCH("*ICB L1*",Sheet4!$1:$1,2), _xlpm.nganhData,INDEX(Sheet4!$2:$1605,0,_xlpm.colNganh), COUNTIF(_xlpm.nganhData,$A14) ) -> 241 | C14: {=_xlfn.LET( _xlpm.colNganh,_xlfn.XMATCH("*ICB L1*",Sheet4!$1:$1,2), _xlpm.colDTT,_xlfn.XMATCH("*Doanh thu thuần*Q2*2026*",Sheet4!$1:$1,2), _xlpm.colTNL,_xlfn.XMATCH("*Thu nhập lãi thuần*Quý: 2*2026*",Sheet4!$1:$1,2), _xlpm.nganhData,INDEX(Sheet4!$2:$1605,0,_xlpm.colNganh), _xlpm.dttData,INDEX(Sheet4!$2:$1605,0,_xlpm.colDTT), _xlpm.tnlData,INDEX(Sheet4!$2:$1605,0,_xlpm.colTNL), IF($A14="Ngân hàng", SUMPRODUCT((_xlpm.nganhData=$A14)*(_xlpm.tnlData<>"")*(_xlpm.tnlData<>0)*1), SUMPRODUCT((_xlpm.nganhData=$A14)*(_xlpm.dttData<>"")*(_xlpm.dttData<>0)*1) ) )} -> 54 | D14: {=_xlfn.LET( _xlpm.colNganh,_xlfn.XMATCH("*ICB L1*",Sheet4!$1:$1,2), _xlpm.colDTT,_xlfn.XMATCH("*Doanh thu thuần*Q2*2026*",Sheet4!$1:$1,2), _xlpm.colTNL,_xlfn.XMATCH("*Thu nhập lãi thuần*Quý: 2*2026*",Sheet4!$1:$1,2), _xlpm.nganhData,INDEX(Sheet4!$2:$1605,0,_xlpm.colNganh), _xlpm.dttData,INDEX(Sheet4!$2:$1605,0,_xlpm.colDTT), _xlpm.tnlData,INDEX(Sheet4!$2:$1605,0,_xlpm.colTNL), IF($A14="Ngân hàng", SUMPRODUCT((_xlpm.nganhData=$A14)*(_xlpm.tnlData))/1000000000, SUMPRODUCT((_xlpm.nganhData=$A14)*(_xlpm.dttData))/1000000000 ) )} -> 23873.363 | E14: {=_xlfn.LET( _xlpm.colNganh,_xlfn.XMATCH("*ICB L1*",Sheet4!$1:$1,2), _xlpm.colLNST,_xlfn.XMATCH("*Lợi nhuận sau thuế*Q2*2026*",Sheet4!$1:$1,2), _xlpm.nganhData,INDEX(Sheet4!$2:$1605,0,_xlpm.colNganh), _xlpm.lnstData,INDEX(Sheet4!$2:$1605,0,_xlpm.colLNST), SUMPRODUCT((_xlpm.nganhData=$A14)*(_xlpm.lnstData))/1000000000 )} -> 1453.7812 | F14: {=_xlfn.LET( _xlpm.colNganh,_xlfn.XMATCH("*ICB L1*",Sheet4!$1:$1,2), _xlpm.colDTT,_xlfn.XMATCH("*Doanh thu thuần*Q2*2026*",Sheet4!$1:$1,2), _xlpm.colTNL26,_xlfn.XMATCH("*Thu nhập lãi thuần*Quý: 2*2026*",Sheet4!$1:$1,2), _xlpm.colTNL25,_xlfn.XMATCH("*Thu nhập lãi thuần*Q2*2025*",Sheet4!$1:$1,2), _xlpm.colTTDTT,_xlfn.XMATCH("*Tăng trưởng doanh thu thuần (YoY) (Quý*",Sheet4!$1:$1,2), _xlpm.nganhData,INDEX(Sheet4!$2:$1605,0,_xlpm.colNganh), _xlpm.dttData,INDEX(Sheet4!$2:$1605,0,_xlpm.colDTT), _xlpm.tnl26Data,INDEX(Sheet4!$2:$1605,0,_xlpm.colTNL26), _xlpm.tnl25Data,INDEX(Sheet4!$2:$1605,0,_xlpm.colTNL25), _xlpm.ttdttData,INDEX(Sheet4!$2:$1605,0,_xlpm.colTTDTT), IF($A14="Ngân hàng", _xlfn.LET( _xlpm.sumTNL26,SUMPRODUCT((_xlpm.nganhData=$A14)*(_xlpm.tnl26Data<>0)*(_xlpm.tnl26Data)), _xlpm.sumTNL25Match,SUMPRODUCT((_xlpm.nganhData=$A14)*(_xlpm.tnl26Data<>0)*(_xlpm.tnl25Data)), IF(OR(_xlpm.sumTNL26=0,_xlpm.sumTNL25Match=0),"-",_xlpm.sumTNL26/_xlpm.sumTNL25Match-1) ), _xlfn.LET( _xlpm.tongDT,SUMPRODUCT((_xlpm.nganhData=$A14)*(_xlpm.dttData)), _xlpm.tongTT,SUMPRODUCT((_xlpm.nganhData=$A14)*(_xlpm.dttData)*(_xlpm.ttdttData)), IF(_xlpm.tongDT=0,"-",_xlpm.tongTT/_xlpm.tongDT) ) ) )} -> 0.086271282 | G14: {=_xlfn.LET( _xlpm.colNganh,_xlfn.XMATCH("*ICB L1*",Sheet4!$1:$1,2), _xlpm.colLNST,_xlfn.XMATCH("*Lợi nhuận sau thuế*Q2*2026*",Sheet4!$1:$1,2), _xlpm.colTTLNST,_xlfn.XMATCH("*Tăng trưởng lợi nhuận sau thuế (YoY) (Quý*",Sheet4!$1:$1,2), _xlpm.nganhData,INDEX(Sheet4!$2:$1605,0,_xlpm.colNganh), _xlpm.lnstData,INDEX(Sheet4!$2:$1605,0,_xlpm.colLNST), _xlpm.ttlnstData,INDEX(Sheet4!$2:$1605,0,_xlpm.colTTLNST), _xlfn.LET( _xlpm.tongLNST,SUMPRODUCT((_xlpm.nganhData=$A14)*(_xlpm.lnstData)), _xlpm.tongTT,SUMPRODUCT((_xlpm.nganhData=$A14)*(_xlpm.lnstData)*(_xlpm.ttlnstData)), IF(_xlpm.tongLNST=0,"-",_xlpm.tongTT/_xlpm.tongLNST) ) )} -> 1.5510906
A15: Nguyên vật liệu | B15: =_xlfn.LET( _xlpm.colNganh,_xlfn.XMATCH("*ICB L1*",Sheet4!$1:$1,2), _xlpm.nganhData,INDEX(Sheet4!$2:$1605,0,_xlpm.colNganh), COUNTIF(_xlpm.nganhData,$A15) ) -> 177 | C15: {=_xlfn.LET( _xlpm.colNganh,_xlfn.XMATCH("*ICB L1*",Sheet4!$1:$1,2), _xlpm.colDTT,_xlfn.XMATCH("*Doanh thu thuần*Q2*2026*",Sheet4!$1:$1,2), _xlpm.colTNL,_xlfn.XMATCH("*Thu nhập lãi thuần*Quý: 2*2026*",Sheet4!$1:$1,2), _xlpm.nganhData,INDEX(Sheet4!$2:$1605,0,_xlpm.colNganh), _xlpm.dttData,INDEX(Sheet4!$2:$1605,0,_xlpm.colDTT), _xlpm.tnlData,INDEX(Sheet4!$2:$1605,0,_xlpm.colTNL), IF($A15="Ngân hàng", SUMPRODUCT((_xlpm.nganhData=$A15)*(_xlpm.tnlData<>"")*(_xlpm.tnlData<>0)*1), SUMPRODUCT((_xlpm.nganhData=$A15)*(_xlpm.dttData<>"")*(_xlpm.dttData<>0)*1) ) )} -> 55 | D15: {=_xlfn.LET( _xlpm.colNganh,_xlfn.XMATCH("*ICB L1*",Sheet4!$1:$1,2), _xlpm.colDTT,_xlfn.XMATCH("*Doanh thu thuần*Q2*2026*",Sheet4!$1:$1,2), _xlpm.colTNL,_xlfn.XMATCH("*Thu nhập lãi thuần*Quý: 2*2026*",Sheet4!$1:$1,2), _xlpm.nganhData,INDEX(Sheet4!$2:$1605,0,_xlpm.colNganh), _xlpm.dttData,INDEX(Sheet4!$2:$1605,0,_xlpm.colDTT), _xlpm.tnlData,INDEX(Sheet4!$2:$1605,0,_xlpm.colTNL), IF($A15="Ngân hàng", SUMPRODUCT((_xlpm.nganhData=$A15)*(_xlpm.tnlData))/1000000000, SUMPRODUCT((_xlpm.nganhData=$A15)*(_xlpm.dttData))/1000000000 ) )} -> 33424.859 | E15: {=_xlfn.LET( _xlpm.colNganh,_xlfn.XMATCH("*ICB L1*",Sheet4!$1:$1,2), _xlpm.colLNST,_xlfn.XMATCH("*Lợi nhuận sau thuế*Q2*2026*",Sheet4!$1:$1,2), _xlpm.nganhData,INDEX(Sheet4!$2:$1605,0,_xlpm.colNganh), _xlpm.lnstData,INDEX(Sheet4!$2:$1605,0,_xlpm.colLNST), SUMPRODUCT((_xlpm.nganhData=$A15)*(_xlpm.lnstData))/1000000000 )} -> 1298.9606 | F15: {=_xlfn.LET( _xlpm.colNganh,_xlfn.XMATCH("*ICB L1*",Sheet4!$1:$1,2), _xlpm.colDTT,_xlfn.XMATCH("*Doanh thu thuần*Q2*2026*",Sheet4!$1:$1,2), _xlpm.colTNL26,_xlfn.XMATCH("*Thu nhập lãi thuần*Quý: 2*2026*",Sheet4!$1:$1,2), _xlpm.colTNL25,_xlfn.XMATCH("*Thu nhập lãi thuần*Q2*2025*",Sheet4!$1:$1,2), _xlpm.colTTDTT,_xlfn.XMATCH("*Tăng trưởng doanh thu thuần (YoY) (Quý*",Sheet4!$1:$1,2), _xlpm.nganhData,INDEX(Sheet4!$2:$1605,0,_xlpm.colNganh), _xlpm.dttData,INDEX(Sheet4!$2:$1605,0,_xlpm.colDTT), _xlpm.tnl26Data,INDEX(Sheet4!$2:$1605,0,_xlpm.colTNL26), _xlpm.tnl25Data,INDEX(Sheet4!$2:$1605,0,_xlpm.colTNL25), _xlpm.ttdttData,INDEX(Sheet4!$2:$1605,0,_xlpm.colTTDTT), IF($A15="Ngân hàng", _xlfn.LET( _xlpm.sumTNL26,SUMPRODUCT((_xlpm.nganhData=$A15)*(_xlpm.tnl26Data<>0)*(_xlpm.tnl26Data)), _xlpm.sumTNL25Match,SUMPRODUCT((_xlpm.nganhData=$A15)*(_xlpm.tnl26Data<>0)*(_xlpm.tnl25Data)), IF(OR(_xlpm.sumTNL26=0,_xlpm.sumTNL25Match=0),"-",_xlpm.sumTNL26/_xlpm.sumTNL25Match-1) ), _xlfn.LET( _xlpm.tongDT,SUMPRODUCT((_xlpm.nganhData=$A15)*(_xlpm.dttData)), _xlpm.tongTT,SUMPRODUCT((_xlpm.nganhData=$A15)*(_xlpm.dttData)*(_xlpm.ttdttData)), IF(_xlpm.tongDT=0,"-",_xlpm.tongTT/_xlpm.tongDT) ) ) )} -> 0.094879474 | G15: {=_xlfn.LET( _xlpm.colNganh,_xlfn.XMATCH("*ICB L1*",Sheet4!$1:$1,2), _xlpm.colLNST,_xlfn.XMATCH("*Lợi nhuận sau thuế*Q2*2026*",Sheet4!$1:$1,2), _xlpm.colTTLNST,_xlfn.XMATCH("*Tăng trưởng lợi nhuận sau thuế (YoY) (Quý*",Sheet4!$1:$1,2), _xlpm.nganhData,INDEX(Sheet4!$2:$1605,0,_xlpm.colNganh), _xlpm.lnstData,INDEX(Sheet4!$2:$1605,0,_xlpm.colLNST), _xlpm.ttlnstData,INDEX(Sheet4!$2:$1605,0,_xlpm.colTTLNST), _xlfn.LET( _xlpm.tongLNST,SUMPRODUCT((_xlpm.nganhData=$A15)*(_xlpm.lnstData)), _xlpm.tongTT,SUMPRODUCT((_xlpm.nganhData=$A15)*(_xlpm.lnstData)*(_xlpm.ttlnstData)), IF(_xlpm.tongLNST=0,"-",_xlpm.tongTT/_xlpm.tongLNST) ) )} -> 0.77945911
A16: Ngân hàng | B16: =_xlfn.LET( _xlpm.colNganh,_xlfn.XMATCH("*ICB L1*",Sheet4!$1:$1,2), _xlpm.nganhData,INDEX(Sheet4!$2:$1605,0,_xlpm.colNganh), COUNTIF(_xlpm.nganhData,$A16) ) -> 28 | C16: {=_xlfn.LET( _xlpm.colNganh,_xlfn.XMATCH("*ICB L1*",Sheet4!$1:$1,2), _xlpm.colDTT,_xlfn.XMATCH("*Doanh thu thuần*Q2*2026*",Sheet4!$1:$1,2), _xlpm.colTNL,_xlfn.XMATCH("*Thu nhập lãi thuần*Quý: 2*2026*",Sheet4!$1:$1,2), _xlpm.nganhData,INDEX(Sheet4!$2:$1605,0,_xlpm.colNganh), _xlpm.dttData,INDEX(Sheet4!$2:$1605,0,_xlpm.colDTT), _xlpm.tnlData,INDEX(Sheet4!$2:$1605,0,_xlpm.colTNL), IF($A16="Ngân hàng", SUMPRODUCT((_xlpm.nganhData=$A16)*(_xlpm.tnlData<>"")*(_xlpm.tnlData<>0)*1), SUMPRODUCT((_xlpm.nganhData=$A16)*(_xlpm.dttData<>"")*(_xlpm.dttData<>0)*1) ) )} -> 6 | D16: {=_xlfn.LET( _xlpm.colNganh,_xlfn.XMATCH("*ICB L1*",Sheet4!$1:$1,2), _xlpm.colDTT,_xlfn.XMATCH("*Doanh thu thuần*Q2*2026*",Sheet4!$1:$1,2), _xlpm.colTNL,_xlfn.XMATCH("*Thu nhập lãi thuần*Quý: 2*2026*",Sheet4!$1:$1,2), _xlpm.nganhData,INDEX(Sheet4!$2:$1605,0,_xlpm.colNganh), _xlpm.dttData,INDEX(Sheet4!$2:$1605,0,_xlpm.colDTT), _xlpm.tnlData,INDEX(Sheet4!$2:$1605,0,_xlpm.colTNL), IF($A16="Ngân hàng", SUMPRODUCT((_xlpm.nganhData=$A16)*(_xlpm.tnlData))/1000000000, SUMPRODUCT((_xlpm.nganhData=$A16)*(_xlpm.dttData))/1000000000 ) )} -> 41884.24 | E16: {=_xlfn.LET( _xlpm.colNganh,_xlfn.XMATCH("*ICB L1*",Sheet4!$1:$1,2), _xlpm.colLNST,_xlfn.XMATCH("*Lợi nhuận sau thuế*Q2*2026*",Sheet4!$1:$1,2), _xlpm.nganhData,INDEX(Sheet4!$2:$1605,0,_xlpm.colNganh), _xlpm.lnstData,INDEX(Sheet4!$2:$1605,0,_xlpm.colLNST), SUMPRODUCT((_xlpm.nganhData=$A16)*(_xlpm.lnstData))/1000000000 )} -> 23891.646 | F16: {=_xlfn.LET( _xlpm.colNganh,_xlfn.XMATCH("*ICB L1*",Sheet4!$1:$1,2), _xlpm.colDTT,_xlfn.XMATCH("*Doanh thu thuần*Q2*2026*",Sheet4!$1:$1,2), _xlpm.colTNL26,_xlfn.XMATCH("*Thu nhập lãi thuần*Quý: 2*2026*",Sheet4!$1:$1,2), _xlpm.colTNL25,_xlfn.XMATCH("*Thu nhập lãi thuần*Q2*2025*",Sheet4!$1:$1,2), _xlpm.colTTDTT,_xlfn.XMATCH("*Tăng trưởng doanh thu thuần (YoY) (Quý*",Sheet4!$1:$1,2), _xlpm.nganhData,INDEX(Sheet4!$2:$1605,0,_xlpm.colNganh), _xlpm.dttData,INDEX(Sheet4!$2:$1605,0,_xlpm.colDTT), _xlpm.tnl26Data,INDEX(Sheet4!$2:$1605,0,_xlpm.colTNL26), _xlpm.tnl25Data,INDEX(Sheet4!$2:$1605,0,_xlpm.colTNL25), _xlpm.ttdttData,INDEX(Sheet4!$2:$1605,0,_xlpm.colTTDTT), IF($A16="Ngân hàng", _xlfn.LET( _xlpm.sumTNL26,SUMPRODUCT((_xlpm.nganhData=$A16)*(_xlpm.tnl26Data<>0)*(_xlpm.tnl26Data)), _xlpm.sumTNL25Match,SUMPRODUCT((_xlpm.nganhData=$A16)*(_xlpm.tnl26Data<>0)*(_xlpm.tnl25Data)), IF(OR(_xlpm.sumTNL26=0,_xlpm.sumTNL25Match=0),"-",_xlpm.sumTNL26/_xlpm.sumTNL25Match-1) ), _xlfn.LET( _xlpm.tongDT,SUMPRODUCT((_xlpm.nganhData=$A16)*(_xlpm.dttData)), _xlpm.tongTT,SUMPRODUCT((_xlpm.nganhData=$A16)*(_xlpm.dttData)*(_xlpm.ttdttData)), IF(_xlpm.tongDT=0,"-",_xlpm.tongTT/_xlpm.tongDT) ) ) )} -> 0.19630757 | G16: {=_xlfn.LET( _xlpm.colNganh,_xlfn.XMATCH("*ICB L1*",Sheet4!$1:$1,2), _xlpm.colLNST,_xlfn.XMATCH("*Lợi nhuận sau thuế*Q2*2026*",Sheet4!$1:$1,2), _xlpm.colTTLNST,_xlfn.XMATCH("*Tăng trưởng lợi nhuận sau thuế (YoY) (Quý*",Sheet4!$1:$1,2), _xlpm.nganhData,INDEX(Sheet4!$2:$1605,0,_xlpm.colNganh), _xlpm.lnstData,INDEX(Sheet4!$2:$1605,0,_xlpm.colLNST), _xlpm.ttlnstData,INDEX(Sheet4!$2:$1605,0,_xlpm.colTTLNST), _xlfn.LET( _xlpm.tongLNST,SUMPRODUCT((_xlpm.nganhData=$A16)*(_xlpm.lnstData)), _xlpm.tongTT,SUMPRODUCT((_xlpm.nganhData=$A16)*(_xlpm.lnstData)*(_xlpm.ttlnstData)), IF(_xlpm.tongLNST=0,"-",_xlpm.tongTT/_xlpm.tongLNST) ) )} -> 0.31664278
A17: Tiện ích Cộng đồng | B17: =_xlfn.LET( _xlpm.colNganh,_xlfn.XMATCH("*ICB L1*",Sheet4!$1:$1,2), _xlpm.nganhData,INDEX(Sheet4!$2:$1605,0,_xlpm.colNganh), COUNTIF(_xlpm.nganhData,$A17) ) -> 141 | C17: {=_xlfn.LET( _xlpm.colNganh,_xlfn.XMATCH("*ICB L1*",Sheet4!$1:$1,2), _xlpm.colDTT,_xlfn.XMATCH("*Doanh thu thuần*Q2*2026*",Sheet4!$1:$1,2), _xlpm.colTNL,_xlfn.XMATCH("*Thu nhập lãi thuần*Quý: 2*2026*",Sheet4!$1:$1,2), _xlpm.nganhData,INDEX(Sheet4!$2:$1605,0,_xlpm.colNganh), _xlpm.dttData,INDEX(Sheet4!$2:$1605,0,_xlpm.colDTT), _xlpm.tnlData,INDEX(Sheet4!$2:$1605,0,_xlpm.colTNL), IF($A17="Ngân hàng", SUMPRODUCT((_xlpm.nganhData=$A17)*(_xlpm.tnlData<>"")*(_xlpm.tnlData<>0)*1), SUMPRODUCT((_xlpm.nganhData=$A17)*(_xlpm.dttData<>"")*(_xlpm.dttData<>0)*1) ) )} -> 57 | D17: {=_xlfn.LET( _xlpm.colNganh,_xlfn.XMATCH("*ICB L1*",Sheet4!$1:$1,2), _xlpm.colDTT,_xlfn.XMATCH("*Doanh thu thuần*Q2*2026*",Sheet4!$1:$1,2), _xlpm.colTNL,_xlfn.XMATCH("*Thu nhập lãi thuần*Quý: 2*2026*",Sheet4!$1:$1,2), _xlpm.nganhData,INDEX(Sheet4!$2:$1605,0,_xlpm.colNganh), _xlpm.dttData,INDEX(Sheet4!$2:$1605,0,_xlpm.colDTT), _xlpm.tnlData,INDEX(Sheet4!$2:$1605,0,_xlpm.colTNL), IF($A17="Ngân hàng", SUMPRODUCT((_xlpm.nganhData=$A17)*(_xlpm.tnlData))/1000000000, SUMPRODUCT((_xlpm.nganhData=$A17)*(_xlpm.dttData))/1000000000 ) )} -> 35300.077 | E17: {=_xlfn.LET( _xlpm.colNganh,_xlfn.XMATCH("*ICB L1*",Sheet4!$1:$1,2), _xlpm.colLNST,_xlfn.XMATCH("*Lợi nhuận sau thuế*Q2*2026*",Sheet4!$1:$1,2), _xlpm.nganhData,INDEX(Sheet4!$2:$1605,0,_xlpm.colNganh), _xlpm.lnstData,INDEX(Sheet4!$2:$1605,0,_xlpm.colLNST), SUMPRODUCT((_xlpm.nganhData=$A17)*(_xlpm.lnstData))/1000000000 )} -> 2034.3132 | F17: {=_xlfn.LET( _xlpm.colNganh,_xlfn.XMATCH("*ICB L1*",Sheet4!$1:$1,2), _xlpm.colDTT,_xlfn.XMATCH("*Doanh thu thuần*Q2*2026*",Sheet4!$1:$1,2), _xlpm.colTNL26,_xlfn.XMATCH("*Thu nhập lãi thuần*Quý: 2*2026*",Sheet4!$1:$1,2), _xlpm.colTNL25,_xlfn.XMATCH("*Thu nhập lãi thuần*Q2*2025*",Sheet4!$1:$1,2), _xlpm.colTTDTT,_xlfn.XMATCH("*Tăng trưởng doanh thu thuần (YoY) (Quý*",Sheet4!$1:$1,2), _xlpm.nganhData,INDEX(Sheet4!$2:$1605,0,_xlpm.colNganh), _xlpm.dttData,INDEX(Sheet4!$2:$1605,0,_xlpm.colDTT), _xlpm.tnl26Data,INDEX(Sheet4!$2:$1605,0,_xlpm.colTNL26), _xlpm.tnl25Data,INDEX(Sheet4!$2:$1605,0,_xlpm.colTNL25), _xlpm.ttdttData,INDEX(Sheet4!$2:$1605,0,_xlpm.colTTDTT), IF($A17="Ngân hàng", _xlfn.LET( _xlpm.sumTNL26,SUMPRODUCT((_xlpm.nganhData=$A17)*(_xlpm.tnl26Data<>0)*(_xlpm.tnl26Data)), _xlpm.sumTNL25Match,SUMPRODUCT((_xlpm.nganhData=$A17)*(_xlpm.tnl26Data<>0)*(_xlpm.tnl25Data)), IF(OR(_xlpm.sumTNL26=0,_xlpm.sumTNL25Match=0),"-",_xlpm.sumTNL26/_xlpm.sumTNL25Match-1) ), _xlfn.LET( _xlpm.tongDT,SUMPRODUCT((_xlpm.nganhData=$A17)*(_xlpm.dttData)), _xlpm.tongTT,SUMPRODUCT((_xlpm.nganhData=$A17)*(_xlpm.dttData)*(_xlpm.ttdttData)), IF(_xlpm.tongDT=0,"-",_xlpm.tongTT/_xlpm.tongDT) ) ) )} -> 0.38972356 | G17: {=_xlfn.LET( _xlpm.colNganh,_xlfn.XMATCH("*ICB L1*",Sheet4!$1:$1,2), _xlpm.colLNST,_xlfn.XMATCH("*Lợi nhuận sau thuế*Q2*2026*",Sheet4!$1:$1,2), _xlpm.colTTLNST,_xlfn.XMATCH("*Tăng trưởng lợi nhuận sau thuế (YoY) (Quý*",Sheet4!$1:$1,2), _xlpm.nganhData,INDEX(Sheet4!$2:$1605,0,_xlpm.colNganh), _xlpm.lnstData,INDEX(Sheet4!$2:$1605,0,_xlpm.colLNST), _xlpm.ttlnstData,INDEX(Sheet4!$2:$1605,0,_xlpm.colTTLNST), _xlfn.LET( _xlpm.tongLNST,SUMPRODUCT((_xlpm.nganhData=$A17)*(_xlpm.lnstData)), _xlpm.tongTT,SUMPRODUCT((_xlpm.nganhData=$A17)*(_xlpm.lnstData)*(_xlpm.ttlnstData)), IF(_xlpm.tongLNST=0,"-",_xlpm.tongTT/_xlpm.tongLNST) ) )} -> 0.92146668
A18: Tài chính | B18: =_xlfn.LET( _xlpm.colNganh,_xlfn.XMATCH("*ICB L1*",Sheet4!$1:$1,2), _xlpm.nganhData,INDEX(Sheet4!$2:$1605,0,_xlpm.colNganh), COUNTIF(_xlpm.nganhData,$A18) ) -> 213 | C18: {=_xlfn.LET( _xlpm.colNganh,_xlfn.XMATCH("*ICB L1*",Sheet4!$1:$1,2), _xlpm.colDTT,_xlfn.XMATCH("*Doanh thu thuần*Q2*2026*",Sheet4!$1:$1,2), _xlpm.colTNL,_xlfn.XMATCH("*Thu nhập lãi thuần*Quý: 2*2026*",Sheet4!$1:$1,2), _xlpm.nganhData,INDEX(Sheet4!$2:$1605,0,_xlpm.colNganh), _xlpm.dttData,INDEX(Sheet4!$2:$1605,0,_xlpm.colDTT), _xlpm.tnlData,INDEX(Sheet4!$2:$1605,0,_xlpm.colTNL), IF($A18="Ngân hàng", SUMPRODUCT((_xlpm.nganhData=$A18)*(_xlpm.tnlData<>"")*(_xlpm.tnlData<>0)*1), SUMPRODUCT((_xlpm.nganhData=$A18)*(_xlpm.dttData<>"")*(_xlpm.dttData<>0)*1) ) )} -> 69 | D18: {=_xlfn.LET( _xlpm.colNganh,_xlfn.XMATCH("*ICB L1*",Sheet4!$1:$1,2), _xlpm.colDTT,_xlfn.XMATCH("*Doanh thu thuần*Q2*2026*",Sheet4!$1:$1,2), _xlpm.colTNL,_xlfn.XMATCH("*Thu nhập lãi thuần*Quý: 2*2026*",Sheet4!$1:$1,2), _xlpm.nganhData,INDEX(Sheet4!$2:$1605,0,_xlpm.colNganh), _xlpm.dttData,INDEX(Sheet4!$2:$1605,0,_xlpm.colDTT), _xlpm.tnlData,INDEX(Sheet4!$2:$1605,0,_xlpm.colTNL), IF($A18="Ngân hàng", SUMPRODUCT((_xlpm.nganhData=$A18)*(_xlpm.tnlData))/1000000000, SUMPRODUCT((_xlpm.nganhData=$A18)*(_xlpm.dttData))/1000000000 ) )} -> 32092.385 | E18: {=_xlfn.LET( _xlpm.colNganh,_xlfn.XMATCH("*ICB L1*",Sheet4!$1:$1,2), _xlpm.colLNST,_xlfn.XMATCH("*Lợi nhuận sau thuế*Q2*2026*",Sheet4!$1:$1,2), _xlpm.nganhData,INDEX(Sheet4!$2:$1605,0,_xlpm.colNganh), _xlpm.lnstData,INDEX(Sheet4!$2:$1605,0,_xlpm.colLNST), SUMPRODUCT((_xlpm.nganhData=$A18)*(_xlpm.lnstData))/1000000000 )} -> 10492.285 | F18: {=_xlfn.LET( _xlpm.colNganh,_xlfn.XMATCH("*ICB L1*",Sheet4!$1:$1,2), _xlpm.colDTT,_xlfn.XMATCH("*Doanh thu thuần*Q2*2026*",Sheet4!$1:$1,2), _xlpm.colTNL26,_xlfn.XMATCH("*Thu nhập lãi thuần*Quý: 2*2026*",Sheet4!$1:$1,2), _xlpm.colTNL25,_xlfn.XMATCH("*Thu nhập lãi thuần*Q2*2025*",Sheet4!$1:$1,2), _xlpm.colTTDTT,_xlfn.XMATCH("*Tăng trưởng doanh thu thuần (YoY) (Quý*",Sheet4!$1:$1,2), _xlpm.nganhData,INDEX(Sheet4!$2:$1605,0,_xlpm.colNganh), _xlpm.dttData,INDEX(Sheet4!$2:$1605,0,_xlpm.colDTT), _xlpm.tnl26Data,INDEX(Sheet4!$2:$1605,0,_xlpm.colTNL26), _xlpm.tnl25Data,INDEX(Sheet4!$2:$1605,0,_xlpm.colTNL25), _xlpm.ttdttData,INDEX(Sheet4!$2:$1605,0,_xlpm.colTTDTT), IF($A18="Ngân hàng", _xlfn.LET( _xlpm.sumTNL26,SUMPRODUCT((_xlpm.nganhData=$A18)*(_xlpm.tnl26Data<>0)*(_xlpm.tnl26Data)), _xlpm.sumTNL25Match,SUMPRODUCT((_xlpm.nganhData=$A18)*(_xlpm.tnl26Data<>0)*(_xlpm.tnl25Data)), IF(OR(_xlpm.sumTNL26=0,_xlpm.sumTNL25Match=0),"-",_xlpm.sumTNL26/_xlpm.sumTNL25Match-1) ), _xlfn.LET( _xlpm.tongDT,SUMPRODUCT((_xlpm.nganhData=$A18)*(_xlpm.dttData)), _xlpm.tongTT,SUMPRODUCT((_xlpm.nganhData=$A18)*(_xlpm.dttData)*(_xlpm.ttdttData)), IF(_xlpm.tongDT=0,"-",_xlpm.tongTT/_xlpm.tongDT) ) ) )} -> 1.8165816 | G18: {=_xlfn.LET( _xlpm.colNganh,_xlfn.XMATCH("*ICB L1*",Sheet4!$1:$1,2), _xlpm.colLNST,_xlfn.XMATCH("*Lợi nhuận sau thuế*Q2*2026*",Sheet4!$1:$1,2), _xlpm.colTTLNST,_xlfn.XMATCH("*Tăng trưởng lợi nhuận sau thuế (YoY) (Quý*",Sheet4!$1:$1,2), _xlpm.nganhData,INDEX(Sheet4!$2:$1605,0,_xlpm.colNganh), _xlpm.lnstData,INDEX(Sheet4!$2:$1605,0,_xlpm.colLNST), _xlpm.ttlnstData,INDEX(Sheet4!$2:$1605,0,_xlpm.colTTLNST), _xlfn.LET( _xlpm.tongLNST,SUMPRODUCT((_xlpm.nganhData=$A18)*(_xlpm.lnstData)), _xlpm.tongTT,SUMPRODUCT((_xlpm.nganhData=$A18)*(_xlpm.lnstData)*(_xlpm.ttlnstData)), IF(_xlpm.tongLNST=0,"-",_xlpm.tongTT/_xlpm.tongLNST) ) )} -> 2.5227069
A19: Viễn thông | B19: =_xlfn.LET( _xlpm.colNganh,_xlfn.XMATCH("*ICB L1*",Sheet4!$1:$1,2), _xlpm.nganhData,INDEX(Sheet4!$2:$1605,0,_xlpm.colNganh), COUNTIF(_xlpm.nganhData,$A19) ) -> 8 | C19: {=_xlfn.LET( _xlpm.colNganh,_xlfn.XMATCH("*ICB L1*",Sheet4!$1:$1,2), _xlpm.colDTT,_xlfn.XMATCH("*Doanh thu thuần*Q2*2026*",Sheet4!$1:$1,2), _xlpm.colTNL,_xlfn.XMATCH("*Thu nhập lãi thuần*Quý: 2*2026*",Sheet4!$1:$1,2), _xlpm.nganhData,INDEX(Sheet4!$2:$1605,0,_xlpm.colNganh), _xlpm.dttData,INDEX(Sheet4!$2:$1605,0,_xlpm.colDTT), _xlpm.tnlData,INDEX(Sheet4!$2:$1605,0,_xlpm.colTNL), IF($A19="Ngân hàng", SUMPRODUCT((_xlpm.nganhData=$A19)*(_xlpm.tnlData<>"")*(_xlpm.tnlData<>0)*1), SUMPRODUCT((_xlpm.nganhData=$A19)*(_xlpm.dttData<>"")*(_xlpm.dttData<>0)*1) ) )} -> 0 | D19: {=_xlfn.LET( _xlpm.colNganh,_xlfn.XMATCH("*ICB L1*",Sheet4!$1:$1,2), _xlpm.colDTT,_xlfn.XMATCH("*Doanh thu thuần*Q2*2026*",Sheet4!$1:$1,2), _xlpm.colTNL,_xlfn.XMATCH("*Thu nhập lãi thuần*Quý: 2*2026*",Sheet4!$1:$1,2), _xlpm.nganhData,INDEX(Sheet4!$2:$1605,0,_xlpm.colNganh), _xlpm.dttData,INDEX(Sheet4!$2:$1605,0,_xlpm.colDTT), _xlpm.tnlData,INDEX(Sheet4!$2:$1605,0,_xlpm.colTNL), IF($A19="Ngân hàng", SUMPRODUCT((_xlpm.nganhData=$A19)*(_xlpm.tnlData))/1000000000, SUMPRODUCT((_xlpm.nganhData=$A19)*(_xlpm.dttData))/1000000000 ) )} -> 0 | E19: {=_xlfn.LET( _xlpm.colNganh,_xlfn.XMATCH("*ICB L1*",Sheet4!$1:$1,2), _xlpm.colLNST,_xlfn.XMATCH("*Lợi nhuận sau thuế*Q2*2026*",Sheet4!$1:$1,2), _xlpm.nganhData,INDEX(Sheet4!$2:$1605,0,_xlpm.colNganh), _xlpm.lnstData,INDEX(Sheet4!$2:$1605,0,_xlpm.colLNST), SUMPRODUCT((_xlpm.nganhData=$A19)*(_xlpm.lnstData))/1000000000 )} -> 0 | F19: {=_xlfn.LET( _xlpm.colNganh,_xlfn.XMATCH("*ICB L1*",Sheet4!$1:$1,2), _xlpm.colDTT,_xlfn.XMATCH("*Doanh thu thuần*Q2*2026*",Sheet4!$1:$1,2), _xlpm.colTNL26,_xlfn.XMATCH("*Thu nhập lãi thuần*Quý: 2*2026*",Sheet4!$1:$1,2), _xlpm.colTNL25,_xlfn.XMATCH("*Thu nhập lãi thuần*Q2*2025*",Sheet4!$1:$1,2), _xlpm.colTTDTT,_xlfn.XMATCH("*Tăng trưởng doanh thu thuần (YoY) (Quý*",Sheet4!$1:$1,2), _xlpm.nganhData,INDEX(Sheet4!$2:$1605,0,_xlpm.colNganh), _xlpm.dttData,INDEX(Sheet4!$2:$1605,0,_xlpm.colDTT), _xlpm.tnl26Data,INDEX(Sheet4!$2:$1605,0,_xlpm.colTNL26), _xlpm.tnl25Data,INDEX(Sheet4!$2:$1605,0,_xlpm.colTNL25), _xlpm.ttdttData,INDEX(Sheet4!$2:$1605,0,_xlpm.colTTDTT), IF($A19="Ngân hàng", _xlfn.LET( _xlpm.sumTNL26,SUMPRODUCT((_xlpm.nganhData=$A19)*(_xlpm.tnl26Data<>0)*(_xlpm.tnl26Data)), _xlpm.sumTNL25Match,SUMPRODUCT((_xlpm.nganhData=$A19)*(_xlpm.tnl26Data<>0)*(_xlpm.tnl25Data)), IF(OR(_xlpm.sumTNL26=0,_xlpm.sumTNL25Match=0),"-",_xlpm.sumTNL26/_xlpm.sumTNL25Match-1) ), _xlfn.LET( _xlpm.tongDT,SUMPRODUCT((_xlpm.nganhData=$A19)*(_xlpm.dttData)), _xlpm.tongTT,SUMPRODUCT((_xlpm.nganhData=$A19)*(_xlpm.dttData)*(_xlpm.ttdttData)), IF(_xlpm.tongDT=0,"-",_xlpm.tongTT/_xlpm.tongDT) ) ) )} -> - | G19: {=_xlfn.LET( _xlpm.colNganh,_xlfn.XMATCH("*ICB L1*",Sheet4!$1:$1,2), _xlpm.colLNST,_xlfn.XMATCH("*Lợi nhuận sau thuế*Q2*2026*",Sheet4!$1:$1,2), _xlpm.colTTLNST,_xlfn.XMATCH("*Tăng trưởng lợi nhuận sau thuế (YoY) (Quý*",Sheet4!$1:$1,2), _xlpm.nganhData,INDEX(Sheet4!$2:$1605,0,_xlpm.colNganh), _xlpm.lnstData,INDEX(Sheet4!$2:$1605,0,_xlpm.colLNST), _xlpm.ttlnstData,INDEX(Sheet4!$2:$1605,0,_xlpm.colTTLNST), _xlfn.LET( _xlpm.tongLNST,SUMPRODUCT((_xlpm.nganhData=$A19)*(_xlpm.lnstData)), _xlpm.tongTT,SUMPRODUCT((_xlpm.nganhData=$A19)*(_xlpm.lnstData)*(_xlpm.ttlnstData)), IF(_xlpm.tongLNST=0,"-",_xlpm.tongTT/_xlpm.tongLNST) ) )} -> -
A21: 📋 BẢNG KẾT QUẢ KINH DOANH CHI TIẾT CỔ PHIẾU
A22: STT | B22: Mã CP | C22: Tên công ty | D22: Sàn | E22: Vốn hóa thị trường (tỷ đồng) | F22: Ngành L1 | G22: Ngành L2 | H22: Ngành L4 | I22: DTT Q2/26 (tỷ đồng) | J22: DTT 6T/26 (tỷ đồng) | K22: TT DTT Q YoY | L22: TT DTT 6M YoY | M22: LNST Q2/26 (tỷ đồng) | N22: LNST 6T/26 (tỷ đồng) | O22: TT LNST Q YoY | P22: TT LNST 6M YoY | Q22: TT DTT QoQ | R22: TT LNST QoQ
A23: =Sheet4!A2 -> 1 | B23: =Sheet4!B2 -> AAA | C23: =Sheet4!C1 -> Tên công ty | D23: =Sheet4!D2 -> HOSE | E23: =Sheet4!AH2/1000000000 -> 2630.2014 | F23: =Sheet4!E2 -> Nguyên vật liệu | G23: =Sheet4!F2 -> Hóa chất | H23: =Sheet4!G2 -> Nhựa, cao su & sợi | I23: {=_xlfn.LET(_xlpm.colDTT,_xlfn.XMATCH("*Doanh thu thuần*Q2*2026*",Sheet4!$1:$1,2),_xlpm.colTNL,_xlfn.XMATCH("*Thu nhập lãi thuần*Quý: 2*2026*",Sheet4!$1:$1,2),_xlpm.maCP,ChiTietKQKD[[#This Row],[Mã CP]],_xlpm.nganhL1,ChiTietKQKD[[#This Row],[Ngành L1]],IF(_xlpm.nganhL1="Ngân hàng",_xlfn.LET(_xlpm.val,_xlfn.XLOOKUP(_xlpm.maCP,Sheet4!$B$2:$B$1605,INDEX(Sheet4!$2:$1605,0,_xlpm.colTNL)),IF(OR(_xlpm.val="",_xlpm.val=0),"",_xlpm.val/1000000000)),_xlfn.LET(_xlpm.val,_xlfn.XLOOKUP(_xlpm.maCP,Sheet4!$B$2:$B$1605,INDEX(Sheet4!$2:$1605,0,_xlpm.colDTT)),IF(OR(_xlpm.val="",_xlpm.val=0),"",_xlpm.val/1000000000))))} | J23: {=_xlfn.LET(_xlpm.colDTT,_xlfn.XMATCH("*Doanh thu thuần*6 tháng*2026*",Sheet4!$1:$1,2),_xlpm.colTNL,_xlfn.XMATCH("*Thu nhập lãi thuần*6 tháng*2026*",Sheet4!$1:$1,2),_xlpm.maCP,ChiTietKQKD[[#This Row],[Mã CP]],_xlpm.nganhL1,ChiTietKQKD[[#This Row],[Ngành L1]],IF(_xlpm.nganhL1="Ngân hàng",_xlfn.LET(_xlpm.val,_xlfn.XLOOKUP(_xlpm.maCP,Sheet4!$B$2:$B$1605,INDEX(Sheet4!$2:$1605,0,_xlpm.colTNL)),IF(OR(_xlpm.val="",_xlpm.val=0),"",_xlpm.val/1000000000)),_xlfn.LET(_xlpm.val,_xlfn.XLOOKUP(_xlpm.maCP,Sheet4!$B$2:$B$1605,INDEX(Sheet4!$2:$1605,0,_xlpm.colDTT)),IF(OR(_xlpm.val="",_xlpm.val=0),"",_xlpm.val/1000000000))))} | K23: {=IF(ChiTietKQKD[[#This Row],[Ngành L1]]="Ngân hàng",IF(AND(INDEX(Sheet4!$2:$1605,MATCH(ChiTietKQKD[[#This Row],[Mã CP]],Sheet4!$B$2:$B$1605,0),_xlfn.XMATCH("*Thu nhập lãi thuần*Quý: 2*2026*",Sheet4!$1:$1,2))<>0,INDEX(Sheet4!$2:$1605,MATCH(ChiTietKQKD[[#This Row],[Mã CP]],Sheet4!$B$2:$B$1605,0),_xlfn.XMATCH("*Thu nhập lãi thuần*Q2*2025*",Sheet4!$1:$1,2))<>0),INDEX(Sheet4!$2:$1605,MATCH(ChiTietKQKD[[#This Row],[Mã CP]],Sheet4!$B$2:$B$1605,0),_xlfn.XMATCH("*Thu nhập lãi thuần*Quý: 2*2026*",Sheet4!$1:$1,2))/INDEX(Sheet4!$2:$1605,MATCH(ChiTietKQKD[[#This Row],[Mã CP]],Sheet4!$B$2:$B$1605,0),_xlfn.XMATCH("*Thu nhập lãi thuần*Q2*2025*",Sheet4!$1:$1,2))-1,""),IFERROR(INDEX(Sheet4!$2:$1605,MATCH(ChiTietKQKD[[#This Row],[Mã CP]],Sheet4!$B$2:$B$1605,0),_xlfn.XMATCH("*Tăng trưởng doanh thu thuần (YoY) (Quý*",Sheet4!$1:$1,2)),""))} -> 0 | L23: {=IF(ChiTietKQKD[[#This Row],[Ngành L1]]="Ngân hàng",IF(AND(INDEX(Sheet4!$2:$1605,MATCH(ChiTietKQKD[[#This Row],[Mã CP]],Sheet4!$B$2:$B$1605,0),_xlfn.XMATCH("*Thu nhập lãi thuần*6 tháng*2026*",Sheet4!$1:$1,2))<>0,INDEX(Sheet4!$2:$1605,MATCH(ChiTietKQKD[[#This Row],[Mã CP]],Sheet4!$B$2:$B$1605,0),_xlfn.XMATCH("*Thu nhập lãi thuần*6 tháng*2025*",Sheet4!$1:$1,2))<>0),INDEX(Sheet4!$2:$1605,MATCH(ChiTietKQKD[[#This Row],[Mã CP]],Sheet4!$B$2:$B$1605,0),_xlfn.XMATCH("*Thu nhập lãi thuần*6 tháng*2026*",Sheet4!$1:$1,2))/INDEX(Sheet4!$2:$1605,MATCH(ChiTietKQKD[[#This Row],[Mã CP]],Sheet4!$B$2:$B$1605,0),_xlfn.XMATCH("*Thu nhập lãi thuần*6 tháng*2025*",Sheet4!$1:$1,2))-1,""),IFERROR(INDEX(Sheet4!$2:$1605,MATCH(ChiTietKQKD[[#This Row],[Mã CP]],Sheet4!$B$2:$B$1605,0),_xlfn.XMATCH("*Tăng trưởng doanh thu thuần (YoY) (6M)*",Sheet4!$1:$1,2)),""))} -> 0 | M23: {=_xlfn.LET(_xlpm.val,IFERROR(INDEX(Sheet4!$2:$1605,MATCH(ChiTietKQKD[[#This Row],[Mã CP]],Sheet4!$B$2:$B$1605,0),_xlfn.XMATCH("*Lợi nhuận sau thuế*Q2*2026*",Sheet4!$1:$1,2)),0),IF(OR(_xlpm.val="",_xlpm.val=0),"",_xlpm.val/1000000000))} | N23: {=_xlfn.LET(_xlpm.val,IFERROR(INDEX(Sheet4!$2:$1605,MATCH(ChiTietKQKD[[#This Row],[Mã CP]],Sheet4!$B$2:$B$1605,0),_xlfn.XMATCH("*Lợi nhuận sau thuế*6 tháng*2026*",Sheet4!$1:$1,2)),0),IF(OR(_xlpm.val="",_xlpm.val=0),"",_xlpm.val/1000000000))} | O23: {=IFERROR(INDEX(Sheet4!$2:$1605,MATCH(ChiTietKQKD[[#This Row],[Mã CP]],Sheet4!$B$2:$B$1605,0),_xlfn.XMATCH("*Tăng trưởng lợi nhuận sau thuế (YoY) (Quý*",Sheet4!$1:$1,2)),"")} -> 0 | P23: {=IFERROR(INDEX(Sheet4!$2:$1605,MATCH(ChiTietKQKD[[#This Row],[Mã CP]],Sheet4!$B$2:$B$1605,0),_xlfn.XMATCH("*Tăng trưởng lợi nhuận sau thuế (YoY) (6M)*",Sheet4!$1:$1,2)),"")} -> 0 | Q23: {=IFERROR(INDEX(Sheet4!$2:$1605,MATCH(ChiTietKQKD[[#This Row],[Mã CP]],Sheet4!$B$2:$B$1605,0),_xlfn.XMATCH("*Tăng trưởng doanh thu thuần (QoQ)*",Sheet4!$1:$1,2)),"")} -> 0 | R23: {=IFERROR(INDEX(Sheet4!$2:$1605,MATCH(ChiTietKQKD[[#This Row],[Mã CP]],Sheet4!$B$2:$B$1605,0),_xlfn.XMATCH("*Tăng trưởng lợi nhuận sau thuế (QoQ)*",Sheet4!$1:$1,2)),"")} -> 0
A24: =Sheet4!A3 -> 2 | B24: =Sheet4!B3 -> AAM | C24: =Sheet4!C2 -> An Phát Bioplastics | D24: =Sheet4!D3 -> HOSE | E24: =Sheet4!AH3/1000000000 -> 68.455242 | F24: =Sheet4!E3 -> Hàng Tiêu dùng | G24: =Sheet4!F3 -> Thực phẩm và đồ uống | H24: =Sheet4!G3 -> Nuôi trồng nông & hải sản | I24: {=_xlfn.LET(_xlpm.colDTT,_xlfn.XMATCH("*Doanh thu thuần*Q2*2026*",Sheet4!$1:$1,2),_xlpm.colTNL,_xlfn.XMATCH("*Thu nhập lãi thuần*Quý: 2*2026*",Sheet4!$1:$1,2),_xlpm.maCP,ChiTietKQKD[[#This Row],[Mã CP]],_xlpm.nganhL1,ChiTietKQKD[[#This Row],[Ngành L1]],IF(_xlpm.nganhL1="Ngân hàng",_xlfn.LET(_xlpm.val,_xlfn.XLOOKUP(_xlpm.maCP,Sheet4!$B$2:$B$1605,INDEX(Sheet4!$2:$1605,0,_xlpm.colTNL)),IF(OR(_xlpm.val="",_xlpm.val=0),"",_xlpm.val/1000000000)),_xlfn.LET(_xlpm.val,_xlfn.XLOOKUP(_xlpm.maCP,Sheet4!$B$2:$B$1605,INDEX(Sheet4!$2:$1605,0,_xlpm.colDTT)),IF(OR(_xlpm.val="",_xlpm.val=0),"",_xlpm.val/1000000000))))} -> 16.795302 | J24: {=_xlfn.LET(_xlpm.colDTT,_xlfn.XMATCH("*Doanh thu thuần*6 tháng*2026*",Sheet4!$1:$1,2),_xlpm.colTNL,_xlfn.XMATCH("*Thu nhập lãi thuần*6 tháng*2026*",Sheet4!$1:$1,2),_xlpm.maCP,ChiTietKQKD[[#This Row],[Mã CP]],_xlpm.nganhL1,ChiTietKQKD[[#This Row],[Ngành L1]],IF(_xlpm.nganhL1="Ngân hàng",_xlfn.LET(_xlpm.val,_xlfn.XLOOKUP(_xlpm.maCP,Sheet4!$B$2:$B$1605,INDEX(Sheet4!$2:$1605,0,_xlpm.colTNL)),IF(OR(_xlpm.val="",_xlpm.val=0),"",_xlpm.val/1000000000)),_xlfn.LET(_xlpm.val,_xlfn.XLOOKUP(_xlpm.maCP,Sheet4!$B$2:$B$1605,INDEX(Sheet4!$2:$1605,0,_xlpm.colDTT)),IF(OR(_xlpm.val="",_xlpm.val=0),"",_xlpm.val/1000000000))))} -> 50.239307 | K24: {=IF(ChiTietKQKD[[#This Row],[Ngành L1]]="Ngân hàng",IF(AND(INDEX(Sheet4!$2:$1605,MATCH(ChiTietKQKD[[#This Row],[Mã CP]],Sheet4!$B$2:$B$1605,0),_xlfn.XMATCH("*Thu nhập lãi thuần*Quý: 2*2026*",Sheet4!$1:$1,2))<>0,INDEX(Sheet4!$2:$1605,MATCH(ChiTietKQKD[[#This Row],[Mã CP]],Sheet4!$B$2:$B$1605,0),_xlfn.XMATCH("*Thu nhập lãi thuần*Q2*2025*",Sheet4!$1:$1,2))<>0),INDEX(Sheet4!$2:$1605,MATCH(ChiTietKQKD[[#This Row],[Mã CP]],Sheet4!$B$2:$B$1605,0),_xlfn.XMATCH("*Thu nhập lãi thuần*Quý: 2*2026*",Sheet4!$1:$1,2))/INDEX(Sheet4!$2:$1605,MATCH(ChiTietKQKD[[#This Row],[Mã CP]],Sheet4!$B$2:$B$1605,0),_xlfn.XMATCH("*Thu nhập lãi thuần*Q2*2025*",Sheet4!$1:$1,2))-1,""),IFERROR(INDEX(Sheet4!$2:$1605,MATCH(ChiTietKQKD[[#This Row],[Mã CP]],Sheet4!$B$2:$B$1605,0),_xlfn.XMATCH("*Tăng trưởng doanh thu thuần (YoY) (Quý*",Sheet4!$1:$1,2)),""))} -> -0.7389 | L24: {=IF(ChiTietKQKD[[#This Row],[Ngành L1]]="Ngân hàng",IF(AND(INDEX(Sheet4!$2:$1605,MATCH(ChiTietKQKD[[#This Row],[Mã CP]],Sheet4!$B$2:$B$1605,0),_xlfn.XMATCH("*Thu nhập lãi thuần*6 tháng*2026*",Sheet4!$1:$1,2))<>0,INDEX(Sheet4!$2:$1605,MATCH(ChiTietKQKD[[#This Row],[Mã CP]],Sheet4!$B$2:$B$1605,0),_xlfn.XMATCH("*Thu nhập lãi thuần*6 tháng*2025*",Sheet4!$1:$1,2))<>0),INDEX(Sheet4!$2:$1605,MATCH(ChiTietKQKD[[#This Row],[Mã CP]],Sheet4!$B$2:$B$1605,0),_xlfn.XMATCH("*Thu nhập lãi thuần*6 tháng*2026*",Sheet4!$1:$1,2))/INDEX(Sheet4!$2:$1605,MATCH(ChiTietKQKD[[#This Row],[Mã CP]],Sheet4!$B$2:$B$1605,0),_xlfn.XMATCH("*Thu nhập lãi thuần*6 tháng*2025*",Sheet4!$1:$1,2))-1,""),IFERROR(INDEX(Sheet4!$2:$1605,MATCH(ChiTietKQKD[[#This Row],[Mã CP]],Sheet4!$B$2:$B$1605,0),_xlfn.XMATCH("*Tăng trưởng doanh thu thuần (YoY) (6M)*",Sheet4!$1:$1,2)),""))} -> -0.5767 | M24: {=_xlfn.LET(_xlpm.val,IFERROR(INDEX(Sheet4!$2:$1605,MATCH(ChiTietKQKD[[#This Row],[Mã CP]],Sheet4!$B$2:$B$1605,0),_xlfn.XMATCH("*Lợi nhuận sau thuế*Q2*2026*",Sheet4!$1:$1,2)),0),IF(OR(_xlpm.val="",_xlpm.val=0),"",_xlpm.val/1000000000))} -> 3.3907519 | N24: {=_xlfn.LET(_xlpm.val,IFERROR(INDEX(Sheet4!$2:$1605,MATCH(ChiTietKQKD[[#This Row],[Mã CP]],Sheet4!$B$2:$B$1605,0),_xlfn.XMATCH("*Lợi nhuận sau thuế*6 tháng*2026*",Sheet4!$1:$1,2)),0),IF(OR(_xlpm.val="",_xlpm.val=0),"",_xlpm.val/1000000000))} -> 5.7783557 | O24: {=IFERROR(INDEX(Sheet4!$2:$1605,MATCH(ChiTietKQKD[[#This Row],[Mã CP]],Sheet4!$B$2:$B$1605,0),_xlfn.XMATCH("*Tăng trưởng lợi nhuận sau thuế (YoY) (Quý*",Sheet4!$1:$1,2)),"")} -> 2.0053 | P24: {=IFERROR(INDEX(Sheet4!$2:$1605,MATCH(ChiTietKQKD[[#This Row],[Mã CP]],Sheet4!$B$2:$B$1605,0),_xlfn.XMATCH("*Tăng trưởng lợi nhuận sau thuế (YoY) (6M)*",Sheet4!$1:$1,2)),"")} -> 1.4728 | Q24: {=IFERROR(INDEX(Sheet4!$2:$1605,MATCH(ChiTietKQKD[[#This Row],[Mã CP]],Sheet4!$B$2:$B$1605,0),_xlfn.XMATCH("*Tăng trưởng doanh thu thuần (QoQ)*",Sheet4!$1:$1,2)),"")} -> -0.4978 | R24: {=IFERROR(INDEX(Sheet4!$2:$1605,MATCH(ChiTietKQKD[[#This Row],[Mã CP]],Sheet4!$B$2:$B$1605,0),_xlfn.XMATCH("*Tăng trưởng lợi nhuận sau thuế (QoQ)*",Sheet4!$1:$1,2)),"")} -> 0.4201
A25: =Sheet4!A4 -> 3 | B25: =Sheet4!B4 -> AAN | C25: =Sheet4!C3 -> Thủy sản Mekong | D25: =Sheet4!D4 -> HOSE | E25: =Sheet4!AH4/1000000000 -> 1388.4968 | F25: =Sheet4!E4 -> Hàng Tiêu dùng | G25: =Sheet4!F4 -> Thực phẩm và đồ uống | H25: =Sheet4!G4 -> Nuôi trồng nông & hải sản | I25: {=_xlfn.LET(_xlpm.colDTT,_xlfn.XMATCH("*Doanh thu thuần*Q2*2026*",Sheet4!$1:$1,2),_xlpm.colTNL,_xlfn.XMATCH("*Thu nhập lãi thuần*Quý: 2*2026*",Sheet4!$1:$1,2),_xlpm.maCP,ChiTietKQKD[[#This Row],[Mã CP]],_xlpm.nganhL1,ChiTietKQKD[[#This Row],[Ngành L1]],IF(_xlpm.nganhL1="Ngân hàng",_xlfn.LET(_xlpm.val,_xlfn.XLOOKUP(_xlpm.maCP,Sheet4!$B$2:$B$1605,INDEX(Sheet4!$2:$1605,0,_xlpm.colTNL)),IF(OR(_xlpm.val="",_xlpm.val=0),"",_xlpm.val/1000000000)),_xlfn.LET(_xlpm.val,_xlfn.XLOOKUP(_xlpm.maCP,Sheet4!$B$2:$B$1605,INDEX(Sheet4!$2:$1605,0,_xlpm.colDTT)),IF(OR(_xlpm.val="",_xlpm.val=0),"",_xlpm.val/1000000000))))} | J25: {=_xlfn.LET(_xlpm.colDTT,_xlfn.XMATCH("*Doanh thu thuần*6 tháng*2026*",Sheet4!$1:$1,2),_xlpm.colTNL,_xlfn.XMATCH("*Thu nhập lãi thuần*6 tháng*2026*",Sheet4!$1:$1,2),_xlpm.maCP,ChiTietKQKD[[#This Row],[Mã CP]],_xlpm.nganhL1,ChiTietKQKD[[#This Row],[Ngành L1]],IF(_xlpm.nganhL1="Ngân hàng",_xlfn.LET(_xlpm.val,_xlfn.XLOOKUP(_xlpm.maCP,Sheet4!$B$2:$B$1605,INDEX(Sheet4!$2:$1605,0,_xlpm.colTNL)),IF(OR(_xlpm.val="",_xlpm.val=0),"",_xlpm.val/1000000000)),_xlfn.LET(_xlpm.val,_xlfn.XLOOKUP(_xlpm.maCP,Sheet4!$B$2:$B$1605,INDEX(Sheet4!$2:$1605,0,_xlpm.colDTT)),IF(OR(_xlpm.val="",_xlpm.val=0),"",_xlpm.val/1000000000))))} | K25: {=IF(ChiTietKQKD[[#This Row],[Ngành L1]]="Ngân hàng",IF(AND(INDEX(Sheet4!$2:$1605,MATCH(ChiTietKQKD[[#This Row],[Mã CP]],Sheet4!$B$2:$B$1605,0),_xlfn.XMATCH("*Thu nhập lãi thuần*Quý: 2*2026*",Sheet4!$1:$1,2))<>0,INDEX(Sheet4!$2:$1605,MATCH(ChiTietKQKD[[#This Row],[Mã CP]],Sheet4!$B$2:$B$1605,0),_xlfn.XMATCH("*Thu nhập lãi thuần*Q2*2025*",Sheet4!$1:$1,2))<>0),INDEX(Sheet4!$2:$1605,MATCH(ChiTietKQKD[[#This Row],[Mã CP]],Sheet4!$B$2:$B$1605,0),_xlfn.XMATCH("*Thu nhập lãi thuần*Quý: 2*2026*",Sheet4!$1:$1,2))/INDEX(Sheet4!$2:$1605,MATCH(ChiTietKQKD[[#This Row],[Mã CP]],Sheet4!$B$2:$B$1605,0),_xlfn.XMATCH("*Thu nhập lãi thuần*Q2*2025*",Sheet4!$1:$1,2))-1,""),IFERROR(INDEX(Sheet4!$2:$1605,MATCH(ChiTietKQKD[[#This Row],[Mã CP]],Sheet4!$B$2:$B$1605,0),_xlfn.XMATCH("*Tăng trưởng doanh thu thuần (YoY) (Quý*",Sheet4!$1:$1,2)),""))} -> 0 | L25: {=IF(ChiTietKQKD[[#This Row],[Ngành L1]]="Ngân hàng",IF(AND(INDEX(Sheet4!$2:$1605,MATCH(ChiTietKQKD[[#This Row],[Mã CP]],Sheet4!$B$2:$B$1605,0),_xlfn.XMATCH("*Thu nhập lãi thuần*6 tháng*2026*",Sheet4!$1:$1,2))<>0,INDEX(Sheet4!$2:$1605,MATCH(ChiTietKQKD[[#This Row],[Mã CP]],Sheet4!$B$2:$B$1605,0),_xlfn.XMATCH("*Thu nhập lãi thuần*6 tháng*2025*",Sheet4!$1:$1,2))<>0),INDEX(Sheet4!$2:$1605,MATCH(ChiTietKQKD[[#This Row],[Mã CP]],Sheet4!$B$2:$B$1605,0),_xlfn.XMATCH("*Thu nhập lãi thuần*6 tháng*2026*",Sheet4!$1:$1,2))/INDEX(Sheet4!$2:$1605,MATCH(ChiTietKQKD[[#This Row],[Mã CP]],Sheet4!$B$2:$B$1605,0),_xlfn.XMATCH("*Thu nhập lãi thuần*6 tháng*2025*",Sheet4!$1:$1,2))-1,""),IFERROR(INDEX(Sheet4!$2:$1605,MATCH(ChiTietKQKD[[#This Row],[Mã CP]],Sheet4!$B$2:$B$1605,0),_xlfn.XMATCH("*Tăng trưởng doanh thu thuần (YoY) (6M)*",Sheet4!$1:$1,2)),""))} -> 0 | M25: {=_xlfn.LET(_xlpm.val,IFERROR(INDEX(Sheet4!$2:$1605,MATCH(ChiTietKQKD[[#This Row],[Mã CP]],Sheet4!$B$2:$B$1605,0),_xlfn.XMATCH("*Lợi nhuận sau thuế*Q2*2026*",Sheet4!$1:$1,2)),0),IF(OR(_xlpm.val="",_xlpm.val=0),"",_xlpm.val/1000000000))} | N25: {=_xlfn.LET(_xlpm.val,IFERROR(INDEX(Sheet4!$2:$1605,MATCH(ChiTietKQKD[[#This Row],[Mã CP]],Sheet4!$B$2:$B$1605,0),_xlfn.XMATCH("*Lợi nhuận sau thuế*6 tháng*2026*",Sheet4!$1:$1,2)),0),IF(OR(_xlpm.val="",_xlpm.val=0),"",_xlpm.val/1000000000))} | O25: {=IFERROR(INDEX(Sheet4!$2:$1605,MATCH(ChiTietKQKD[[#This Row],[Mã CP]],Sheet4!$B$2:$B$1605,0),_xlfn.XMATCH("*Tăng trưởng lợi nhuận sau thuế (YoY) (Quý*",Sheet4!$1:$1,2)),"")} -> 0 | P25: {=IFERROR(INDEX(Sheet4!$2:$1605,MATCH(ChiTietKQKD[[#This Row],[Mã CP]],Sheet4!$B$2:$B$1605,0),_xlfn.XMATCH("*Tăng trưởng lợi nhuận sau thuế (YoY) (6M)*",Sheet4!$1:$1,2)),"")} -> 0 | Q25: {=IFERROR(INDEX(Sheet4!$2:$1605,MATCH(ChiTietKQKD[[#This Row],[Mã CP]],Sheet4!$B$2:$B$1605,0),_xlfn.XMATCH("*Tăng trưởng doanh thu thuần (QoQ)*",Sheet4!$1:$1,2)),"")} -> 0 | R25: {=IFERROR(INDEX(Sheet4!$2:$1605,MATCH(ChiTietKQKD[[#This Row],[Mã CP]],Sheet4!$B$2:$B$1605,0),_xlfn.XMATCH("*Tăng trưởng lợi nhuận sau thuế (QoQ)*",Sheet4!$1:$1,2)),"")} -> 0
A26: =Sheet4!A5 -> 4 | B26: =Sheet4!B5 -> AAT | C26: =Sheet4!C4 -> Lương thực A An | D26: =Sheet4!D5 -> HOSE | E26: =Sheet4!AH5/1000000000 -> 182.71329 | F26: =Sheet4!E5 -> Hàng Tiêu dùng | G26: =Sheet4!F5 -> Hàng cá nhân & Gia dụng | H26: =Sheet4!G5 -> Hàng May mặc | I26: {=_xlfn.LET(_xlpm.colDTT,_xlfn.XMATCH("*Doanh thu thuần*Q2*2026*",Sheet4!$1:$1,2),_xlpm.colTNL,_xlfn.XMATCH("*Thu nhập lãi thuần*Quý: 2*2026*",Sheet4!$1:$1,2),_xlpm.maCP,ChiTietKQKD[[#This Row],[Mã CP]],_xlpm.nganhL1,ChiTietKQKD[[#This Row],[Ngành L1]],IF(_xlpm.nganhL1="Ngân hàng",_xlfn.LET(_xlpm.val,_xlfn.XLOOKUP(_xlpm.maCP,Sheet4!$B$2:$B$1605,INDEX(Sheet4!$2:$1605,0,_xlpm.colTNL)),IF(OR(_xlpm.val="",_xlpm.val=0),"",_xlpm.val/1000000000)),_xlfn.LET(_xlpm.val,_xlfn.XLOOKUP(_xlpm.maCP,Sheet4!$B$2:$B$1605,INDEX(Sheet4!$2:$1605,0,_xlpm.colDTT)),IF(OR(_xlpm.val="",_xlpm.val=0),"",_xlpm.val/1000000000))))} | J26: {=_xlfn.LET(_xlpm.colDTT,_xlfn.XMATCH("*Doanh thu thuần*6 tháng*2026*",Sheet4!$1:$1,2),_xlpm.colTNL,_xlfn.XMATCH("*Thu nhập lãi thuần*6 tháng*2026*",Sheet4!$1:$1,2),_xlpm.maCP,ChiTietKQKD[[#This Row],[Mã CP]],_xlpm.nganhL1,ChiTietKQKD[[#This Row],[Ngành L1]],IF(_xlpm.nganhL1="Ngân hàng",_xlfn.LET(_xlpm.val,_xlfn.XLOOKUP(_xlpm.maCP,Sheet4!$B$2:$B$1605,INDEX(Sheet4!$2:$1605,0,_xlpm.colTNL)),IF(OR(_xlpm.val="",_xlpm.val=0),"",_xlpm.val/1000000000)),_xlfn.LET(_xlpm.val,_xlfn.XLOOKUP(_xlpm.maCP,Sheet4!$B$2:$B$1605,INDEX(Sheet4!$2:$1605,0,_xlpm.colDTT)),IF(OR(_xlpm.val="",_xlpm.val=0),"",_xlpm.val/1000000000))))} | K26: {=IF(ChiTietKQKD[[#This Row],[Ngành L1]]="Ngân hàng",IF(AND(INDEX(Sheet4!$2:$1605,MATCH(ChiTietKQKD[[#This Row],[Mã CP]],Sheet4!$B$2:$B$1605,0),_xlfn.XMATCH("*Thu nhập lãi thuần*Quý: 2*2026*",Sheet4!$1:$1,2))<>0,INDEX(Sheet4!$2:$1605,MATCH(ChiTietKQKD[[#This Row],[Mã CP]],Sheet4!$B$2:$B$1605,0),_xlfn.XMATCH("*Thu nhập lãi thuần*Q2*2025*",Sheet4!$1:$1,2))<>0),INDEX(Sheet4!$2:$1605,MATCH(ChiTietKQKD[[#This Row],[Mã CP]],Sheet4!$B$2:$B$1605,0),_xlfn.XMATCH("*Thu nhập lãi thuần*Quý: 2*2026*",Sheet4!$1:$1,2))/INDEX(Sheet4!$2:$1605,MATCH(ChiTietKQKD[[#This Row],[Mã CP]],Sheet4!$B$2:$B$1605,0),_xlfn.XMATCH("*Thu nhập lãi thuần*Q2*2025*",Sheet4!$1:$1,2))-1,""),IFERROR(INDEX(Sheet4!$2:$1605,MATCH(ChiTietKQKD[[#This Row],[Mã CP]],Sheet4!$B$2:$B$1605,0),_xlfn.XMATCH("*Tăng trưởng doanh thu thuần (YoY) (Quý*",Sheet4!$1:$1,2)),""))} -> 0 | L26: {=IF(ChiTietKQKD[[#This Row],[Ngành L1]]="Ngân hàng",IF(AND(INDEX(Sheet4!$2:$1605,MATCH(ChiTietKQKD[[#This Row],[Mã CP]],Sheet4!$B$2:$B$1605,0),_xlfn.XMATCH("*Thu nhập lãi thuần*6 tháng*2026*",Sheet4!$1:$1,2))<>0,INDEX(Sheet4!$2:$1605,MATCH(ChiTietKQKD[[#This Row],[Mã CP]],Sheet4!$B$2:$B$1605,0),_xlfn.XMATCH("*Thu nhập lãi thuần*6 tháng*2025*",Sheet4!$1:$1,2))<>0),INDEX(Sheet4!$2:$1605,MATCH(ChiTietKQKD[[#This Row],[Mã CP]],Sheet4!$B$2:$B$1605,0),_xlfn.XMATCH("*Thu nhập lãi thuần*6 tháng*2026*",Sheet4!$1:$1,2))/INDEX(Sheet4!$2:$1605,MATCH(ChiTietKQKD[[#This Row],[Mã CP]],Sheet4!$B$2:$B$1605,0),_xlfn.XMATCH("*Thu nhập lãi thuần*6 tháng*2025*",Sheet4!$1:$1,2))-1,""),IFERROR(INDEX(Sheet4!$2:$1605,MATCH(ChiTietKQKD[[#This Row],[Mã CP]],Sheet4!$B$2:$B$1605,0),_xlfn.XMATCH("*Tăng trưởng doanh thu thuần (YoY) (6M)*",Sheet4!$1:$1,2)),""))} -> 0 | M26: {=_xlfn.LET(_xlpm.val,IFERROR(INDEX(Sheet4!$2:$1605,MATCH(ChiTietKQKD[[#This Row],[Mã CP]],Sheet4!$B$2:$B$1605,0),_xlfn.XMATCH("*Lợi nhuận sau thuế*Q2*2026*",Sheet4!$1:$1,2)),0),IF(OR(_xlpm.val="",_xlpm.val=0),"",_xlpm.val/1000000000))} | N26: {=_xlfn.LET(_xlpm.val,IFERROR(INDEX(Sheet4!$2:$1605,MATCH(ChiTietKQKD[[#This Row],[Mã CP]],Sheet4!$B$2:$B$1605,0),_xlfn.XMATCH("*Lợi nhuận sau thuế*6 tháng*2026*",Sheet4!$1:$1,2)),0),IF(OR(_xlpm.val="",_xlpm.val=0),"",_xlpm.val/1000000000))} | O26: {=IFERROR(INDEX(Sheet4!$2:$1605,MATCH(ChiTietKQKD[[#This Row],[Mã CP]],Sheet4!$B$2:$B$1605,0),_xlfn.XMATCH("*Tăng trưởng lợi nhuận sau thuế (YoY) (Quý*",Sheet4!$1:$1,2)),"")} -> 0 | P26: {=IFERROR(INDEX(Sheet4!$2:$1605,MATCH(ChiTietKQKD[[#This Row],[Mã CP]],Sheet4!$B$2:$B$1605,0),_xlfn.XMATCH("*Tăng trưởng lợi nhuận sau thuế (YoY) (6M)*",Sheet4!$1:$1,2)),"")} -> 0 | Q26: {=IFERROR(INDEX(Sheet4!$2:$1605,MATCH(ChiTietKQKD[[#This Row],[Mã CP]],Sheet4!$B$2:$B$1605,0),_xlfn.XMATCH("*Tăng trưởng doanh thu thuần (QoQ)*",Sheet4!$1:$1,2)),"")} -> 0 | R26: {=IFERROR(INDEX(Sheet4!$2:$1605,MATCH(ChiTietKQKD[[#This Row],[Mã CP]],Sheet4!$B$2:$B$1605,0),_xlfn.XMATCH("*Tăng trưởng lợi nhuận sau thuế (QoQ)*",Sheet4!$1:$1,2)),"")} -> 0
A27: =Sheet4!A6 -> 5 | B27: =Sheet4!B6 -> ABR | C27: =Sheet4!C5 -> Tập đoàn Tiên Sơn Thanh Hóa | D27: =Sheet4!D6 -> HOSE | E27: =Sheet4!AH6/1000000000 -> 231 | F27: =Sheet4!E6 -> Công nghiệp | G27: =Sheet4!F6 -> Hàng & Dịch vụ Công nghiệp | H27: =Sheet4!G6 -> Tư vấn & Hỗ trợ KD | I27: {=_xlfn.LET(_xlpm.colDTT,_xlfn.XMATCH("*Doanh thu thuần*Q2*2026*",Sheet4!$1:$1,2),_xlpm.colTNL,_xlfn.XMATCH("*Thu nhập lãi thuần*Quý: 2*2026*",Sheet4!$1:$1,2),_xlpm.maCP,ChiTietKQKD[[#This Row],[Mã CP]],_xlpm.nganhL1,ChiTietKQKD[[#This Row],[Ngành L1]],IF(_xlpm.nganhL1="Ngân hàng",_xlfn.LET(_xlpm.val,_xlfn.XLOOKUP(_xlpm.maCP,Sheet4!$B$2:$B$1605,INDEX(Sheet4!$2:$1605,0,_xlpm.colTNL)),IF(OR(_xlpm.val="",_xlpm.val=0),"",_xlpm.val/1000000000)),_xlfn.LET(_xlpm.val,_xlfn.XLOOKUP(_xlpm.maCP,Sheet4!$B$2:$B$1605,INDEX(Sheet4!$2:$1605,0,_xlpm.colDTT)),IF(OR(_xlpm.val="",_xlpm.val=0),"",_xlpm.val/1000000000))))} -> 6.2765263 | J27: {=_xlfn.LET(_xlpm.colDTT,_xlfn.XMATCH("*Doanh thu thuần*6 tháng*2026*",Sheet4!$1:$1,2),_xlpm.colTNL,_xlfn.XMATCH("*Thu nhập lãi thuần*6 tháng*2026*",Sheet4!$1:$1,2),_xlpm.maCP,ChiTietKQKD[[#This Row],[Mã CP]],_xlpm.nganhL1,ChiTietKQKD[[#This Row],[Ngành L1]],IF(_xlpm.nganhL1="Ngân hàng",_xlfn.LET(_xlpm.val,_xlfn.XLOOKUP(_xlpm.maCP,Sheet4!$B$2:$B$1605,INDEX(Sheet4!$2:$1605,0,_xlpm.colTNL)),IF(OR(_xlpm.val="",_xlpm.val=0),"",_xlpm.val/1000000000)),_xlfn.LET(_xlpm.val,_xlfn.XLOOKUP(_xlpm.maCP,Sheet4!$B$2:$B$1605,INDEX(Sheet4!$2:$1605,0,_xlpm.colDTT)),IF(OR(_xlpm.val="",_xlpm.val=0),"",_xlpm.val/1000000000))))} -> 12.611617 | K27: {=IF(ChiTietKQKD[[#This Row],[Ngành L1]]="Ngân hàng",IF(AND(INDEX(Sheet4!$2:$1605,MATCH(ChiTietKQKD[[#This Row],[Mã CP]],Sheet4!$B$2:$B$1605,0),_xlfn.XMATCH("*Thu nhập lãi thuần*Quý: 2*2026*",Sheet4!$1:$1,2))<>0,INDEX(Sheet4!$2:$1605,MATCH(ChiTietKQKD[[#This Row],[Mã CP]],Sheet4!$B$2:$B$1605,0),_xlfn.XMATCH("*Thu nhập lãi thuần*Q2*2025*",Sheet4!$1:$1,2))<>0),INDEX(Sheet4!$2:$1605,MATCH(ChiTietKQKD[[#This Row],[Mã CP]],Sheet4!$B$2:$B$1605,0),_xlfn.XMATCH("*Thu nhập lãi thuần*Quý: 2*2026*",Sheet4!$1:$1,2))/INDEX(Sheet4!$2:$1605,MATCH(ChiTietKQKD[[#This Row],[Mã CP]],Sheet4!$B$2:$B$1605,0),_xlfn.XMATCH("*Thu nhập lãi thuần*Q2*2025*",Sheet4!$1:$1,2))-1,""),IFERROR(INDEX(Sheet4!$2:$1605,MATCH(ChiTietKQKD[[#This Row],[Mã CP]],Sheet4!$B$2:$B$1605,0),_xlfn.XMATCH("*Tăng trưởng doanh thu thuần (YoY) (Quý*",Sheet4!$1:$1,2)),""))} -> 0.0026 | L27: {=IF(ChiTietKQKD[[#This Row],[Ngành L1]]="Ngân hàng",IF(AND(INDEX(Sheet4!$2:$1605,MATCH(ChiTietKQKD[[#This Row],[Mã CP]],Sheet4!$B$2:$B$1605,0),_xlfn.XMATCH("*Thu nhập lãi thuần*6 tháng*2026*",Sheet4!$1:$1,2))<>0,INDEX(Sheet4!$2:$1605,MATCH(ChiTietKQKD[[#This Row],[Mã CP]],Sheet4!$B$2:$B$1605,0),_xlfn.XMATCH("*Thu nhập lãi thuần*6 tháng*2025*",Sheet4!$1:$1,2))<>0),INDEX(Sheet4!$2:$1605,MATCH(ChiTietKQKD[[#This Row],[Mã CP]],Sheet4!$B$2:$B$1605,0),_xlfn.XMATCH("*Thu nhập lãi thuần*6 tháng*2026*",Sheet4!$1:$1,2))/INDEX(Sheet4!$2:$1605,MATCH(ChiTietKQKD[[#This Row],[Mã CP]],Sheet4!$B$2:$B$1605,0),_xlfn.XMATCH("*Thu nhập lãi thuần*6 tháng*2025*",Sheet4!$1:$1,2))-1,""),IFERROR(INDEX(Sheet4!$2:$1605,MATCH(ChiTietKQKD[[#This Row],[Mã CP]],Sheet4!$B$2:$B$1605,0),_xlfn.XMATCH("*Tăng trưởng doanh thu thuần (YoY) (6M)*",Sheet4!$1:$1,2)),""))} -> -0.1103 | M27: {=_xlfn.LET(_xlpm.val,IFERROR(INDEX(Sheet4!$2:$1605,MATCH(ChiTietKQKD[[#This Row],[Mã CP]],Sheet4!$B$2:$B$1605,0),_xlfn.XMATCH("*Lợi nhuận sau thuế*Q2*2026*",Sheet4!$1:$1,2)),0),IF(OR(_xlpm.val="",_xlpm.val=0),"",_xlpm.val/1000000000))} -> 5.1841274 | N27: {=_xlfn.LET(_xlpm.val,IFERROR(INDEX(Sheet4!$2:$1605,MATCH(ChiTietKQKD[[#This Row],[Mã CP]],Sheet4!$B$2:$B$1605,0),_xlfn.XMATCH("*Lợi nhuận sau thuế*6 tháng*2026*",Sheet4!$1:$1,2)),0),IF(OR(_xlpm.val="",_xlpm.val=0),"",_xlpm.val/1000000000))} -> 7.5547323 | O27: {=IFERROR(INDEX(Sheet4!$2:$1605,MATCH(ChiTietKQKD[[#This Row],[Mã CP]],Sheet4!$B$2:$B$1605,0),_xlfn.XMATCH("*Tăng trưởng lợi nhuận sau thuế (YoY) (Quý*",Sheet4!$1:$1,2)),"")} -> 0.5608 | P27: {=IFERROR(INDEX(Sheet4!$2:$1605,MATCH(ChiTietKQKD[[#This Row],[Mã CP]],Sheet4!$B$2:$B$1605,0),_xlfn.XMATCH("*Tăng trưởng lợi nhuận sau thuế (YoY) (6M)*",Sheet4!$1:$1,2)),"")} -> -0.0495 | Q27: {=IFERROR(INDEX(Sheet4!$2:$1605,MATCH(ChiTietKQKD[[#This Row],[Mã CP]],Sheet4!$B$2:$B$1605,0),_xlfn.XMATCH("*Tăng trưởng doanh thu thuần (QoQ)*",Sheet4!$1:$1,2)),"")} -> -0.0092 | R27: {=IFERROR(INDEX(Sheet4!$2:$1605,MATCH(ChiTietKQKD[[#This Row],[Mã CP]],Sheet4!$B$2:$B$1605,0),_xlfn.XMATCH("*Tăng trưởng lợi nhuận sau thuế (QoQ)*",Sheet4!$1:$1,2)),"")} -> 1.1868
A28: =Sheet4!A7 -> 6 | B28: =Sheet4!B7 -> ABS | C28: =Sheet4!C6 -> Đầu tư Nhãn Hiệu Việt | D28: =Sheet4!D7 -> HOSE | E28: =Sheet4!AH7/1000000000 -> 248 | F28: =Sheet4!E7 -> Nguyên vật liệu | G28: =Sheet4!F7 -> Hóa chất | H28: =Sheet4!G7 -> Sản phẩm hóa dầu, Nông dược & Hóa chất khác | I28: {=_xlfn.LET(_xlpm.colDTT,_xlfn.XMATCH("*Doanh thu thuần*Q2*2026*",Sheet4!$1:$1,2),_xlpm.colTNL,_xlfn.XMATCH("*Thu nhập lãi thuần*Quý: 2*2026*",Sheet4!$1:$1,2),_xlpm.maCP,ChiTietKQKD[[#This Row],[Mã CP]],_xlpm.nganhL1,ChiTietKQKD[[#This Row],[Ngành L1]],IF(_xlpm.nganhL1="Ngân hàng",_xlfn.LET(_xlpm.val,_xlfn.XLOOKUP(_xlpm.maCP,Sheet4!$B$2:$B$1605,INDEX(Sheet4!$2:$1605,0,_xlpm.colTNL)),IF(OR(_xlpm.val="",_xlpm.val=0),"",_xlpm.val/1000000000)),_xlfn.LET(_xlpm.val,_xlfn.XLOOKUP(_xlpm.maCP,Sheet4!$B$2:$B$1605,INDEX(Sheet4!$2:$1605,0,_xlpm.colDTT)),IF(OR(_xlpm.val="",_xlpm.val=0),"",_xlpm.val/1000000000))))} -> 70.347608 | J28: {=_xlfn.LET(_xlpm.colDTT,_xlfn.XMATCH("*Doanh thu thuần*6 tháng*2026*",Sheet4!$1:$1,2),_xlpm.colTNL,_xlfn.XMATCH("*Thu nhập lãi thuần*6 tháng*2026*",Sheet4!$1:$1,2),_xlpm.maCP,ChiTietKQKD[[#This Row],[Mã CP]],_xlpm.nganhL1,ChiTietKQKD[[#This Row],[Ngành L1]],IF(_xlpm.nganhL1="Ngân hàng",_xlfn.LET(_xlpm.val,_xlfn.XLOOKUP(_xlpm.maCP,Sheet4!$B$2:$B$1605,INDEX(Sheet4!$2:$1605,0,_xlpm.colTNL)),IF(OR(_xlpm.val="",_xlpm.val=0),"",_xlpm.val/1000000000)),_xlfn.LET(_xlpm.val,_xlfn.XLOOKUP(_xlpm.maCP,Sheet4!$B$2:$B$1605,INDEX(Sheet4!$2:$1605,0,_xlpm.colDTT)),IF(OR(_xlpm.val="",_xlpm.val=0),"",_xlpm.val/1000000000))))} -> 113.30378 | K28: {=IF(ChiTietKQKD[[#This Row],[Ngành L1]]="Ngân hàng",IF(AND(INDEX(Sheet4!$2:$1605,MATCH(ChiTietKQKD[[#This Row],[Mã CP]],Sheet4!$B$2:$B$1605,0),_xlfn.XMATCH("*Thu nhập lãi thuần*Quý: 2*2026*",Sheet4!$1:$1,2))<>0,INDEX(Sheet4!$2:$1605,MATCH(ChiTietKQKD[[#This Row],[Mã CP]],Sheet4!$B$2:$B$1605,0),_xlfn.XMATCH("*Thu nhập lãi thuần*Q2*2025*",Sheet4!$1:$1,2))<>0),INDEX(Sheet4!$2:$1605,MATCH(ChiTietKQKD[[#This Row],[Mã CP]],Sheet4!$B$2:$B$1605,0),_xlfn.XMATCH("*Thu nhập lãi thuần*Quý: 2*2026*",Sheet4!$1:$1,2))/INDEX(Sheet4!$2:$1605,MATCH(ChiTietKQKD[[#This Row],[Mã CP]],Sheet4!$B$2:$B$1605,0),_xlfn.XMATCH("*Thu nhập lãi thuần*Q2*2025*",Sheet4!$1:$1,2))-1,""),IFERROR(INDEX(Sheet4!$2:$1605,MATCH(ChiTietKQKD[[#This Row],[Mã CP]],Sheet4!$B$2:$B$1605,0),_xlfn.XMATCH("*Tăng trưởng doanh thu thuần (YoY) (Quý*",Sheet4!$1:$1,2)),""))} -> 0.9954 | L28: {=IF(ChiTietKQKD[[#This Row],[Ngành L1]]="Ngân hàng",IF(AND(INDEX(Sheet4!$2:$1605,MATCH(ChiTietKQKD[[#This Row],[Mã CP]],Sheet4!$B$2:$B$1605,0),_xlfn.XMATCH("*Thu nhập lãi thuần*6 tháng*2026*",Sheet4!$1:$1,2))<>0,INDEX(Sheet4!$2:$1605,MATCH(ChiTietKQKD[[#This Row],[Mã CP]],Sheet4!$B$2:$B$1605,0),_xlfn.XMATCH("*Thu nhập lãi thuần*6 tháng*2025*",Sheet4!$1:$1,2))<>0),INDEX(Sheet4!$2:$1605,MATCH(ChiTietKQKD[[#This Row],[Mã CP]],Sheet4!$B$2:$B$1605,0),_xlfn.XMATCH("*Thu nhập lãi thuần*6 tháng*2026*",Sheet4!$1:$1,2))/INDEX(Sheet4!$2:$1605,MATCH(ChiTietKQKD[[#This Row],[Mã CP]],Sheet4!$B$2:$B$1605,0),_xlfn.XMATCH("*Thu nhập lãi thuần*6 tháng*2025*",Sheet4!$1:$1,2))-1,""),IFERROR(INDEX(Sheet4!$2:$1605,MATCH(ChiTietKQKD[[#This Row],[Mã CP]],Sheet4!$B$2:$B$1605,0),_xlfn.XMATCH("*Tăng trưởng doanh thu thuần (YoY) (6M)*",Sheet4!$1:$1,2)),""))} -> 0.1208 | M28: {=_xlfn.LET(_xlpm.val,IFERROR(INDEX(Sheet4!$2:$1605,MATCH(ChiTietKQKD[[#This Row],[Mã CP]],Sheet4!$B$2:$B$1605,0),_xlfn.XMATCH("*Lợi nhuận sau thuế*Q2*2026*",Sheet4!$1:$1,2)),0),IF(OR(_xlpm.val="",_xlpm.val=0),"",_xlpm.val/1000000000))} -> -3.4552741 | N28: {=_xlfn.LET(_xlpm.val,IFERROR(INDEX(Sheet4!$2:$1605,MATCH(ChiTietKQKD[[#This Row],[Mã CP]],Sheet4!$B$2:$B$1605,0),_xlfn.XMATCH("*Lợi nhuận sau thuế*6 tháng*2026*",Sheet4!$1:$1,2)),0),IF(OR(_xlpm.val="",_xlpm.val=0),"",_xlpm.val/1000000000))} -> -5.1963509 | O28: {=IFERROR(INDEX(Sheet4!$2:$1605,MATCH(ChiTietKQKD[[#This Row],[Mã CP]],Sheet4!$B$2:$B$1605,0),_xlfn.XMATCH("*Tăng trưởng lợi nhuận sau thuế (YoY) (Quý*",Sheet4!$1:$1,2)),"")} -> 0.9882 | P28: {=IFERROR(INDEX(Sheet4!$2:$1605,MATCH(ChiTietKQKD[[#This Row],[Mã CP]],Sheet4!$B$2:$B$1605,0),_xlfn.XMATCH("*Tăng trưởng lợi nhuận sau thuế (YoY) (6M)*",Sheet4!$1:$1,2)),"")} -> 0.9824 | Q28: {=IFERROR(INDEX(Sheet4!$2:$1605,MATCH(ChiTietKQKD[[#This Row],[Mã CP]],Sheet4!$B$2:$B$1605,0),_xlfn.XMATCH("*Tăng trưởng doanh thu thuần (QoQ)*",Sheet4!$1:$1,2)),"")} -> 0.6377 | R28: {=IFERROR(INDEX(Sheet4!$2:$1605,MATCH(ChiTietKQKD[[#This Row],[Mã CP]],Sheet4!$B$2:$B$1605,0),_xlfn.XMATCH("*Tăng trưởng lợi nhuận sau thuế (QoQ)*",Sheet4!$1:$1,2)),"")} -> -0.9846
A29: =Sheet4!A8 -> 7 | B29: =Sheet4!B8 -> ABT | C29: =Sheet4!C7 -> DV Nông nghiệp Bình Thuận | D29: =Sheet4!D8 -> HOSE | E29: =Sheet4!AH8/1000000000 -> 588.86285 | F29: =Sheet4!E8 -> Hàng Tiêu dùng | G29: =Sheet4!F8 -> Thực phẩm và đồ uống | H29: =Sheet4!G8 -> Nuôi trồng nông & hải sản | I29: {=_xlfn.LET(_xlpm.colDTT,_xlfn.XMATCH("*Doanh thu thuần*Q2*2026*",Sheet4!$1:$1,2),_xlpm.colTNL,_xlfn.XMATCH("*Thu nhập lãi thuần*Quý: 2*2026*",Sheet4!$1:$1,2),_xlpm.maCP,ChiTietKQKD[[#This Row],[Mã CP]],_xlpm.nganhL1,ChiTietKQKD[[#This Row],[Ngành L1]],IF(_xlpm.nganhL1="Ngân hàng",_xlfn.LET(_xlpm.val,_xlfn.XLOOKUP(_xlpm.maCP,Sheet4!$B$2:$B$1605,INDEX(Sheet4!$2:$1605,0,_xlpm.colTNL)),IF(OR(_xlpm.val="",_xlpm.val=0),"",_xlpm.val/1000000000)),_xlfn.LET(_xlpm.val,_xlfn.XLOOKUP(_xlpm.maCP,Sheet4!$B$2:$B$1605,INDEX(Sheet4!$2:$1605,0,_xlpm.colDTT)),IF(OR(_xlpm.val="",_xlpm.val=0),"",_xlpm.val/1000000000))))} | J29: {=_xlfn.LET(_xlpm.colDTT,_xlfn.XMATCH("*Doanh thu thuần*6 tháng*2026*",Sheet4!$1:$1,2),_xlpm.colTNL,_xlfn.XMATCH("*Thu nhập lãi thuần*6 tháng*2026*",Sheet4!$1:$1,2),_xlpm.maCP,ChiTietKQKD[[#This Row],[Mã CP]],_xlpm.nganhL1,ChiTietKQKD[[#This Row],[Ngành L1]],IF(_xlpm.nganhL1="Ngân hàng",_xlfn.LET(_xlpm.val,_xlfn.XLOOKUP(_xlpm.maCP,Sheet4!$B$2:$B$1605,INDEX(Sheet4!$2:$1605,0,_xlpm.colTNL)),IF(OR(_xlpm.val="",_xlpm.val=0),"",_xlpm.val/1000000000)),_xlfn.LET(_xlpm.val,_xlfn.XLOOKUP(_xlpm.maCP,Sheet4!$B$2:$B$1605,INDEX(Sheet4!$2:$1605,0,_xlpm.colDTT)),IF(OR(_xlpm.val="",_xlpm.val=0),"",_xlpm.val/1000000000))))} | K29: {=IF(ChiTietKQKD[[#This Row],[Ngành L1]]="Ngân hàng",IF(AND(INDEX(Sheet4!$2:$1605,MATCH(ChiTietKQKD[[#This Row],[Mã CP]],Sheet4!$B$2:$B$1605,0),_xlfn.XMATCH("*Thu nhập lãi thuần*Quý: 2*2026*",Sheet4!$1:$1,2))<>0,INDEX(Sheet4!$2:$1605,MATCH(ChiTietKQKD[[#This Row],[Mã CP]],Sheet4!$B$2:$B$1605,0),_xlfn.XMATCH("*Thu nhập lãi thuần*Q2*2025*",Sheet4!$1:$1,2))<>0),INDEX(Sheet4!$2:$1605,MATCH(ChiTietKQKD[[#This Row],[Mã CP]],Sheet4!$B$2:$B$1605,0),_xlfn.XMATCH("*Thu nhập lãi thuần*Quý: 2*2026*",Sheet4!$1:$1,2))/INDEX(Sheet4!$2:$1605,MATCH(ChiTietKQKD[[#This Row],[Mã CP]],Sheet4!$B$2:$B$1605,0),_xlfn.XMATCH("*Thu nhập lãi thuần*Q2*2025*",Sheet4!$1:$1,2))-1,""),IFERROR(INDEX(Sheet4!$2:$1605,MATCH(ChiTietKQKD[[#This Row],[Mã CP]],Sheet4!$B$2:$B$1605,0),_xlfn.XMATCH("*Tăng trưởng doanh thu thuần (YoY) (Quý*",Sheet4!$1:$1,2)),""))} -> 0 | L29: {=IF(ChiTietKQKD[[#This Row],[Ngành L1]]="Ngân hàng",IF(AND(INDEX(Sheet4!$2:$1605,MATCH(ChiTietKQKD[[#This Row],[Mã CP]],Sheet4!$B$2:$B$1605,0),_xlfn.XMATCH("*Thu nhập lãi thuần*6 tháng*2026*",Sheet4!$1:$1,2))<>0,INDEX(Sheet4!$2:$1605,MATCH(ChiTietKQKD[[#This Row],[Mã CP]],Sheet4!$B$2:$B$1605,0),_xlfn.XMATCH("*Thu nhập lãi thuần*6 tháng*2025*",Sheet4!$1:$1,2))<>0),INDEX(Sheet4!$2:$1605,MATCH(ChiTietKQKD[[#This Row],[Mã CP]],Sheet4!$B$2:$B$1605,0),_xlfn.XMATCH("*Thu nhập lãi thuần*6 tháng*2026*",Sheet4!$1:$1,2))/INDEX(Sheet4!$2:$1605,MATCH(ChiTietKQKD[[#This Row],[Mã CP]],Sheet4!$B$2:$B$1605,0),_xlfn.XMATCH("*Thu nhập lãi thuần*6 tháng*2025*",Sheet4!$1:$1,2))-1,""),IFERROR(INDEX(Sheet4!$2:$1605,MATCH(ChiTietKQKD[[#This Row],[Mã CP]],Sheet4!$B$2:$B$1605,0),_xlfn.XMATCH("*Tăng trưởng doanh thu thuần (YoY) (6M)*",Sheet4!$1:$1,2)),""))} -> 0 | M29: {=_xlfn.LET(_xlpm.val,IFERROR(INDEX(Sheet4!$2:$1605,MATCH(ChiTietKQKD[[#This Row],[Mã CP]],Sheet4!$B$2:$B$1605,0),_xlfn.XMATCH("*Lợi nhuận sau thuế*Q2*2026*",Sheet4!$1:$1,2)),0),IF(OR(_xlpm.val="",_xlpm.val=0),"",_xlpm.val/1000000000))} | N29: {=_xlfn.LET(_xlpm.val,IFERROR(INDEX(Sheet4!$2:$1605,MATCH(ChiTietKQKD[[#This Row],[Mã CP]],Sheet4!$B$2:$B$1605,0),_xlfn.XMATCH("*Lợi nhuận sau thuế*6 tháng*2026*",Sheet4!$1:$1,2)),0),IF(OR(_xlpm.val="",_xlpm.val=0),"",_xlpm.val/1000000000))} | O29: {=IFERROR(INDEX(Sheet4!$2:$1605,MATCH(ChiTietKQKD[[#This Row],[Mã CP]],Sheet4!$B$2:$B$1605,0),_xlfn.XMATCH("*Tăng trưởng lợi nhuận sau thuế (YoY) (Quý*",Sheet4!$1:$1,2)),"")} -> 0 | P29: {=IFERROR(INDEX(Sheet4!$2:$1605,MATCH(ChiTietKQKD[[#This Row],[Mã CP]],Sheet4!$B$2:$B$1605,0),_xlfn.XMATCH("*Tăng trưởng lợi nhuận sau thuế (YoY) (6M)*",Sheet4!$1:$1,2)),"")} -> 0 | Q29: {=IFERROR(INDEX(Sheet4!$2:$1605,MATCH(ChiTietKQKD[[#This Row],[Mã CP]],Sheet4!$B$2:$B$1605,0),_xlfn.XMATCH("*Tăng trưởng doanh thu thuần (QoQ)*",Sheet4!$1:$1,2)),"")} -> 0 | R29: {=IFERROR(INDEX(Sheet4!$2:$1605,MATCH(ChiTietKQKD[[#This Row],[Mã CP]],Sheet4!$B$2:$B$1605,0),_xlfn.XMATCH("*Tăng trưởng lợi nhuận sau thuế (QoQ)*",Sheet4!$1:$1,2)),"")} -> 0
A30: =Sheet4!A9 -> 8 | B30: =Sheet4!B9 -> ACB | C30: =Sheet4!C8 -> Thủy sản Bến Tre | D30: =Sheet4!D9 -> HOSE | E30: =Sheet4!AH9/1000000000 -> 130019.05 | F30: =Sheet4!E9 -> Ngân hàng | G30: =Sheet4!F9 -> Ngân hàng | H30: =Sheet4!G9 -> Ngân hàng | I30: {=_xlfn.LET(_xlpm.colDTT,_xlfn.XMATCH("*Doanh thu thuần*Q2*2026*",Sheet4!$1:$1,2),_xlpm.colTNL,_xlfn.XMATCH("*Thu nhập lãi thuần*Quý: 2*2026*",Sheet4!$1:$1,2),_xlpm.maCP,ChiTietKQKD[[#This Row],[Mã CP]],_xlpm.nganhL1,ChiTietKQKD[[#This Row],[Ngành L1]],IF(_xlpm.nganhL1="Ngân hàng",_xlfn.LET(_xlpm.val,_xlfn.XLOOKUP(_xlpm.maCP,Sheet4!$B$2:$B$1605,INDEX(Sheet4!$2:$1605,0,_xlpm.colTNL)),IF(OR(_xlpm.val="",_xlpm.val=0),"",_xlpm.val/1000000000)),_xlfn.LET(_xlpm.val,_xlfn.XLOOKUP(_xlpm.maCP,Sheet4!$B$2:$B$1605,INDEX(Sheet4!$2:$1605,0,_xlpm.colDTT)),IF(OR(_xlpm.val="",_xlpm.val=0),"",_xlpm.val/1000000000))))} -> 7784.691 | J30: {=_xlfn.LET(_xlpm.colDTT,_xlfn.XMATCH("*Doanh thu thuần*6 tháng*2026*",Sheet4!$1:$1,2),_xlpm.colTNL,_xlfn.XMATCH("*Thu nhập lãi thuần*6 tháng*2026*",Sheet4!$1:$1,2),_xlpm.maCP,ChiTietKQKD[[#This Row],[Mã CP]],_xlpm.nganhL1,ChiTietKQKD[[#This Row],[Ngành L1]],IF(_xlpm.nganhL1="Ngân hàng",_xlfn.LET(_xlpm.val,_xlfn.XLOOKUP(_xlpm.maCP,Sheet4!$B$2:$B$1605,INDEX(Sheet4!$2:$1605,0,_xlpm.colTNL)),IF(OR(_xlpm.val="",_xlpm.val=0),"",_xlpm.val/1000000000)),_xlfn.LET(_xlpm.val,_xlfn.XLOOKUP(_xlpm.maCP,Sheet4!$B$2:$B$1605,INDEX(Sheet4!$2:$1605,0,_xlpm.colDTT)),IF(OR(_xlpm.val="",_xlpm.val=0),"",_xlpm.val/1000000000))))} -> 14773.853 | K30: {=IF(ChiTietKQKD[[#This Row],[Ngành L1]]="Ngân hàng",IF(AND(INDEX(Sheet4!$2:$1605,MATCH(ChiTietKQKD[[#This Row],[Mã CP]],Sheet4!$B$2:$B$1605,0),_xlfn.XMATCH("*Thu nhập lãi thuần*Quý: 2*2026*",Sheet4!$1:$1,2))<>0,INDEX(Sheet4!$2:$1605,MATCH(ChiTietKQKD[[#This Row],[Mã CP]],Sheet4!$B$2:$B$1605,0),_xlfn.XMATCH("*Thu nhập lãi thuần*Q2*2025*",Sheet4!$1:$1,2))<>0),INDEX(Sheet4!$2:$1605,MATCH(ChiTietKQKD[[#This Row],[Mã CP]],Sheet4!$B$2:$B$1605,0),_xlfn.XMATCH("*Thu nhập lãi thuần*Quý: 2*2026*",Sheet4!$1:$1,2))/INDEX(Sheet4!$2:$1605,MATCH(ChiTietKQKD[[#This Row],[Mã CP]],Sheet4!$B$2:$B$1605,0),_xlfn.XMATCH("*Thu nhập lãi thuần*Q2*2025*",Sheet4!$1:$1,2))-1,""),IFERROR(INDEX(Sheet4!$2:$1605,MATCH(ChiTietKQKD[[#This Row],[Mã CP]],Sheet4!$B$2:$B$1605,0),_xlfn.XMATCH("*Tăng trưởng doanh thu thuần (YoY) (Quý*",Sheet4!$1:$1,2)),""))} -> 0.16470198 | L30: {=IF(ChiTietKQKD[[#This Row],[Ngành L1]]="Ngân hàng",IF(AND(INDEX(Sheet4!$2:$1605,MATCH(ChiTietKQKD[[#This Row],[Mã CP]],Sheet4!$B$2:$B$1605,0),_xlfn.XMATCH("*Thu nhập lãi thuần*6 tháng*2026*",Sheet4!$1:$1,2))<>0,INDEX(Sheet4!$2:$1605,MATCH(ChiTietKQKD[[#This Row],[Mã CP]],Sheet4!$B$2:$B$1605,0),_xlfn.XMATCH("*Thu nhập lãi thuần*6 tháng*2025*",Sheet4!$1:$1,2))<>0),INDEX(Sheet4!$2:$1605,MATCH(ChiTietKQKD[[#This Row],[Mã CP]],Sheet4!$B$2:$B$1605,0),_xlfn.XMATCH("*Thu nhập lãi thuần*6 tháng*2026*",Sheet4!$1:$1,2))/INDEX(Sheet4!$2:$1605,MATCH(ChiTietKQKD[[#This Row],[Mã CP]],Sheet4!$B$2:$B$1605,0),_xlfn.XMATCH("*Thu nhập lãi thuần*6 tháng*2025*",Sheet4!$1:$1,2))-1,""),IFERROR(INDEX(Sheet4!$2:$1605,MATCH(ChiTietKQKD[[#This Row],[Mã CP]],Sheet4!$B$2:$B$1605,0),_xlfn.XMATCH("*Tăng trưởng doanh thu thuần (YoY) (6M)*",Sheet4!$1:$1,2)),""))} -> 0.13272852 | M30: {=_xlfn.LET(_xlpm.val,IFERROR(INDEX(Sheet4!$2:$1605,MATCH(ChiTietKQKD[[#This Row],[Mã CP]],Sheet4!$B$2:$B$1605,0),_xlfn.XMATCH("*Lợi nhuận sau thuế*Q2*2026*",Sheet4!$1:$1,2)),0),IF(OR(_xlpm.val="",_xlpm.val=0),"",_xlpm.val/1000000000))} -> 4292.478 | N30: {=_xlfn.LET(_xlpm.val,IFERROR(INDEX(Sheet4!$2:$1605,MATCH(ChiTietKQKD[[#This Row],[Mã CP]],Sheet4!$B$2:$B$1605,0),_xlfn.XMATCH("*Lợi nhuận sau thuế*6 tháng*2026*",Sheet4!$1:$1,2)),0),IF(OR(_xlpm.val="",_xlpm.val=0),"",_xlpm.val/1000000000))} -> 8612.866 | O30: {=IFERROR(INDEX(Sheet4!$2:$1605,MATCH(ChiTietKQKD[[#This Row],[Mã CP]],Sheet4!$B$2:$B$1605,0),_xlfn.XMATCH("*Tăng trưởng lợi nhuận sau thuế (YoY) (Quý*",Sheet4!$1:$1,2)),"")} -> -0.1206 | P30: {=IFERROR(INDEX(Sheet4!$2:$1605,MATCH(ChiTietKQKD[[#This Row],[Mã CP]],Sheet4!$B$2:$B$1605,0),_xlfn.XMATCH("*Tăng trưởng lợi nhuận sau thuế (YoY) (6M)*",Sheet4!$1:$1,2)),"")} -> 0 | Q30: {=IFERROR(INDEX(Sheet4!$2:$1605,MATCH(ChiTietKQKD[[#This Row],[Mã CP]],Sheet4!$B$2:$B$1605,0),_xlfn.XMATCH("*Tăng trưởng doanh thu thuần (QoQ)*",Sheet4!$1:$1,2)),"")} -> 0.1436 | R30: {=IFERROR(INDEX(Sheet4!$2:$1605,MATCH(ChiTietKQKD[[#This Row],[Mã CP]],Sheet4!$B$2:$B$1605,0),_xlfn.XMATCH("*Tăng trưởng lợi nhuận sau thuế (QoQ)*",Sheet4!$1:$1,2)),"")} -> -0.0065
A31: =Sheet4!A10 -> 9 | B31: =Sheet4!B10 -> ACC | C31: =Sheet4!C9 -> ACB | D31: =Sheet4!D10 -> HOSE | E31: =Sheet4!AH10/1000000000 -> 632.09996 | F31: =Sheet4!E10 -> Công nghiệp | G31: =Sheet4!F10 -> Xây dựng và Vật liệu | H31: =Sheet4!G10 -> Vật liệu xây dựng & Nội thất | I31: {=_xlfn.LET(_xlpm.colDTT,_xlfn.XMATCH("*Doanh thu thuần*Q2*2026*",Sheet4!$1:$1,2),_xlpm.colTNL,_xlfn.XMATCH("*Thu nhập lãi thuần*Quý: 2*2026*",Sheet4!$1:$1,2),_xlpm.maCP,ChiTietKQKD[[#This Row],[Mã CP]],_xlpm.nganhL1,ChiTietKQKD[[#This Row],[Ngành L1]],IF(_xlpm.nganhL1="Ngân hàng",_xlfn.LET(_xlpm.val,_xlfn.XLOOKUP(_xlpm.maCP,Sheet4!$B$2:$B$1605,INDEX(Sheet4!$2:$1605,0,_xlpm.colTNL)),IF(OR(_xlpm.val="",_xlpm.val=0),"",_xlpm.val/1000000000)),_xlfn.LET(_xlpm.val,_xlfn.XLOOKUP(_xlpm.maCP,Sheet4!$B$2:$B$1605,INDEX(Sheet4!$2:$1605,0,_xlpm.colDTT)),IF(OR(_xlpm.val="",_xlpm.val=0),"",_xlpm.val/1000000000))))} | J31: {=_xlfn.LET(_xlpm.colDTT,_xlfn.XMATCH("*Doanh thu thuần*6 tháng*2026*",Sheet4!$1:$1,2),_xlpm.colTNL,_xlfn.XMATCH("*Thu nhập lãi thuần*6 tháng*2026*",Sheet4!$1:$1,2),_xlpm.maCP,ChiTietKQKD[[#This Row],[Mã CP]],_xlpm.nganhL1,ChiTietKQKD[[#This Row],[Ngành L1]],IF(_xlpm.nganhL1="Ngân hàng",_xlfn.LET(_xlpm.val,_xlfn.XLOOKUP(_xlpm.maCP,Sheet4!$B$2:$B$1605,INDEX(Sheet4!$2:$1605,0,_xlpm.colTNL)),IF(OR(_xlpm.val="",_xlpm.val=0),"",_xlpm.val/1000000000)),_xlfn.LET(_xlpm.val,_xlfn.XLOOKUP(_xlpm.maCP,Sheet4!$B$2:$B$1605,INDEX(Sheet4!$2:$1605,0,_xlpm.colDTT)),IF(OR(_xlpm.val="",_xlpm.val=0),"",_xlpm.val/1000000000))))} | K31: {=IF(ChiTietKQKD[[#This Row],[Ngành L1]]="Ngân hàng",IF(AND(INDEX(Sheet4!$2:$1605,MATCH(ChiTietKQKD[[#This Row],[Mã CP]],Sheet4!$B$2:$B$1605,0),_xlfn.XMATCH("*Thu nhập lãi thuần*Quý: 2*2026*",Sheet4!$1:$1,2))<>0,INDEX(Sheet4!$2:$1605,MATCH(ChiTietKQKD[[#This Row],[Mã CP]],Sheet4!$B$2:$B$1605,0),_xlfn.XMATCH("*Thu nhập lãi thuần*Q2*2025*",Sheet4!$1:$1,2))<>0),INDEX(Sheet4!$2:$1605,MATCH(ChiTietKQKD[[#This Row],[Mã CP]],Sheet4!$B$2:$B$1605,0),_xlfn.XMATCH("*Thu nhập lãi thuần*Quý: 2*2026*",Sheet4!$1:$1,2))/INDEX(Sheet4!$2:$1605,MATCH(ChiTietKQKD[[#This Row],[Mã CP]],Sheet4!$B$2:$B$1605,0),_xlfn.XMATCH("*Thu nhập lãi thuần*Q2*2025*",Sheet4!$1:$1,2))-1,""),IFERROR(INDEX(Sheet4!$2:$1605,MATCH(ChiTietKQKD[[#This Row],[Mã CP]],Sheet4!$B$2:$B$1605,0),_xlfn.XMATCH("*Tăng trưởng doanh thu thuần (YoY) (Quý*",Sheet4!$1:$1,2)),""))} -> 0 | L31: {=IF(ChiTietKQKD[[#This Row],[Ngành L1]]="Ngân hàng",IF(AND(INDEX(Sheet4!$2:$1605,MATCH(ChiTietKQKD[[#This Row],[Mã CP]],Sheet4!$B$2:$B$1605,0),_xlfn.XMATCH("*Thu nhập lãi thuần*6 tháng*2026*",Sheet4!$1:$1,2))<>0,INDEX(Sheet4!$2:$1605,MATCH(ChiTietKQKD[[#This Row],[Mã CP]],Sheet4!$B$2:$B$1605,0),_xlfn.XMATCH("*Thu nhập lãi thuần*6 tháng*2025*",Sheet4!$1:$1,2))<>0),INDEX(Sheet4!$2:$1605,MATCH(ChiTietKQKD[[#This Row],[Mã CP]],Sheet4!$B$2:$B$1605,0),_xlfn.XMATCH("*Thu nhập lãi thuần*6 tháng*2026*",Sheet4!$1:$1,2))/INDEX(Sheet4!$2:$1605,MATCH(ChiTietKQKD[[#This Row],[Mã CP]],Sheet4!$B$2:$B$1605,0),_xlfn.XMATCH("*Thu nhập lãi thuần*6 tháng*2025*",Sheet4!$1:$1,2))-1,""),IFERROR(INDEX(Sheet4!$2:$1605,MATCH(ChiTietKQKD[[#This Row],[Mã CP]],Sheet4!$B$2:$B$1605,0),_xlfn.XMATCH("*Tăng trưởng doanh thu thuần (YoY) (6M)*",Sheet4!$1:$1,2)),""))} -> 0 | M31: {=_xlfn.LET(_xlpm.val,IFERROR(INDEX(Sheet4!$2:$1605,MATCH(ChiTietKQKD[[#This Row],[Mã CP]],Sheet4!$B$2:$B$1605,0),_xlfn.XMATCH("*Lợi nhuận sau thuế*Q2*2026*",Sheet4!$1:$1,2)),0),IF(OR(_xlpm.val="",_xlpm.val=0),"",_xlpm.val/1000000000))} | N31: {=_xlfn.LET(_xlpm.val,IFERROR(INDEX(Sheet4!$2:$1605,MATCH(ChiTietKQKD[[#This Row],[Mã CP]],Sheet4!$B$2:$B$1605,0),_xlfn.XMATCH("*Lợi nhuận sau thuế*6 tháng*2026*",Sheet4!$1:$1,2)),0),IF(OR(_xlpm.val="",_xlpm.val=0),"",_xlpm.val/1000000000))} | O31: {=IFERROR(INDEX(Sheet4!$2:$1605,MATCH(ChiTietKQKD[[#This Row],[Mã CP]],Sheet4!$B$2:$B$1605,0),_xlfn.XMATCH("*Tăng trưởng lợi nhuận sau thuế (YoY) (Quý*",Sheet4!$1:$1,2)),"")} -> 0 | P31: {=IFERROR(INDEX(Sheet4!$2:$1605,MATCH(ChiTietKQKD[[#This Row],[Mã CP]],Sheet4!$B$2:$B$1605,0),_xlfn.XMATCH("*Tăng trưởng lợi nhuận sau thuế (YoY) (6M)*",Sheet4!$1:$1,2)),"")} -> 0 | Q31: {=IFERROR(INDEX(Sheet4!$2:$1605,MATCH(ChiTietKQKD[[#This Row],[Mã CP]],Sheet4!$B$2:$B$1605,0),_xlfn.XMATCH("*Tăng trưởng doanh thu thuần (QoQ)*",Sheet4!$1:$1,2)),"")} -> 0 | R31: {=IFERROR(INDEX(Sheet4!$2:$1605,MATCH(ChiTietKQKD[[#This Row],[Mã CP]],Sheet4!$B$2:$B$1605,0),_xlfn.XMATCH("*Tăng trưởng lợi nhuận sau thuế (QoQ)*",Sheet4!$1:$1,2)),"")} -> 0
A32: =Sheet4!A11 -> 10 | B32: =Sheet4!B11 -> ACG | C32: =Sheet4!C10 -> Đầu tư và XD Bình Dương ACC | D32: =Sheet4!D11 -> HOSE | E32: =Sheet4!AH11/1000000000 -> 4840.2931 | F32: =Sheet4!E11 -> Nguyên vật liệu | G32: =Sheet4!F11 -> Tài nguyên Cơ bản | H32: =Sheet4!G11 -> Lâm sản và Chế biến gỗ | I32: {=_xlfn.LET(_xlpm.colDTT,_xlfn.XMATCH("*Doanh thu thuần*Q2*2026*",Sheet4!$1:$1,2),_xlpm.colTNL,_xlfn.XMATCH("*Thu nhập lãi thuần*Quý: 2*2026*",Sheet4!$1:$1,2),_xlpm.maCP,ChiTietKQKD[[#This Row],[Mã CP]],_xlpm.nganhL1,ChiTietKQKD[[#This Row],[Ngành L1]],IF(_xlpm.nganhL1="Ngân hàng",_xlfn.LET(_xlpm.val,_xlfn.XLOOKUP(_xlpm.maCP,Sheet4!$B$2:$B$1605,INDEX(Sheet4!$2:$1605,0,_xlpm.colTNL)),IF(OR(_xlpm.val="",_xlpm.val=0),"",_xlpm.val/1000000000)),_xlfn.LET(_xlpm.val,_xlfn.XLOOKUP(_xlpm.maCP,Sheet4!$B$2:$B$1605,INDEX(Sheet4!$2:$1605,0,_xlpm.colDTT)),IF(OR(_xlpm.val="",_xlpm.val=0),"",_xlpm.val/1000000000))))} | J32: {=_xlfn.LET(_xlpm.colDTT,_xlfn.XMATCH("*Doanh thu thuần*6 tháng*2026*",Sheet4!$1:$1,2),_xlpm.colTNL,_xlfn.XMATCH("*Thu nhập lãi thuần*6 tháng*2026*",Sheet4!$1:$1,2),_xlpm.maCP,ChiTietKQKD[[#This Row],[Mã CP]],_xlpm.nganhL1,ChiTietKQKD[[#This Row],[Ngành L1]],IF(_xlpm.nganhL1="Ngân hàng",_xlfn.LET(_xlpm.val,_xlfn.XLOOKUP(_xlpm.maCP,Sheet4!$B$2:$B$1605,INDEX(Sheet4!$2:$1605,0,_xlpm.colTNL)),IF(OR(_xlpm.val="",_xlpm.val=0),"",_xlpm.val/1000000000)),_xlfn.LET(_xlpm.val,_xlfn.XLOOKUP(_xlpm.maCP,Sheet4!$B$2:$B$1605,INDEX(Sheet4!$2:$1605,0,_xlpm.colDTT)),IF(OR(_xlpm.val="",_xlpm.val=0),"",_xlpm.val/1000000000))))} | K32: {=IF(ChiTietKQKD[[#This Row],[Ngành L1]]="Ngân hàng",IF(AND(INDEX(Sheet4!$2:$1605,MATCH(ChiTietKQKD[[#This Row],[Mã CP]],Sheet4!$B$2:$B$1605,0),_xlfn.XMATCH("*Thu nhập lãi thuần*Quý: 2*2026*",Sheet4!$1:$1,2))<>0,INDEX(Sheet4!$2:$1605,MATCH(ChiTietKQKD[[#This Row],[Mã CP]],Sheet4!$B$2:$B$1605,0),_xlfn.XMATCH("*Thu nhập lãi thuần*Q2*2025*",Sheet4!$1:$1,2))<>0),INDEX(Sheet4!$2:$1605,MATCH(ChiTietKQKD[[#This Row],[Mã CP]],Sheet4!$B$2:$B$1605,0),_xlfn.XMATCH("*Thu nhập lãi thuần*Quý: 2*2026*",Sheet4!$1:$1,2))/INDEX(Sheet4!$2:$1605,MATCH(ChiTietKQKD[[#This Row],[Mã CP]],Sheet4!$B$2:$B$1605,0),_xlfn.XMATCH("*Thu nhập lãi thuần*Q2*2025*",Sheet4!$1:$1,2))-1,""),IFERROR(INDEX(Sheet4!$2:$1605,MATCH(ChiTietKQKD[[#This Row],[Mã CP]],Sheet4!$B$2:$B$1605,0),_xlfn.XMATCH("*Tăng trưởng doanh thu thuần (YoY) (Quý*",Sheet4!$1:$1,2)),""))} -> 0 | L32: {=IF(ChiTietKQKD[[#This Row],[Ngành L1]]="Ngân hàng",IF(AND(INDEX(Sheet4!$2:$1605,MATCH(ChiTietKQKD[[#This Row],[Mã CP]],Sheet4!$B$2:$B$1605,0),_xlfn.XMATCH("*Thu nhập lãi thuần*6 tháng*2026*",Sheet4!$1:$1,2))<>0,INDEX(Sheet4!$2:$1605,MATCH(ChiTietKQKD[[#This Row],[Mã CP]],Sheet4!$B$2:$B$1605,0),_xlfn.XMATCH("*Thu nhập lãi thuần*6 tháng*2025*",Sheet4!$1:$1,2))<>0),INDEX(Sheet4!$2:$1605,MATCH(ChiTietKQKD[[#This Row],[Mã CP]],Sheet4!$B$2:$B$1605,0),_xlfn.XMATCH("*Thu nhập lãi thuần*6 tháng*2026*",Sheet4!$1:$1,2))/INDEX(Sheet4!$2:$1605,MATCH(ChiTietKQKD[[#This Row],[Mã CP]],Sheet4!$B$2:$B$1605,0),_xlfn.XMATCH("*Thu nhập lãi thuần*6 tháng*2025*",Sheet4!$1:$1,2))-1,""),IFERROR(INDEX(Sheet4!$2:$1605,MATCH(ChiTietKQKD[[#This Row],[Mã CP]],Sheet4!$B$2:$B$1605,0),_xlfn.XMATCH("*Tăng trưởng doanh thu thuần (YoY) (6M)*",Sheet4!$1:$1,2)),""))} -> 0 | M32: {=_xlfn.LET(_xlpm.val,IFERROR(INDEX(Sheet4!$2:$1605,MATCH(ChiTietKQKD[[#This Row],[Mã CP]],Sheet4!$B$2:$B$1605,0),_xlfn.XMATCH("*Lợi nhuận sau thuế*Q2*2026*",Sheet4!$1:$1,2)),0),IF(OR(_xlpm.val="",_xlpm.val=0),"",_xlpm.val/1000000000))} | N32: {=_xlfn.LET(_xlpm.val,IFERROR(INDEX(Sheet4!$2:$1605,MATCH(ChiTietKQKD[[#This Row],[Mã CP]],Sheet4!$B$2:$B$1605,0),_xlfn.XMATCH("*Lợi nhuận sau thuế*6 tháng*2026*",Sheet4!$1:$1,2)),0),IF(OR(_xlpm.val="",_xlpm.val=0),"",_xlpm.val/1000000000))} | O32: {=IFERROR(INDEX(Sheet4!$2:$1605,MATCH(ChiTietKQKD[[#This Row],[Mã CP]],Sheet4!$B$2:$B$1605,0),_xlfn.XMATCH("*Tăng trưởng lợi nhuận sau thuế (YoY) (Quý*",Sheet4!$1:$1,2)),"")} -> 0 | P32: {=IFERROR(INDEX(Sheet4!$2:$1605,MATCH(ChiTietKQKD[[#This Row],[Mã CP]],Sheet4!$B$2:$B$1605,0),_xlfn.XMATCH("*Tăng trưởng lợi nhuận sau thuế (YoY) (6M)*",Sheet4!$1:$1,2)),"")} -> 0 | Q32: {=IFERROR(INDEX(Sheet4!$2:$1605,MATCH(ChiTietKQKD[[#This Row],[Mã CP]],Sheet4!$B$2:$B$1605,0),_xlfn.XMATCH("*Tăng trưởng doanh thu thuần (QoQ)*",Sheet4!$1:$1,2)),"")} -> 0 | R32: {=IFERROR(INDEX(Sheet4!$2:$1605,MATCH(ChiTietKQKD[[#This Row],[Mã CP]],Sheet4!$B$2:$B$1605,0),_xlfn.XMATCH("*Tăng trưởng lợi nhuận sau thuế (QoQ)*",Sheet4!$1:$1,2)),"")} -> 0
A33: =Sheet4!A12 -> 11 | B33: =Sheet4!B12 -> ACL | C33: =Sheet4!C11 -> Gỗ An Cường | D33: =Sheet4!D12 -> HOSE | E33: =Sheet4!AH12/1000000000 -> 647.05135 | F33: =Sheet4!E12 -> Hàng Tiêu dùng | G33: =Sheet4!F12 -> Thực phẩm và đồ uống | H33: =Sheet4!G12 -> Nuôi trồng nông & hải sản | I33: {=_xlfn.LET(_xlpm.colDTT,_xlfn.XMATCH("*Doanh thu thuần*Q2*2026*",Sheet4!$1:$1,2),_xlpm.colTNL,_xlfn.XMATCH("*Thu nhập lãi thuần*Quý: 2*2026*",Sheet4!$1:$1,2),_xlpm.maCP,ChiTietKQKD[[#This Row],[Mã CP]],_xlpm.nganhL1,ChiTietKQKD[[#This Row],[Ngành L1]],IF(_xlpm.nganhL1="Ngân hàng",_xlfn.LET(_xlpm.val,_xlfn.XLOOKUP(_xlpm.maCP,Sheet4!$B$2:$B$1605,INDEX(Sheet4!$2:$1605,0,_xlpm.colTNL)),IF(OR(_xlpm.val="",_xlpm.val=0),"",_xlpm.val/1000000000)),_xlfn.LET(_xlpm.val,_xlfn.XLOOKUP(_xlpm.maCP,Sheet4!$B$2:$B$1605,INDEX(Sheet4!$2:$1605,0,_xlpm.colDTT)),IF(OR(_xlpm.val="",_xlpm.val=0),"",_xlpm.val/1000000000))))} | J33: {=_xlfn.LET(_xlpm.colDTT,_xlfn.XMATCH("*Doanh thu thuần*6 tháng*2026*",Sheet4!$1:$1,2),_xlpm.colTNL,_xlfn.XMATCH("*Thu nhập lãi thuần*6 tháng*2026*",Sheet4!$1:$1,2),_xlpm.maCP,ChiTietKQKD[[#This Row],[Mã CP]],_xlpm.nganhL1,ChiTietKQKD[[#This Row],[Ngành L1]],IF(_xlpm.nganhL1="Ngân hàng",_xlfn.LET(_xlpm.val,_xlfn.XLOOKUP(_xlpm.maCP,Sheet4!$B$2:$B$1605,INDEX(Sheet4!$2:$1605,0,_xlpm.colTNL)),IF(OR(_xlpm.val="",_xlpm.val=0),"",_xlpm.val/1000000000)),_xlfn.LET(_xlpm.val,_xlfn.XLOOKUP(_xlpm.maCP,Sheet4!$B$2:$B$1605,INDEX(Sheet4!$2:$1605,0,_xlpm.colDTT)),IF(OR(_xlpm.val="",_xlpm.val=0),"",_xlpm.val/1000000000))))} | K33: {=IF(ChiTietKQKD[[#This Row],[Ngành L1]]="Ngân hàng",IF(AND(INDEX(Sheet4!$2:$1605,MATCH(ChiTietKQKD[[#This Row],[Mã CP]],Sheet4!$B$2:$B$1605,0),_xlfn.XMATCH("*Thu nhập lãi thuần*Quý: 2*2026*",Sheet4!$1:$1,2))<>0,INDEX(Sheet4!$2:$1605,MATCH(ChiTietKQKD[[#This Row],[Mã CP]],Sheet4!$B$2:$B$1605,0),_xlfn.XMATCH("*Thu nhập lãi thuần*Q2*2025*",Sheet4!$1:$1,2))<>0),INDEX(Sheet4!$2:$1605,MATCH(ChiTietKQKD[[#This Row],[Mã CP]],Sheet4!$B$2:$B$1605,0),_xlfn.XMATCH("*Thu nhập lãi thuần*Quý: 2*2026*",Sheet4!$1:$1,2))/INDEX(Sheet4!$2:$1605,MATCH(ChiTietKQKD[[#This Row],[Mã CP]],Sheet4!$B$2:$B$1605,0),_xlfn.XMATCH("*Thu nhập lãi thuần*Q2*2025*",Sheet4!$1:$1,2))-1,""),IFERROR(INDEX(Sheet4!$2:$1605,MATCH(ChiTietKQKD[[#This Row],[Mã CP]],Sheet4!$B$2:$B$1605,0),_xlfn.XMATCH("*Tăng trưởng doanh thu thuần (YoY) (Quý*",Sheet4!$1:$1,2)),""))} -> 0 | L33: {=IF(ChiTietKQKD[[#This Row],[Ngành L1]]="Ngân hàng",IF(AND(INDEX(Sheet4!$2:$1605,MATCH(ChiTietKQKD[[#This Row],[Mã CP]],Sheet4!$B$2:$B$1605,0),_xlfn.XMATCH("*Thu nhập lãi thuần*6 tháng*2026*",Sheet4!$1:$1,2))<>0,INDEX(Sheet4!$2:$1605,MATCH(ChiTietKQKD[[#This Row],[Mã CP]],Sheet4!$B$2:$B$1605,0),_xlfn.XMATCH("*Thu nhập lãi thuần*6 tháng*2025*",Sheet4!$1:$1,2))<>0),INDEX(Sheet4!$2:$1605,MATCH(ChiTietKQKD[[#This Row],[Mã CP]],Sheet4!$B$2:$B$1605,0),_xlfn.XMATCH("*Thu nhập lãi thuần*6 tháng*2026*",Sheet4!$1:$1,2))/INDEX(Sheet4!$2:$1605,MATCH(ChiTietKQKD[[#This Row],[Mã CP]],Sheet4!$B$2:$B$1605,0),_xlfn.XMATCH("*Thu nhập lãi thuần*6 tháng*2025*",Sheet4!$1:$1,2))-1,""),IFERROR(INDEX(Sheet4!$2:$1605,MATCH(ChiTietKQKD[[#This Row],[Mã CP]],Sheet4!$B$2:$B$1605,0),_xlfn.XMATCH("*Tăng trưởng doanh thu thuần (YoY) (6M)*",Sheet4!$1:$1,2)),""))} -> 0 | M33: {=_xlfn.LET(_xlpm.val,IFERROR(INDEX(Sheet4!$2:$1605,MATCH(ChiTietKQKD[[#This Row],[Mã CP]],Sheet4!$B$2:$B$1605,0),_xlfn.XMATCH("*Lợi nhuận sau thuế*Q2*2026*",Sheet4!$1:$1,2)),0),IF(OR(_xlpm.val="",_xlpm.val=0),"",_xlpm.val/1000000000))} | N33: {=_xlfn.LET(_xlpm.val,IFERROR(INDEX(Sheet4!$2:$1605,MATCH(ChiTietKQKD[[#This Row],[Mã CP]],Sheet4!$B$2:$B$1605,0),_xlfn.XMATCH("*Lợi nhuận sau thuế*6 tháng*2026*",Sheet4!$1:$1,2)),0),IF(OR(_xlpm.val="",_xlpm.val=0),"",_xlpm.val/1000000000))} | O33: {=IFERROR(INDEX(Sheet4!$2:$1605,MATCH(ChiTietKQKD[[#This Row],[Mã CP]],Sheet4!$B$2:$B$1605,0),_xlfn.XMATCH("*Tăng trưởng lợi nhuận sau thuế (YoY) (Quý*",Sheet4!$1:$1,2)),"")} -> 0 | P33: {=IFERROR(INDEX(Sheet4!$2:$1605,MATCH(ChiTietKQKD[[#This Row],[Mã CP]],Sheet4!$B$2:$B$1605,0),_xlfn.XMATCH("*Tăng trưởng lợi nhuận sau thuế (YoY) (6M)*",Sheet4!$1:$1,2)),"")} -> 0 | Q33: {=IFERROR(INDEX(Sheet4!$2:$1605,MATCH(ChiTietKQKD[[#This Row],[Mã CP]],Sheet4!$B$2:$B$1605,0),_xlfn.XMATCH("*Tăng trưởng doanh thu thuần (QoQ)*",Sheet4!$1:$1,2)),"")} -> 0 | R33: {=IFERROR(INDEX(Sheet4!$2:$1605,MATCH(ChiTietKQKD[[#This Row],[Mã CP]],Sheet4!$B$2:$B$1605,0),_xlfn.XMATCH("*Tăng trưởng lợi nhuận sau thuế (QoQ)*",Sheet4!$1:$1,2)),"")} -> 0
A34: =Sheet4!A13 -> 12 | B34: =Sheet4!B13 -> ADG | C34: =Sheet4!C12 -> Thủy sản CL An Giang | D34: =Sheet4!D13 -> HOSE | E34: =Sheet4!AH13/1000000000 -> 173.18222 | F34: =Sheet4!E13 -> Dịch vụ Tiêu dùng | G34: =Sheet4!F13 -> Truyền thông | H34: =Sheet4!G13 -> Dịch vụ truyền thông | I34: {=_xlfn.LET(_xlpm.colDTT,_xlfn.XMATCH("*Doanh thu thuần*Q2*2026*",Sheet4!$1:$1,2),_xlpm.colTNL,_xlfn.XMATCH("*Thu nhập lãi thuần*Quý: 2*2026*",Sheet4!$1:$1,2),_xlpm.maCP,ChiTietKQKD[[#This Row],[Mã CP]],_xlpm.nganhL1,ChiTietKQKD[[#This Row],[Ngành L1]],IF(_xlpm.nganhL1="Ngân hàng",_xlfn.LET(_xlpm.val,_xlfn.XLOOKUP(_xlpm.maCP,Sheet4!$B$2:$B$1605,INDEX(Sheet4!$2:$1605,0,_xlpm.colTNL)),IF(OR(_xlpm.val="",_xlpm.val=0),"",_xlpm.val/1000000000)),_xlfn.LET(_xlpm.val,_xlfn.XLOOKUP(_xlpm.maCP,Sheet4!$B$2:$B$1605,INDEX(Sheet4!$2:$1605,0,_xlpm.colDTT)),IF(OR(_xlpm.val="",_xlpm.val=0),"",_xlpm.val/1000000000))))} | J34: {=_xlfn.LET(_xlpm.colDTT,_xlfn.XMATCH("*Doanh thu thuần*6 tháng*2026*",Sheet4!$1:$1,2),_xlpm.colTNL,_xlfn.XMATCH("*Thu nhập lãi thuần*6 tháng*2026*",Sheet4!$1:$1,2),_xlpm.maCP,ChiTietKQKD[[#This Row],[Mã CP]],_xlpm.nganhL1,ChiTietKQKD[[#This Row],[Ngành L1]],IF(_xlpm.nganhL1="Ngân hàng",_xlfn.LET(_xlpm.val,_xlfn.XLOOKUP(_xlpm.maCP,Sheet4!$B$2:$B$1605,INDEX(Sheet4!$2:$1605,0,_xlpm.colTNL)),IF(OR(_xlpm.val="",_xlpm.val=0),"",_xlpm.val/1000000000)),_xlfn.LET(_xlpm.val,_xlfn.XLOOKUP(_xlpm.maCP,Sheet4!$B$2:$B$1605,INDEX(Sheet4!$2:$1605,0,_xlpm.colDTT)),IF(OR(_xlpm.val="",_xlpm.val=0),"",_xlpm.val/1000000000))))} | K34: {=IF(ChiTietKQKD[[#This Row],[Ngành L1]]="Ngân hàng",IF(AND(INDEX(Sheet4!$2:$1605,MATCH(ChiTietKQKD[[#This Row],[Mã CP]],Sheet4!$B$2:$B$1605,0),_xlfn.XMATCH("*Thu nhập lãi thuần*Quý: 2*2026*",Sheet4!$1:$1,2))<>0,INDEX(Sheet4!$2:$1605,MATCH(ChiTietKQKD[[#This Row],[Mã CP]],Sheet4!$B$2:$B$1605,0),_xlfn.XMATCH("*Thu nhập lãi thuần*Q2*2025*",Sheet4!$1:$1,2))<>0),INDEX(Sheet4!$2:$1605,MATCH(ChiTietKQKD[[#This Row],[Mã CP]],Sheet4!$B$2:$B$1605,0),_xlfn.XMATCH("*Thu nhập lãi thuần*Quý: 2*2026*",Sheet4!$1:$1,2))/INDEX(Sheet4!$2:$1605,MATCH(ChiTietKQKD[[#This Row],[Mã CP]],Sheet4!$B$2:$B$1605,0),_xlfn.XMATCH("*Thu nhập lãi thuần*Q2*2025*",Sheet4!$1:$1,2))-1,""),IFERROR(INDEX(Sheet4!$2:$1605,MATCH(ChiTietKQKD[[#This Row],[Mã CP]],Sheet4!$B$2:$B$1605,0),_xlfn.XMATCH("*Tăng trưởng doanh thu thuần (YoY) (Quý*",Sheet4!$1:$1,2)),""))} -> 0 | L34: {=IF(ChiTietKQKD[[#This Row],[Ngành L1]]="Ngân hàng",IF(AND(INDEX(Sheet4!$2:$1605,MATCH(ChiTietKQKD[[#This Row],[Mã CP]],Sheet4!$B$2:$B$1605,0),_xlfn.XMATCH("*Thu nhập lãi thuần*6 tháng*2026*",Sheet4!$1:$1,2))<>0,INDEX(Sheet4!$2:$1605,MATCH(ChiTietKQKD[[#This Row],[Mã CP]],Sheet4!$B$2:$B$1605,0),_xlfn.XMATCH("*Thu nhập lãi thuần*6 tháng*2025*",Sheet4!$1:$1,2))<>0),INDEX(Sheet4!$2:$1605,MATCH(ChiTietKQKD[[#This Row],[Mã CP]],Sheet4!$B$2:$B$1605,0),_xlfn.XMATCH("*Thu nhập lãi thuần*6 tháng*2026*",Sheet4!$1:$1,2))/INDEX(Sheet4!$2:$1605,MATCH(ChiTietKQKD[[#This Row],[Mã CP]],Sheet4!$B$2:$B$1605,0),_xlfn.XMATCH("*Thu nhập lãi thuần*6 tháng*2025*",Sheet4!$1:$1,2))-1,""),IFERROR(INDEX(Sheet4!$2:$1605,MATCH(ChiTietKQKD[[#This Row],[Mã CP]],Sheet4!$B$2:$B$1605,0),_xlfn.XMATCH("*Tăng trưởng doanh thu thuần (YoY) (6M)*",Sheet4!$1:$1,2)),""))} -> 0 | M34: {=_xlfn.LET(_xlpm.val,IFERROR(INDEX(Sheet4!$2:$1605,MATCH(ChiTietKQKD[[#This Row],[Mã CP]],Sheet4!$B$2:$B$1605,0),_xlfn.XMATCH("*Lợi nhuận sau thuế*Q2*2026*",Sheet4!$1:$1,2)),0),IF(OR(_xlpm.val="",_xlpm.val=0),"",_xlpm.val/1000000000))} | N34: {=_xlfn.LET(_xlpm.val,IFERROR(INDEX(Sheet4!$2:$1605,MATCH(ChiTietKQKD[[#This Row],[Mã CP]],Sheet4!$B$2:$B$1605,0),_xlfn.XMATCH("*Lợi nhuận sau thuế*6 tháng*2026*",Sheet4!$1:$1,2)),0),IF(OR(_xlpm.val="",_xlpm.val=0),"",_xlpm.val/1000000000))} | O34: {=IFERROR(INDEX(Sheet4!$2:$1605,MATCH(ChiTietKQKD[[#This Row],[Mã CP]],Sheet4!$B$2:$B$1605,0),_xlfn.XMATCH("*Tăng trưởng lợi nhuận sau thuế (YoY) (Quý*",Sheet4!$1:$1,2)),"")} -> 0 | P34: {=IFERROR(INDEX(Sheet4!$2:$1605,MATCH(ChiTietKQKD[[#This Row],[Mã CP]],Sheet4!$B$2:$B$1605,0),_xlfn.XMATCH("*Tăng trưởng lợi nhuận sau thuế (YoY) (6M)*",Sheet4!$1:$1,2)),"")} -> 0 | Q34: {=IFERROR(INDEX(Sheet4!$2:$1605,MATCH(ChiTietKQKD[[#This Row],[Mã CP]],Sheet4!$B$2:$B$1605,0),_xlfn.XMATCH("*Tăng trưởng doanh thu thuần (QoQ)*",Sheet4!$1:$1,2)),"")} -> 0 | R34: {=IFERROR(INDEX(Sheet4!$2:$1605,MATCH(ChiTietKQKD[[#This Row],[Mã CP]],Sheet4!$B$2:$B$1605,0),_xlfn.XMATCH("*Tăng trưởng lợi nhuận sau thuế (QoQ)*",Sheet4!$1:$1,2)),"")} -> 0
... A1615: =Sheet4!A1594 -> 1593 | B1615: =Sheet4!B1594 -> YTC | C1615: =Sheet4!C1593 -> Xi măng và Khoáng sản Yên Bái | D1615: =Sheet4!D1594 -> UPCoM | E1615: =Sheet4!AH1594/1000000000 -> 207.1916 | F1615: =Sheet4!E1594 -> Dược phẩm và Y tế | G1615: =Sheet4!F1594 -> Y tế | H1615: =Sheet4!G1594 -> Dụng cụ y tế | I1615: {=_xlfn.LET(_xlpm.colDTT,_xlfn.XMATCH("*Doanh thu thuần*Q2*2026*",Sheet4!$1:$1,2),_xlpm.colTNL,_xlfn.XMATCH("*Thu nhập lãi thuần*Quý: 2*2026*",Sheet4!$1:$1,2),_xlpm.maCP,ChiTietKQKD[[#This Row],[Mã CP]],_xlpm.nganhL1,ChiTietKQKD[[#This Row],[Ngành L1]],IF(_xlpm.nganhL1="Ngân hàng",_xlfn.LET(_xlpm.val,_xlfn.XLOOKUP(_xlpm.maCP,Sheet4!$B$2:$B$1605,INDEX(Sheet4!$2:$1605,0,_xlpm.colTNL)),IF(OR(_xlpm.val="",_xlpm.val=0),"",_xlpm.val/1000000000)),_xlfn.LET(_xlpm.val,_xlfn.XLOOKUP(_xlpm.maCP,Sheet4!$B$2:$B$1605,INDEX(Sheet4!$2:$1605,0,_xlpm.colDTT)),IF(OR(_xlpm.val="",_xlpm.val=0),"",_xlpm.val/1000000000))))} | J1615: {=_xlfn.LET(_xlpm.colDTT,_xlfn.XMATCH("*Doanh thu thuần*6 tháng*2026*",Sheet4!$1:$1,2),_xlpm.colTNL,_xlfn.XMATCH("*Thu nhập lãi thuần*6 tháng*2026*",Sheet4!$1:$1,2),_xlpm.maCP,ChiTietKQKD[[#This Row],[Mã CP]],_xlpm.nganhL1,ChiTietKQKD[[#This Row],[Ngành L1]],IF(_xlpm.nganhL1="Ngân hàng",_xlfn.LET(_xlpm.val,_xlfn.XLOOKUP(_xlpm.maCP,Sheet4!$B$2:$B$1605,INDEX(Sheet4!$2:$1605,0,_xlpm.colTNL)),IF(OR(_xlpm.val="",_xlpm.val=0),"",_xlpm.val/1000000000)),_xlfn.LET(_xlpm.val,_xlfn.XLOOKUP(_xlpm.maCP,Sheet4!$B$2:$B$1605,INDEX(Sheet4!$2:$1605,0,_xlpm.colDTT)),IF(OR(_xlpm.val="",_xlpm.val=0),"",_xlpm.val/1000000000))))} | K1615: {=IF(ChiTietKQKD[[#This Row],[Ngành L1]]="Ngân hàng",IF(AND(INDEX(Sheet4!$2:$1605,MATCH(ChiTietKQKD[[#This Row],[Mã CP]],Sheet4!$B$2:$B$1605,0),_xlfn.XMATCH("*Thu nhập lãi thuần*Quý: 2*2026*",Sheet4!$1:$1,2))<>0,INDEX(Sheet4!$2:$1605,MATCH(ChiTietKQKD[[#This Row],[Mã CP]],Sheet4!$B$2:$B$1605,0),_xlfn.XMATCH("*Thu nhập lãi thuần*Q2*2025*",Sheet4!$1:$1,2))<>0),INDEX(Sheet4!$2:$1605,MATCH(ChiTietKQKD[[#This Row],[Mã CP]],Sheet4!$B$2:$B$1605,0),_xlfn.XMATCH("*Thu nhập lãi thuần*Quý: 2*2026*",Sheet4!$1:$1,2))/INDEX(Sheet4!$2:$1605,MATCH(ChiTietKQKD[[#This Row],[Mã CP]],Sheet4!$B$2:$B$1605,0),_xlfn.XMATCH("*Thu nhập lãi thuần*Q2*2025*",Sheet4!$1:$1,2))-1,""),IFERROR(INDEX(Sheet4!$2:$1605,MATCH(ChiTietKQKD[[#This Row],[Mã CP]],Sheet4!$B$2:$B$1605,0),_xlfn.XMATCH("*Tăng trưởng doanh thu thuần (YoY) (Quý*",Sheet4!$1:$1,2)),""))} -> 0 | L1615: {=IF(ChiTietKQKD[[#This Row],[Ngành L1]]="Ngân hàng",IF(AND(INDEX(Sheet4!$2:$1605,MATCH(ChiTietKQKD[[#This Row],[Mã CP]],Sheet4!$B$2:$B$1605,0),_xlfn.XMATCH("*Thu nhập lãi thuần*6 tháng*2026*",Sheet4!$1:$1,2))<>0,INDEX(Sheet4!$2:$1605,MATCH(ChiTietKQKD[[#This Row],[Mã CP]],Sheet4!$B$2:$B$1605,0),_xlfn.XMATCH("*Thu nhập lãi thuần*6 tháng*2025*",Sheet4!$1:$1,2))<>0),INDEX(Sheet4!$2:$1605,MATCH(ChiTietKQKD[[#This Row],[Mã CP]],Sheet4!$B$2:$B$1605,0),_xlfn.XMATCH("*Thu nhập lãi thuần*6 tháng*2026*",Sheet4!$1:$1,2))/INDEX(Sheet4!$2:$1605,MATCH(ChiTietKQKD[[#This Row],[Mã CP]],Sheet4!$B$2:$B$1605,0),_xlfn.XMATCH("*Thu nhập lãi thuần*6 tháng*2025*",Sheet4!$1:$1,2))-1,""),IFERROR(INDEX(Sheet4!$2:$1605,MATCH(ChiTietKQKD[[#This Row],[Mã CP]],Sheet4!$B$2:$B$1605,0),_xlfn.XMATCH("*Tăng trưởng doanh thu thuần (YoY) (6M)*",Sheet4!$1:$1,2)),""))} -> 0 | M1615: {=_xlfn.LET(_xlpm.val,IFERROR(INDEX(Sheet4!$2:$1605,MATCH(ChiTietKQKD[[#This Row],[Mã CP]],Sheet4!$B$2:$B$1605,0),_xlfn.XMATCH("*Lợi nhuận sau thuế*Q2*2026*",Sheet4!$1:$1,2)),0),IF(OR(_xlpm.val="",_xlpm.val=0),"",_xlpm.val/1000000000))} | N1615: {=_xlfn.LET(_xlpm.val,IFERROR(INDEX(Sheet4!$2:$1605,MATCH(ChiTietKQKD[[#This Row],[Mã CP]],Sheet4!$B$2:$B$1605,0),_xlfn.XMATCH("*Lợi nhuận sau thuế*6 tháng*2026*",Sheet4!$1:$1,2)),0),IF(OR(_xlpm.val="",_xlpm.val=0),"",_xlpm.val/1000000000))} | O1615: {=IFERROR(INDEX(Sheet4!$2:$1605,MATCH(ChiTietKQKD[[#This Row],[Mã CP]],Sheet4!$B$2:$B$1605,0),_xlfn.XMATCH("*Tăng trưởng lợi nhuận sau thuế (YoY) (Quý*",Sheet4!$1:$1,2)),"")} -> 0 | P1615: {=IFERROR(INDEX(Sheet4!$2:$1605,MATCH(ChiTietKQKD[[#This Row],[Mã CP]],Sheet4!$B$2:$B$1605,0),_xlfn.XMATCH("*Tăng trưởng lợi nhuận sau thuế (YoY) (6M)*",Sheet4!$1:$1,2)),"")} -> 0 | Q1615: {=IFERROR(INDEX(Sheet4!$2:$1605,MATCH(ChiTietKQKD[[#This Row],[Mã CP]],Sheet4!$B$2:$B$1605,0),_xlfn.XMATCH("*Tăng trưởng doanh thu thuần (QoQ)*",Sheet4!$1:$1,2)),"")} -> 0 | R1615: {=IFERROR(INDEX(Sheet4!$2:$1605,MATCH(ChiTietKQKD[[#This Row],[Mã CP]],Sheet4!$B$2:$B$1605,0),_xlfn.XMATCH("*Tăng trưởng lợi nhuận sau thuế (QoQ)*",Sheet4!$1:$1,2)),"")} -> 0

Sheet Sheet4
A1: STT | B1: Mã | C1: Tên công ty | D1: Sàn | E1: Phân ngành - ICB L1 | F1: Phân ngành - ICB L2 | G1: Phân ngành - ICB L4 | H1: 3. Doanh thu thuần Hợp nhất Quý: Q2 Năm: 2026 Đơn vị: VND | I1: 3. Doanh thu thuần Hợp nhất Quý: 6 tháng Năm: 2026 Đơn vị: VND | J1: Tăng trưởng doanh thu thuần (YoY) (Quý, Năm) Chỉ số TTM Quý: Q2.2026 Đơn vị: % | K1: Tăng trưởng doanh thu thuần (YoY) (6M) Chỉ số TTM Quý: Q2.2026 Đơn vị: % | L1: Tăng trưởng doanh thu thuần (YoY) (9M) Chỉ số TTM Quý: Q2.2026 Đơn vị: % | M1: 32.2. Lợi nhuận sau thuế của chủ sở hữu, tập đoàn Hợp nhất Quý: Q2 Năm: 2026 Đơn vị: VND | N1: 32.2. Lợi nhuận sau thuế của chủ sở hữu, tập đoàn Hợp nhất Quý: 6 tháng Năm: 2026 Đơn vị: VND | O1: 32.2. Lợi nhuận sau thuế của chủ sở hữu, tập đoàn Hợp nhất Quý: 9 tháng Năm: 2026 Đơn vị: VND | P1: Tăng trưởng lợi nhuận sau thuế (YoY) (Quý, Năm) Chỉ số TTM Quý: Q2.2026 Đơn vị: % | Q1: Tăng trưởng lợi nhuận sau thuế (YoY) (6M) Chỉ số TTM Quý: Q2.2026 Đơn vị: % | R1: Tăng trưởng lợi nhuận sau thuế (YoY) (9M) Chỉ số TTM Quý: Q2.2026 Đơn vị: % | S1: Tăng trưởng lợi nhuận sau thuế (QoQ) (Quý) Chỉ số TTM Quý: Q2.2026 Đơn vị: % | T1: 3. Doanh thu thuần Hợp nhất Quý: 9 tháng Năm: 2026 Đơn vị: VND | U1: % Doanh thu kế hoạch Chỉ số TTM Quý: Q2.2026 Đơn vị: % | V1: % LNTT kế hoạch Chỉ số TTM Quý: Q2.2026 Đơn vị: % | W1: % LNST kế hoạch Chỉ số TTM Quý: Q2.2026 Đơn vị: % | X1: Tỷ suất cổ tức (Kế hoạch) Chỉ số TTM Quý: Q2.2026 Đơn vị: % | Y1: 3. Doanh thu thuần Hợp nhất Quý: Hàng năm Năm: 2026 Đơn vị: VND | Z1: Tăng trưởng doanh thu thuần (QoQ) (Quý) Chỉ số TTM Quý: Q2.2026 Đơn vị: % | AA1: 1. Thu nhập lãi thuần Hợp nhất Quý: 2 Năm: 2026 Đơn vị: VND | AB1: 1. Thu nhập lãi thuần Hợp nhất Quý: 6 tháng Năm: 2026 Đơn vị: VND | AC1: 1. Thu nhập lãi thuần Hợp nhất Quý: 9 tháng Năm: 2026 Đơn vị: VND | AD1: Tăng trưởng thu nhập lãi thuần Chỉ số TTM Quý: Q2.2026 Đơn vị: % | AE1: 1. Thu nhập lãi thuần Hợp nhất Quý: Q2 Năm: 2025 Đơn vị: VND | AF1: 1. Thu nhập lãi thuần Hợp nhất Quý: 6 tháng Năm: 2025 Đơn vị: VND | AG1: 1. Thu nhập lãi thuần Hợp nhất Quý: 9 tháng Năm: 2025 Đơn vị: VND | AH1: Vốn hóa thị trường Chỉ số TTM Ngày: 22/07/2026 Đơn vị: VND
A2: 1 | B2: AAA | C2: An Phát Bioplastics | D2: HOSE | E2: Nguyên vật liệu | F2: Hóa chất | G2: Nhựa, cao su & sợi | AH2: 2630201436400
A3: 2 | B3: AAM | C3: Thủy sản Mekong | D3: HOSE | E3: Hàng Tiêu dùng | F3: Thực phẩm và đồ uống | G3: Nuôi trồng nông & hải sản | H3: 16795301860 | I3: 50239306570 | J3: -0.7389 | K3: -0.5767 | L3: -0.6129 | M3: 3390751950 | N3: 5778355722 | P3: 2.0053 | Q3: 1.4728 | R3: 3.8796 | S3: 0.4201 | U3: -0.4976 | V3: 0.4458 | W3: 0.4446 | X3: 0.0458 | Z3: -0.4978 | AD3: 0 | AH3: 68455242100
A4: 3 | B4: AAN | C4: Lương thực A An | D4: HOSE | E4: Hàng Tiêu dùng | F4: Thực phẩm và đồ uống | G4: Nuôi trồng nông & hải sản | AH4: 1388496757650
A5: 4 | B5: AAT | C5: Tập đoàn Tiên Sơn Thanh Hóa | D5: HOSE | E5: Hàng Tiêu dùng | F5: Hàng cá nhân & Gia dụng | G5: Hàng May mặc | AH5: 182713285740
A6: 5 | B6: ABR | C6: Đầu tư Nhãn Hiệu Việt | D6: HOSE | E6: Công nghiệp | F6: Hàng & Dịch vụ Công nghiệp | G6: Tư vấn & Hỗ trợ KD | H6: 6276526317 | I6: 12611617194 | J6: 0.0026 | K6: -0.1103 | L6: -0.037 | M6: 5184127425 | N6: 7554732254 | P6: 0.5608 | Q6: -0.0495 | R6: -0.0971 | S6: 1.1868 | U6: -0.4394 | V6: -0.4503 | W6: -0.4672 | X6: 0 | Z6: -0.0092 | AD6: 0 | AH6: 231000000000
A7: 6 | B7: ABS | C7: DV Nông nghiệp Bình Thuận | D7: HOSE | E7: Nguyên vật liệu | F7: Hóa chất | G7: Sản phẩm hóa dầu, Nông dược & Hóa chất khác | H7: 70347608146 | I7: 113303783645 | J7: 0.9954 | K7: 0.1208 | L7: -0.1889 | M7: -3455274145 | N7: -5196350856 | P7: 0.9882 | Q7: 0.9824 | R7: 0.2545 | S7: -0.9846 | U7: 0 | V7: 0 | W7: 0 | X7: 0 | Z7: 0.6377 | AD7: 0 | AH7: 248000000000
A8: 7 | B8: ABT | C8: Thủy sản Bến Tre | D8: HOSE | E8: Hàng Tiêu dùng | F8: Thực phẩm và đồ uống | G8: Nuôi trồng nông & hải sản | AH8: 588862850000
A9: 8 | B9: ACB | C9: ACB | D9: HOSE | E9: Ngân hàng | F9: Ngân hàng | G9: Ngân hàng | J9: 0.3865 | M9: 4292478000000 | N9: 8612866000000 | P9: -0.1206 | S9: -0.0065 | Z9: 0.1436 | AA9: 7784691000000 | AB9: 14773853000000 | AE9: 6683848000000 | AF9: 13042713000000 | AG9: 19812423000000 | AH9: 130019051836800
A10: 9 | B10: ACC | C10: Đầu tư và XD Bình Dương ACC | D10: HOSE | E10: Công nghiệp | F10: Xây dựng và Vật liệu | G10: Vật liệu xây dựng & Nội thất | AH10: 632099957860
A11: 10 | B11: ACG | C11: Gỗ An Cường | D11: HOSE | E11: Nguyên vật liệu | F11: Tài nguyên Cơ bản | G11: Lâm sản và Chế biến gỗ | AH11: 4840293066600
A12: 11 | B12: ACL | C12: Thủy sản CL An Giang | D12: HOSE | E12: Hàng Tiêu dùng | F12: Thực phẩm và đồ uống | G12: Nuôi trồng nông & hải sản | AH12: 647051345100
A13: 12 | B13: ADG | C13: Clever Group | D13: HOSE | E13: Dịch vụ Tiêu dùng | F13: Truyền thông | G13: Dịch vụ truyền thông | AH13: 173182220100
A14: 13 | B14: ADP | C14: Sơn Á Đông | D14: HOSE | E14: Công nghiệp | F14: Xây dựng và Vật liệu | G14: Vật liệu xây dựng & Nội thất | H14: 146846009252 | I14: 301211000966 | J14: -0.1641 | K14: -0.2 | L14: -0.2318 | M14: 22028350151 | N14: 38653727258 | P14: -0.0252 | Q14: -0.1517 | R14: -0.0712 | S14: 0.3909 | U14: -0.4523 | V14: -0.1354 | W14: -0.1394 | X14: 0 | Z14: -0.0487 | AD14: 0 | AH14: 518396625000
A15: 14 | B15: ADS | C15: Dệt sợi DAMSAN | D15: HOSE | E15: Hàng Tiêu dùng | F15: Hàng cá nhân & Gia dụng | G15: Hàng May mặc | AH15: 584419661550
A16: 15 | B16: AFX | C16: XNK Nông sản Thực phẩm An Giang | D16: HOSE | E16: Dịch vụ Tiêu dùng | F16: Bán lẻ | G16: Phân phối thực phẩm | H16: 704900128999 | I16: 1588916059896 | J16: -0.0118 | K16: 0.5558 | L16: 0.5443 | M16: 8886978834 | N16: 26925026049 | P16: 0.3947 | Q16: 1.4384 | R16: 1.6097 | S16: -0.5073 | U16: -0.5797 | V16: -0.6429 | W16: -0.6435 | X16: 0 | Z16: -0.2026 | AD16: 0 | AH16: 350000000000
A17: 16 | B17: AGG | C17: Bất động sản An Gia | D17: HOSE | E17: Tài chính | F17: Bất động sản | G17: Bất động sản | AH17: 1795935295050
A18: 17 | B18: AGR | C18: Agriseco | D18: HOSE | E18: Tài chính | F18: Dịch vụ tài chính | G18: Môi giới chứng khoán | H18: 139118884076 | I18: 284435444458 | J18: 0.42 | K18: 0.41 | L18: 0.3497 | M18: 30294638128 | N18: 73783489660 | P18: 1.5789 | Q18: 0.6679 | R18: 0.1773 | S18: -0.3034 | U18: -0.5096 | V18: -0.5217 | W18: -0.5246 | X18: 0.0515 | Z18: -0.0426 | AD18: 0 | AH18: 3105040153600
A19: 18 | B19: ANT | C19: Rau quả thực phẩm An Giang | D19: HOSE | E19: Hàng Tiêu dùng | F19: Thực phẩm và đồ uống | G19: Thực phẩm | AH19: 711467420300
A20: 19 | B20: ANV | C20: Thủy sản Nam Việt | D20: HOSE | E20: Hàng Tiêu dùng | F20: Thực phẩm và đồ uống | G20: Nuôi trồng nông & hải sản | H20: 1937045719515 | I20: 3778341837449 | J20: 0.1221 | K20: 0.3339 | L20: 0.4063 | M20: 134869981055 | N20: 330227814705 | P20: -0.5948 | Q20: -0.2896 | R20: 0.2374 | S20: -0.3096 | U20: -0.5093 | V20: -0.6824 | W20: -0.6724 | X20: 0.0875 | Z20: 0.052 | AD20: 0 | AH20: 4566286112500
A21: 20 | B21: APG | C21: Chứng khoán APG | D21: HOSE | E21: Tài chính | F21: Dịch vụ tài chính | G21: Môi giới chứng khoán | H21: 59792334165 | I21: 144766987278 | J21: -0.6293 | K21: -0.2219 | L21: 0.2086 | M21: -3170343941 | N21: 3321029996 | P21: 0.536 | Q21: 0.6711 | R21: 0.5858 | S21: -1.4884 | U21: -0.5174 | V21: -0.8558 | W21: -0.7924 | X21: 0 | Z21: -0.2964 | AD21: 0 | AH21: 995117641900
A22: 21 | B22: APH | C22: Tập đoàn An Phát Holdings | D22: HOSE | E22: Công nghiệp | F22: Hàng & Dịch vụ Công nghiệp | G22: Containers & Đóng gói | AH22: 1295025463080
A23: 22 | B23: ASG | C23: Tập đoàn ASG | D23: HOSE | E23: Công nghiệp | F23: Hàng & Dịch vụ Công nghiệp | G23: Kho bãi, hậu cần và bảo dưỡng | AH23: 1525182439200
A24: 23 | B24: ASM | C24: Tập đoàn Sao Mai | D24: HOSE | E24: Hàng Tiêu dùng | F24: Thực phẩm và đồ uống | G24: Nuôi trồng nông & hải sản | AH24: 2276215482970
A25: 24 | B25: ASP | C25: Dầu khí An Pha | D25: HOSE | E25: Tiện ích Cộng đồng | F25: Điện, nước & xăng dầu khí đốt | G25: Phân phối xăng dầu & khí đốt | AH25: 359579789460
A26: 25 | B26: AST | C26: Dịch vụ Hàng không Taseco | D26: HOSE | E26: Dịch vụ Tiêu dùng | F26: Bán lẻ | G26: Phân phối hàng chuyên dụng | AH26: 3337195612200
A27: 26 | B27: ATP | C27: T.Mại và DV An Thành | D27: HOSE | E27: Hàng Tiêu dùng | F27: Thực phẩm và đồ uống | G27: Nuôi trồng nông & hải sản
A28: 27 | B28: BAF | C28: Nông nghiệp BAF Việt Nam | D28: HOSE | E28: Hàng Tiêu dùng | F28: Thực phẩm và đồ uống | G28: Nuôi trồng nông & hải sản | AH28: 10579922274000
A29: 28 | B29: BCE | C29: XD và GT Bình Dương | D29: HOSE | E29: Công nghiệp | F29: Xây dựng và Vật liệu | G29: Xây dựng | AH29: 235199137600
A30: 29 | B30: BCM | C30: Becamex Group | D30: HOSE | E30: Tài chính | F30: Bất động sản | G30: Bất động sản | AH30: 39226500000000
A31: 30 | B31: BFC | C31: Phân bón Bình Điền | D31: HOSE | E31: Nguyên vật liệu | F31: Hóa chất | G31: Sản phẩm hóa dầu, Nông dược & Hóa chất khác | AH31: 3018470030400
A32: 31 | B32: BHN | C32: HABECO | D32: HOSE | E32: Hàng Tiêu dùng | F32: Thực phẩm và đồ uống | G32: Sản xuất bia | AH32: 6919230000000
A33: 32 | B33: BIC | C33: Bảo hiểm BIDV | D33: HOSE | E33: Tài chính | F33: Bảo hiểm | G33: Bảo hiểm phi nhân thọ | AH33: 4324235019800
A34: 33 | B34: BID | C34: BIDV | D34: HOSE | E34: Ngân hàng | F34: Ngân hàng | G34: Ngân hàng | AE34: 14991731000000 | AF34: 28937315000000 | AG34: 44109933000000 | AH34: 260990337778500
A35: 34 | B35: BKG | C35: Đầu tư BKG Việt Nam | D35: HOSE | E35: Hàng Tiêu dùng | F35: Hàng cá nhân & Gia dụng | G35: Thiết bị gia dụng | AH35: 156823753800
A36: 35 | B36: BMC | C36: Khoáng sản Bình Định | D36: HOSE | E36: Nguyên vật liệu | F36: Tài nguyên Cơ bản | G36: Khai khoáng | H36: 21535499033 | I36: 45144054285 | J36: -0.4473 | K36: -0.1078 | L36: -0.3248 | M36: 693326220 | N36: 2175304748 | P36: -0.8163 | Q36: -0.5344 | R36: -0.6219 | S36: -0.5322 | U36: 0 | V36: 0 | W36: 0 | X36: 0 | Z36: -0.0878 | AD36: 0 | AH36: 143754508000
A37: 36 | B37: BMI | C37: Bảo hiểm Bảo Minh | D37: HOSE | E37: Tài chính | F37: Bảo hiểm | G37: Bảo hiểm phi nhân thọ | AH37: 2002283425800
A38: 37 | B38: BMP | C38: Nhựa Bình Minh | D38: HOSE | E38: Công nghiệp | F38: Xây dựng và Vật liệu | G38: Vật liệu xây dựng & Nội thất | H38: 1319560280244 | I38: 2776871246182 | J38: 0.0087 | K38: 0.0318 | L38: 0.0852 | M38: 367189104893 | N38: 671145164647 | P38: 0.113 | Q38: 0.0881 | R38: 0.0999 | S38: 0.208 | U38: -0.5412 | V38: -0.4748 | W38: -0.4748 | X38: 0.0517 | Z38: -0.0945 | AD38: 0 | AH38: 12361001638000
A39: 38 | B39: BRC | C39: Cao su Bến Thành | D39: HOSE | E39: Nguyên vật liệu | F39: Hóa chất | G39: Nhựa, cao su & sợi | H39: 103742133765 | I39: 198992933659 | J39: -0.0936 | K39: -0.0631 | L39: -0.0558 | M39: 7270987671 | N39: 11917519007 | P39: 0.1372 | Q39: 0.1245 | R39: 0.1334 | S39: 0.5648 | U39: -0.5171 | V39: -0.436 | W39: -0.4381 | X39: 0.0833 | Z39: 0.0891 | AD39: 0 | AH39: 148499964000
A40: 39 | B40: BSI | C40: Chứng khoán BIDV | D40: HOSE | E40: Tài chính | F40: Dịch vụ tài chính | G40: Môi giới chứng khoán | H40: 616834996675 | I40: 1313975770450 | J40: 0.218 | K40: 0.5576 | L40: 0.6174 | M40: 123215863134 | N40: 212034920024 | P40: 0.2092 | Q40: 0.1586 | R40: 0.1201 | S40: 0.3873 | U40: 0 | V40: -0.6244 | W40: -0.6214 | X40: 0.0345 | Z40: -0.1152 | AD40: 0 | AH40: 7827144921000
A41: 40 | B41: BSR | C41: Lọc Hoá dầu Việt Nam | D41: HOSE | E41: Dầu khí | F41: Dầu khí | G41: Sản xuất và Khai thác dầu khí | AH41: 115167892778000
A42: 41 | B42: BTP | C42: Nhiệt điện Bà Rịa | D42: HOSE | E42: Tiện ích Cộng đồng | F42: Điện, nước & xăng dầu khí đốt | G42: Sản xuất & Phân phối Điện | H42: 82178523874 | I42: 136959196687 | J42: 0.2374 | K42: 0.1103 | L42: 0.0345 | M42: 7394569107 | N42: 33307636686 | P42: 70.6551 | Q42: 2.1245 | R42: 0.3669 | S42: -0.7146 | U42: -0.6831 | V42: -0.134 | W42: -0.0495 | X42: 0.0256 | Z42: 0.5001 | AD42: 0 | AH42: 471787680000
A43: 42 | B43: BTT | C43: TM - DV Bến Thành | D43: HOSE | E43: Dịch vụ Tiêu dùng | F43: Bán lẻ | G43: Bán lẻ phức hợp | AH43: 573750000000
A44: 43 | B44: BVB | C44: Ngân hàng Bản Việt - BVBank | D44: HOSE | E44: Ngân hàng | F44: Ngân hàng | G44: Ngân hàng | AE44: 643806000000 | AF44: 1148597000000 | AG44: 1865339000000 | AH44: 8522906000000
A45: 44 | B45: BVH | C45: Tập đoàn Bảo Việt | D45: HOSE | E45: Tài chính | F45: Bảo hiểm | G45: Bảo hiểm nhân thọ | AH45: 42386629824400
A46: 45 | B46: BWE | C46: Nước - Môi trường Bình Dương | D46: HOSE | E46: Tiện ích Cộng đồng | F46: Điện, nước & xăng dầu khí đốt | G46: Nước | AH46: 9830810386800
A47: 46 | B47: C32 | C47: Đầu tư và Xây dựng 3-2 | D47: HOSE | E47: Công nghiệp | F47: Xây dựng và Vật liệu | G47: Vật liệu xây dựng & Nội thất | AH47: 495961785000
A48: 47 | B48: C47 | C48: Xây dựng 47 | D48: HOSE | E48: Công nghiệp | F48: Xây dựng và Vật liệu | G48: Xây dựng | AH48: 327080421000
A49: 48 | B49: CCC | C49: Xây Dựng CDC | D49: HOSE | E49: Công nghiệp | F49: Xây dựng và Vật liệu | G49: Xây dựng | AH49: 299290855230
A50: 49 | B50: CCI | C50: CIDICO | D50: HOSE | E50: Tiện ích Cộng đồng | F50: Điện, nước & xăng dầu khí đốt | G50: Phân phối xăng dầu & khí đốt | H50: 123237126364 | I50: 225284171905 | J50: 0.281 | K50: 0.1968 | L50: 0.1219 | M50: 13130546352 | N50: 27785230554 | P50: -0.3594 | Q50: -0.2272 | R50: -0.1458 | S50: -0.104 | U50: -0.4814 | V50: -0.3008 | W50: -0.298 | X50: 0.0647 | Z50: 0.2077 | AD50: 0 | AH50: 397598380000
A51: 50 | B51: CCL | C51: ĐT & PT Đô thị Dầu khí Cửu Long | D51: HOSE | E51: Tài chính | F51: Bất động sản | G51: Bất động sản | H51: 65492489391 | I51: 134797125372 | J51: -0.5033 | K51: -0.3233 | L51: -0.3486 | M51: 543694145 | N51: 8758243662 | P51: -0.9555 | Q51: -0.665 | R51: -0.8698 | S51: -0.9338 | U51: -0.5507 | V51: -0.708 | W51: -0.7081 | X51: 0.1282 | Z51: -0.055 | AD51: 0 | AH51: 255599303700
A52: 51 | B52: CDC | C52: Chương Dương Corp | D52: HOSE | E52: Công nghiệp | F52: Xây dựng và Vật liệu | G52: Xây dựng | AH52: 1942033924800
A53: 52 | B53: CHP | C53: Thủy điện Miền Trung | D53: HOSE | E53: Tiện ích Cộng đồng | F53: Điện, nước & xăng dầu khí đốt | G53: Sản xuất & Phân phối Điện | H53: 123466741315 | I53: 321969666714 | J53: -0.4783 | K53: -0.3161 | L53: -0.2048 | M53: 27891554090 | N53: 118723963420 | P53: -0.7338 | Q53: -0.4715 | R53: -0.3338 | S53: -0.6929 | U53: -0.5552 | V53: -0.5064 | W53: -0.5062 | X53: 0.0659 | Z53: -0.378 | AD53: 0 | AH53: 4304065474800
A54: 53 | B54: CIG | C54: Xây dựng COMA 18 | D54: HOSE | E54: Công nghiệp | F54: Xây dựng và Vật liệu | G54: Xây dựng | AH54: 353706832710
A55: 54 | B55: CII | C55: Hạ tầng Kỹ thuật TP.HCM | D55: HOSE | E55: Công nghiệp | F55: Xây dựng và Vật liệu | G55: Xây dựng | AH55: 9374194809450
A56: 55 | B56: CKG | C56: Tập đoàn CIC | D56: HOSE | E56: Tài chính | F56: Bất động sản | G56: Bất động sản | AH56: 991880134380
A57: 56 | B57: CLC | C57: Thuốc lá Cát Lợi | D57: HOSE | E57: Hàng Tiêu dùng | F57: Hàng cá nhân & Gia dụng | G57: Thuốc lá | H57: 1147367988112 | I57: 2181227374950 | J57: 0.07 | K57: 0.0772 | L57: 0.0971 | M57: 61496916575 | N57: 96910648074 | P57: 0.6305 | Q57: 0.2367 | R57: 0.4149 | S57: 0.7365 | U57: -0.4364 | V57: -0.4733 | W57: -0.4733 | X57: 0.08 | Z57: 0.1098 | AD57: 0 | AH57: 1310379150000
A58: 57 | B58: CLL | C58: Cảng Cát Lái | D58: HOSE | E58: Công nghiệp | F58: Hàng & Dịch vụ Công nghiệp | G58: Kho bãi, hậu cần và bảo dưỡng | AH58: 1021700000000
A59: 58 | B59: CLW | C59: Cấp nước Chợ Lớn | D59: HOSE | E59: Tiện ích Cộng đồng | F59: Điện, nước & xăng dầu khí đốt | G59: Nước | H59: 325327419153 | I59: 630589223964 | J59: -0.0157 | K59: -0.008 | L59: 0.0017 | M59: 20905372626 | N59: 34751656782 | P59: 0.1847 | Q59: 0.1732 | R59: 0.4892 | S59: 0.5098 | U59: -0.5092 | V59: -0.3976 | W59: -0.3959 | X59: 0.0415 | Z59: 0.0657 | AD59: 0 | AH59: 501150000000
A60: 59 | B60: CMG | C60: Tập đoàn Công nghệ CMC | D60: HOSE | E60: Công nghệ Thông tin | F60: Công nghệ Thông tin | G60: Dịch vụ Máy tính | AH60: 5543041610400
A61: 60 | B61: CMV | C61: Thương nghiệp Cà Mau | D61: HOSE | E61: Dịch vụ Tiêu dùng | F61: Bán lẻ | G61: Bán lẻ phức hợp | AH61: 144339150600
A62: 61 | B62: CMX | C62: CAMIMEX Group | D62: HOSE | E62: Hàng Tiêu dùng | F62: Thực phẩm và đồ uống | G62: Nuôi trồng nông & hải sản | AH62: 506437980300
A63: 62 | B63: CNG | C63: CNG Việt Nam | D63: HOSE | E63: Tiện ích Cộng đồng | F63: Điện, nước & xăng dầu khí đốt | G63: Phân phối xăng dầu & khí đốt | H63: 1835777275155 | I63: 3027457537193 | J63: 0.6763 | K63: 0.5562 | L63: 0.5314 | M63: 43684992351 | N63: 48067779866 | P63: 0.1756 | Q63: 0.2485 | R63: -0.075 | S63: 8.9674 | U63: -0.4256 | V63: -0.332 | W63: -0.3324 | X63: 0 | Z63: 0.5405 | AD63: 0 | AH63: 730065398400
A64: 63 | B64: COM | C64: Vật tư - Xăng dầu | D64: HOSE | E64: Dịch vụ Tiêu dùng | F64: Bán lẻ | G64: Phân phối hàng chuyên dụng | H64: 1367731851289 | I64: 2390387068249 | J64: 0.5812 | K64: 0.3505 | L64: 0.2263 | M64: 18655779012 | N64: 23092696480 | P64: 4.4334 | Q64: 2.8411 | R64: 1.2771 | S64: 3.2047 | U64: -0.317 | V64: 0.5305 | W64: 0.5395 | X64: 0.0304 | Z64: 0.3374 | AD64: 0 | AH64: 464568661200
A65: 64 | B65: CRC | C65: Create Capital Việt Nam | D65: HOSE | E65: Công nghiệp | F65: Xây dựng và Vật liệu | G65: Vật liệu xây dựng & Nội thất | AH65: 636998546280
A66: 65 | B66: CRE | C66: Bất động sản Thế Kỷ | D66: HOSE | E66: Tài chính | F66: Bất động sản | G66: Bất động sản | AH66: 2990725847700
A67: 66 | B67: CRV | C67: Tập đoàn Bất động sản CRV | D67: HOSE | E67: Tài chính | F67: Bất động sản | G67: Bất động sản | AH67: 17528696812500
A68: 67 | B68: CSM | C68: Cao su Miền Nam | D68: HOSE | E68: Hàng Tiêu dùng | F68: Ô tô và phụ tùng | G68: Lốp xe | H68: 1148202586665 | I68: 2253484117304 | J68: 0.0382 | K68: 0.0593 | L68: -0.0236 | M68: 22912272115 | N68: 48933639810 | P68: 0.4763 | Q68: 0.4001 | R68: -0.3121 | S68: -0.1195 | U68: -0.5616 | V68: -0.4987 | W68: -0.4906 | X68: 0 | Z68: 0.0388 | AD68: 0 | AH68: 1461116194200
A69: 68 | B69: CSV | C69: Hóa chất Cơ bản miền Nam | D69: HOSE | E69: Nguyên vật liệu | F69: Hóa chất | G69: Sản phẩm hóa dầu, Nông dược & Hóa chất khác | H69: 687299504698 | I69: 1315610349372 | J69: 0.3127 | K69: 0.3077 | L69: 0.2874 | M69: 129839514307 | N69: 172725558880 | P69: 1.0728 | Q69: 0.5016 | R69: 0.2481 | S69: 2.0275 | U69: -0.3747 | V69: 253.9257 | W69: 240.7771 | X69: 0 | Z69: 0.0939 | AD69: 0 | AH69: 2392323051500
A70: 69 | B70: CTD | C70: Xây dựng Coteccons | D70: HOSE | E70: Công nghiệp | F70: Xây dựng và Vật liệu | G70: Xây dựng | AH70: 6262100320000
A71: 70 | B71: CTF | C71: City Auto | D71: HOSE | E71: Hàng Tiêu dùng | F71: Ô tô và phụ tùng | G71: Sản xuất ô tô | AH71: 1616550217100
A72: 71 | B72: CTG | C72: VietinBank | D72: HOSE | E72: Ngân hàng | F72: Ngân hàng | G72: Ngân hàng | AE72: 15842616000000 | AF72: 31317831000000 | AG72: 48493549000000 | AH72: 230678255718900
A73: 72 | B73: CTI | C73: Cường Thuận IDICO | D73: HOSE | E73: Công nghiệp | F73: Xây dựng và Vật liệu | G73: Xây dựng | AH73: 1171799944200
A74: 73 | B74: CTR | C74: Công trình Viettel | D74: HOSE | E74: Công nghiệp | F74: Xây dựng và Vật liệu | G74: Xây dựng | AH74: 8506472991200
A75: 74 | B75: CTS | C75: Chứng khoán Vietinbank | D75: HOSE | E75: Tài chính | F75: Dịch vụ tài chính | G75: Môi giới chứng khoán | H75: 357099001625 | I75: 709024779575 | J75: -0.3825 | K75: -0.3202 | L75: -0.0572 | M75: 15436425569 | N75: 81280190225 | P75: -0.9122 | Q75: -0.7115 | R75: -0.6869 | S75: -0.7656 | U75: 0 | V75: -0.7782 | W75: -0.7762 | X75: 0.0393 | Z75: 0.0147 | AD75: 0 | AH75: 6234409103100
A76: 75 | B76: CVT | C76: CMC JSC | D76: HOSE | E76: Công nghiệp | F76: Xây dựng và Vật liệu | G76: Vật liệu xây dựng & Nội thất | AH76: 981481227250
A77: 76 | B77: D2D | C77: Phát triển Đô thị số 2 | D77: HOSE | E77: Tài chính | F77: Bất động sản | G77: Bất động sản | H77: 41590751151 | J77: -0.9246 | K77: -0.8668 | L77: -0.8664 | M77: 2530433014 | P77: -0.9878 | Q77: -0.9636 | R77: -0.9533 | S77: -0.522 | U77: -0.8558 | V77: -0.9579 | W77: -0.9592 | X77: 0.0768 | Z77: -0.0575 | AD77: 0 | AH77: 788266279100
A78: 77 | B78: DAH | C78: Tập đoàn Khách sạn Đông Á | D78: HOSE | E78: Dịch vụ Tiêu dùng | F78: Du lịch và Giải trí | G78: Khách sạn | H78: 12292729189 | I78: 22096274169 | J78: -0.0959 | K78: -0.111 | L78: 0.0087 | M78: 1463271980 | N78: 391425380 | P78: 2.5154 | Q78: 1.1055 | R78: -23.2991 | S78: 2.3652 | U78: -0.5581 | V78: -0.9272 | W78: -0.909 | X78: 0 | Z78: 0.2539 | AD78: 0 | AH78: 224814000000
A79: 78 | B79: DAT | C79: ĐT Du lịch và PT Thủy sản | D79: HOSE | E79: Hàng Tiêu dùng | F79: Thực phẩm và đồ uống | G79: Nuôi trồng nông & hải sản | H79: 993420325979 | I79: 1635356205501 | J79: 0.3864 | K79: 0.2602 | L79: 0.1821 | M79: 40182399353 | N79: 58544598275 | P79: 1.4262 | Q79: 0.9576 | R79: 0.8739 | S79: 1.1883 | U79: -0.371 | V79: -0.2428 | W79: -0.1636 | X79: 0 | Z79: 0.5475 | AD79: 0 | AH79: 547596177310
A80: 79 | B80: DBC | C80: Tập đoàn DABACO | D80: HOSE | E80: Hàng Tiêu dùng | F80: Thực phẩm và đồ uống | G80: Nuôi trồng nông & hải sản | AH80: 6896743984000
A81: 80 | B81: DBD | C81: Dược - TB Y tế Bình Định | D81: HOSE | E81: Dược phẩm và Y tế | F81: Y tế | G81: Dược phẩm | AH81: 4620524911800
A82: 81 | B82: DBT | C82: Dược phẩm Bến Tre | D82: HOSE | E82: Dược phẩm và Y tế | F82: Y tế | G82: Dược phẩm | AH82: 274590775000
A83: 82 | B83: DC4 | C83: Dicera Holdings | D83: HOSE | E83: Công nghiệp | F83: Xây dựng và Vật liệu | G83: Xây dựng | AH83: 702381335500
A84: 83 | B84: DCL | C84: Dược phẩm Cửu Long | D84: HOSE | E84: Dược phẩm và Y tế | F84: Y tế | G84: Dược phẩm | AH84: 2782863243000
A85: 84 | B85: DCM | C85: Đạm Cà Mau | D85: HOSE | E85: Nguyên vật liệu | F85: Hóa chất | G85: Sản phẩm hóa dầu, Nông dược & Hóa chất khác | AH85: 15299660000000
A86: 85 | B86: DGC | C86: Hóa chất Đức Giang | D86: HOSE | E86: Nguyên vật liệu | F86: Hóa chất | G86: Sản phẩm hóa dầu, Nông dược & Hóa chất khác | H86: 2415414034358 | I86: 4540004805000 | J86: -0.1655 | M86: 388553679077 | N86: 797377231792 | P86: -0.5387 | S86: -0.0496 | Z86: 0.1369 | AH86: 15381025726500
A87: 86 | B87: DGW | C87: Thế Giới Số | D87: HOSE | E87: Dịch vụ Tiêu dùng | F87: Bán lẻ | G87: Phân phối hàng chuyên dụng | AH87: 7607938400000
A88: 87 | B88: DHA | C88: Hóa An | D88: HOSE | E88: Công nghiệp | F88: Xây dựng và Vật liệu | G88: Vật liệu xây dựng & Nội thất | AH88: 700723074800
A89: 88 | B89: DHC | C89: Đông Hải Bến Tre | D89: HOSE | E89: Nguyên vật liệu | F89: Tài nguyên Cơ bản | G89: Sản xuất giấy | AH89: 3091863942000
A90: 89 | B90: DHG | C90: Dược Hậu Giang | D90: HOSE | E90: Dược phẩm và Y tế | F90: Y tế | G90: Dược phẩm | H90: 1363150471725 | I90: 2561250654513 | J90: 0.1511 | K90: 0.0767 | L90: 0.1215 | M90: 298667559205 | N90: 614344840477 | P90: 0.2608 | Q90: 0.221 | R90: 0.0643 | S90: -0.0539 | U90: -0.5368 | V90: -0.2994 | W90: -0.2374 | X90: 0.0769 | Z90: 0.1378 | AD90: 0 | AH90: 11897892461000
A91: 90 | B91: DHM | C91: Đầu tư và Thương mại DHM | D91: HOSE | E91: Nguyên vật liệu | F91: Tài nguyên Cơ bản | G91: Khai khoáng | H91: 861025726302 | I91: 1943381515537 | J91: 0.5558 | K91: 0.969 | L91: 0.757 | M91: -1903548308 | N91: 104765861 | P91: 0.5464 | Q91: 1.033 | R91: 2.0679 | S91: -1.9478 | U91: -0.4232 | V91: -0.9402 | W91: -0.984 | X91: 0 | Z91: -0.2045 | AD91: 0 | AH91: 221719187580
A92: 91 | B92: DIG | C92: DIC Corp | D92: HOSE | E92: Tài chính | F92: Bất động sản | G92: Bất động sản | AH92: 8760743101000
A93: 92 | B93: DLG | C93: Đức Long Gia Lai | D93: HOSE | E93: Công nghiệp | F93: Xây dựng và Vật liệu | G93: Xây dựng | AH93: 667460675600
A94: 93 | B94: DMC | C94: Dược phẩm DOMESCO | D94: HOSE | E94: Dược phẩm và Y tế | F94: Y tế | G94: Dược phẩm | H94: 519176682326 | I94: 1038767030113 | J94: 0.0174 | K94: 0.0606 | L94: 0.0309 | M94: 56531790067 | N94: 109460491736 | P94: 0.7826 | Q94: 0.3901 | R94: 0.2905 | S94: 0.0681 | U94: -0.53 | V94: -0.5152 | W94: -0.5153 | X94: 0.0427 | Z94: -0.0008 | AD94: 0 | AH94: 2035029449000
A95: 94 | B95: DMX | C95: Đầu tư Điện máy Xanh | D95: HOSE | E95: Dịch vụ Tiêu dùng | F95: Bán lẻ | G95: Bán lẻ phức hợp
A96: 95 | B96: DPG | C96: Tập đoàn Đạt Phương | D96: HOSE | E96: Công nghiệp | F96: Xây dựng và Vật liệu | G96: Xây dựng | AH96: 3184063527600
A97: 96 | B97: DPM | C97: Tổng Công ty Phân bón và Hóa chất Dầu khí | D97: HOSE | E97: Nguyên vật liệu | F97: Hóa chất | G97: Sản phẩm hóa dầu, Nông dược & Hóa chất khác | AH97: 14992346713050
A98: 97 | B98: DPR | C98: Cao su Đồng Phú | D98: HOSE | E98: Nguyên vật liệu | F98: Hóa chất | G98: Nhựa, cao su & sợi | AH98: 3119204958800
A99: 98 | B99: DQC | C99: Tập đoàn Điện Quang | D99: HOSE | E99: Hàng Tiêu dùng | F99: Hàng cá nhân & Gia dụng | G99: Thiết bị gia dụng | AH99: 274202756700
A100: 99 | B100: DRC | C100: Cao su Đà Nẵng | D100: HOSE | E100: Hàng Tiêu dùng | F100: Ô tô và phụ tùng | G100: Lốp xe | H100: 1175876270051 | I100: 2330737731327 | J100: -0.1462 | K100: -0.0885 | L100: -0.0359 | M100: 31700962731 | N100: 47916258100 | P100: -0.0114 | Q100: 0.1535 | R100: -0.1577 | S100: 0.955 | U100: -0.5838 | V100: -0.6282 | W100: -0.6136 | X100: 0 | Z100: 0.0182 | AD100: 0 | AH100: 1559735758300
...
